Workbook
Name Module1.PrintMacro: [1]!Module1.PrintMacro
Name Module1.PrintMacro: [1]!Module1.PrintMacro
Name MultiSort: [2]!MultiSort
Name MultiSort: [2]!MultiSort
Name PrintMacro: [3]!PrintMacro
Name PrintMacro: [3]!PrintMacro
Name ValidateChangeInDialogSelection: SFG_DDS!ValidateChangeInDialogSelection
Name ValidateChangeInDialogSelection: 'SFG_DDS 24'!ValidateChangeInDialogSelection
Name ValidateChangeInDialogSelection: [4]!ValidateChangeInDialogSelection

Sheet Inbound_Monitor
A1: Auto | B1: Ursprüngliches geplantes Ankunftsdatum E-Mail | C1: Lieferdatum Update | D1: Auto | E1: Ist Datum (Tatsächliche Anlieferung) | F1: Reihenfolge pro Ist Datum | G1: Auto | H1: SCI | I1: Source Location/ Spedition | J1: Purchase Order/Sales Order Nummer | K1: Anzahl Pal./Box | L1: Category | M1: Status | N1: Echtzeit vom Büro | O1: Echtzeit vom Büro | P1: Echtzeit vom Büro | Q1: Echtzeit vom Büro | R1: SAP Buchung erfolgt? | S1: Bemerkungen | T1: Dauer der Klärung | U1: Probleme | V1: Auto | W1: Auto | X1: Auto | Y1: Auto
A2: KW IB Plan | D2: KW IB Ist | G2: Timeslot getroffen (auto) | N2: Ankunft Office | O2: Entladung gestartet | P2: Entladung beendet | Q2: Unloaded at Bayreuth (Documents finished) | V2: Wartezeit bis Entladebeginn | W2: Entladezeit | X2: Gesamtzeit 1 | Y2: Gesamtzeit 2
A3: nn | B3: dd.mm.yy | C3: dd.mm.yy | D3: nn | E3: dd.mm.yy | G3: Ja/Nein | H3: 1000xx | I3: Text | J3: No. | L3: Auswahl | M3: Auswahl | N3: hh:mm | O3: hh:mm | P3: hh:mm | Q3: hh:mm | R3: Yes / No | S3: Freitext | T3: Datum | U3: Grund | V3: hh:mm | W3: hh:mm | X3: hh:mm | Y3: hh:mm
A4: =IF(B4="","",WEEKNUM(B4,21)) -> 50 | B4: 45275 | C4: 45303 | D4: =IF(E4="","",WEEKNUM(E4,21)) -> 2 | E4: 45303 | G4: =IF(E4="","",IF(E4=B4,"Ja","Nein")) -> Nein | H4: 1000449201 | I4: Augustow | J4: 4702114236 | K4: 94 | L4: STEM | M4: Entladen | N4: 0.27430556 | O4: 0.28819444 | P4: 0.30555556 | Q4: 0.30555556 | V4: =IF(N4="","",IF(O4="","",O4-N4)) -> 0.013888889 | W4: =IF(O4="","",IF(P4="","",P4-O4)) -> 0.017361111 | X4: =IF(P4="","",IF(N4="","",P4-N4)) -> 0.03125 | Y4: =IF(N4="","",IF(Q4="","",Q4-N4)) -> 0.03125
A5: =IF(B5="","",WEEKNUM(B5,21)) -> 51 | B5: 45278 | C5: 45307 | D5: =IF(E5="","",WEEKNUM(E5,21)) -> 3 | E5: 45308 | F5: 2 | G5: =IF(E5="","",IF(E5=B5,"Ja","Nein")) -> Nein | H5: 1000451102 | I5: Kroatien | J5: 4601391876 | K5: 100 | L5: Leaf | M5: Entladen | N5: 0.34097222 | O5: 0.45833333 | P5: 0.48888889 | Q5: 0.49583333 | R5: Yes | S5: Fahrer kam zu spät, wird am 17.01. abgeladen | V5: =IF(N5="","",IF(O5="","",O5-N5)) -> 0.11736111 | W5: =IF(O5="","",IF(P5="","",P5-O5)) -> 0.030555556 | X5: =IF(P5="","",IF(N5="","",P5-N5)) -> 0.14791667 | Y5: =IF(N5="","",IF(Q5="","",Q5-N5)) -> 0.15486111
A6: =IF(B6="","",WEEKNUM(B6,21)) -> 2 | B6: 45300 | D6: =IF(E6="","",WEEKNUM(E6,21)) -> 2 | E6: 45300 | G6: =IF(E6="","",IF(E6=B6,"Ja","Nein")) -> Ja | I6: Türkei | J6: 158807_1 | K6: 50 | L6: IBC | M6: Entladen | N6: 0.36666667 | O6: 0.39583333 | P6: 0.41666667 | Q6: 0.41666667 | V6: =IF(N6="","",IF(O6="","",O6-N6)) -> 0.029166667 | W6: =IF(O6="","",IF(P6="","",P6-O6)) -> 0.020833333 | X6: =IF(P6="","",IF(N6="","",P6-N6)) -> 0.05 | Y6: =IF(N6="","",IF(Q6="","",Q6-N6)) -> 0.05
A7: =IF(B7="","",WEEKNUM(B7,21)) -> 2 | B7: 45300 | D7: =IF(E7="","",WEEKNUM(E7,21)) -> 2 | E7: 45300 | G7: =IF(E7="","",IF(E7=B7,"Ja","Nein")) -> Ja | I7: Türkei | J7: 158807_2 | K7: 50 | L7: IBC | M7: Entladen | N7: 0.41458333 | O7: 0.42361111 | P7: 0.44791667 | Q7: 0.44791667 | V7: =IF(N7="","",IF(O7="","",O7-N7)) -> 0.0090277778 | W7: =IF(O7="","",IF(P7="","",P7-O7)) -> 0.024305556 | X7: =IF(P7="","",IF(N7="","",P7-N7)) -> 0.033333333 | Y7: =IF(N7="","",IF(Q7="","",Q7-N7)) -> 0.033333333
A8: =IF(B8="","",WEEKNUM(B8,21)) -> 2 | B8: 45300 | D8: =IF(E8="","",WEEKNUM(E8,21)) -> 2 | E8: 45300 | G8: =IF(E8="","",IF(E8=B8,"Ja","Nein")) -> Ja | I8: Türkei | J8: 158807_3 | K8: 50 | L8: IBC | M8: Entladen | N8: 0.50486111 | O8: 0.52083333 | P8: 0.54166667 | Q8: 0.54166667 | V8: =IF(N8="","",IF(O8="","",O8-N8)) -> 0.015972222 | W8: =IF(O8="","",IF(P8="","",P8-O8)) -> 0.020833333 | X8: =IF(P8="","",IF(N8="","",P8-N8)) -> 0.036805556 | Y8: =IF(N8="","",IF(Q8="","",Q8-N8)) -> 0.036805556
A9: =IF(B9="","",WEEKNUM(B9,21)) -> 2 | B9: 45301 | D9: =IF(E9="","",WEEKNUM(E9,21)) -> 2 | E9: 45301 | F9: 1 | G9: =IF(E9="","",IF(E9=B9,"Ja","Nein")) -> Ja | H9: 1000447751 | I9: Antwerpen | J9: 125978 | K9: 105 | L9: Leaf | M9: Entladen | N9: 0.37222222 | O9: 0.3875 | P9: 0.40902778 | Q9: 0.45833333 | R9: Yes | S9: muss auch verladen werden | V9: =IF(N9="","",IF(O9="","",O9-N9)) -> 0.015277778 | W9: =IF(O9="","",IF(P9="","",P9-O9)) -> 0.021527778 | X9: =IF(P9="","",IF(N9="","",P9-N9)) -> 0.036805556 | Y9: =IF(N9="","",IF(Q9="","",Q9-N9)) -> 0.086111111
A10: =IF(B10="","",WEEKNUM(B10,21)) -> 2 | B10: 45301 | D10: =IF(E10="","",WEEKNUM(E10,21)) -> 2 | E10: 45301 | F10: 2 | G10: =IF(E10="","",IF(E10=B10,"Ja","Nein")) -> Ja | H10: 1000447754 | I10: Antwerpen | J10: 125981 | K10: 105 | L10: Leaf | M10: Entladen | N10: 0.3875 | O10: 0.44444444 | P10: 0.47777778 | Q10: 0.59444444 | R10: Yes | S10: muss auch verladen werden | T10: 45306 | U10: Für T1-Ware existiert keine PO, da Preise fehlen. Zollanmeldung und WE-Buchung kann erst erfolgen, wenn Inbound vorhanden. | V10: =IF(N10="","",IF(O10="","",O10-N10)) -> 0.056944444 | W10: =IF(O10="","",IF(P10="","",P10-O10)) -> 0.033333333 | X10: =IF(P10="","",IF(N10="","",P10-N10)) -> 0.090277778 | Y10: =IF(N10="","",IF(Q10="","",Q10-N10)) -> 0.20694444
A11: =IF(B11="","",WEEKNUM(B11,21)) -> 2 | B11: 45301 | C11: 45308 | D11: =IF(E11="","",WEEKNUM(E11,21)) -> 3 | E11: 45309 | F11: 2 | G11: =IF(E11="","",IF(E11=B11,"Ja","Nein")) -> Nein | H11: 1000451497 | I11: Kroatien | J11: 4601387585 | K11: 108 | L11: Leaf | M11: Entladen | N11: 0.45277778 | O11: 0.48611111 | P11: 0.51388889 | Q11: 0.52291667 | R11: Yes | S11: Kapazität von 6 St. erreicht, wird am 18.01. abgeladen | V11: =IF(N11="","",IF(O11="","",O11-N11)) -> 0.033333333 | W11: =IF(O11="","",IF(P11="","",P11-O11)) -> 0.027777778 | X11: =IF(P11="","",IF(N11="","",P11-N11)) -> 0.061111111 | Y11: =IF(N11="","",IF(Q11="","",Q11-N11)) -> 0.070138889
A12: =IF(B12="","",WEEKNUM(B12,21)) -> 2 | B12: 45301 | D12: =IF(E12="","",WEEKNUM(E12,21)) -> 2 | E12: 45301 | F12: 3 | G12: =IF(E12="","",IF(E12=B12,"Ja","Nein")) -> Ja | H12: 1000449464 | I12: Kroatien | J12: 4601387586 | K12: 108 | L12: Leaf | M12: Entladen | N12: 0.52222222 | O12: 0.53472222 | P12: 0.55555556 | Q12: 0.56736111 | R12: Yes | V12: =IF(N12="","",IF(O12="","",O12-N12)) -> 0.0125 | W12: =IF(O12="","",IF(P12="","",P12-O12)) -> 0.020833333 | X12: =IF(P12="","",IF(N12="","",P12-N12)) -> 0.033333333 | Y12: =IF(N12="","",IF(Q12="","",Q12-N12)) -> 0.045138889
A13: =IF(B13="","",WEEKNUM(B13,21)) -> 2 | B13: 45301 | D13: =IF(E13="","",WEEKNUM(E13,21)) -> 2 | E13: 45301 | G13: =IF(E13="","",IF(E13=B13,"Ja","Nein")) -> Ja | I13: Fehrbellin | J13: 4500545501 | K13: 32 | L13: Rohware | M13: Entladen | N13: 0.31805556 | O13: 0.33333333 | P13: 0.375 | Q13: 0.375 | V13: =IF(N13="","",IF(O13="","",O13-N13)) -> 0.015277778 | W13: =IF(O13="","",IF(P13="","",P13-O13)) -> 0.041666667 | X13: =IF(P13="","",IF(N13="","",P13-N13)) -> 0.056944444 | Y13: =IF(N13="","",IF(Q13="","",Q13-N13)) -> 0.056944444
A14: =IF(B14="","",WEEKNUM(B14,21)) -> 2 | B14: 45302 | D14: =IF(E14="","",WEEKNUM(E14,21)) -> 2 | E14: 45303 | F14: 1 | G14: =IF(E14="","",IF(E14=B14,"Ja","Nein")) -> Nein | H14: 1000450230 | I14: Kroatien | J14: 4601395602 | K14: 105 | L14: Leaf | M14: Entladen | N14: 0.31527778 | O14: 0.33333333 | P14: 0.36458333 | Q14: 0.37777778 | R14: Yes | V14: =IF(N14="","",IF(O14="","",O14-N14)) -> 0.018055556 | W14: =IF(O14="","",IF(P14="","",P14-O14)) -> 0.03125 | X14: =IF(P14="","",IF(N14="","",P14-N14)) -> 0.049305556 | Y14: =IF(N14="","",IF(Q14="","",Q14-N14)) -> 0.0625
A15: =IF(B15="","",WEEKNUM(B15,21)) -> 2 | B15: 45303 | D15: =IF(E15="","",WEEKNUM(E15,21)) -> 3 | E15: 45306 | G15: =IF(E15="","",IF(E15=B15,"Ja","Nein")) -> Nein | H15: 1000451166 | I15: Ploiesti | K15: 66 | L15: IBC | M15: Entladen | N15: 0.34236111 | O15: 0.36111111 | P15: 0.37847222 | Q15: 0.37847222 | V15: =IF(N15="","",IF(O15="","",O15-N15)) -> 0.01875 | W15: =IF(O15="","",IF(P15="","",P15-O15)) -> 0.017361111 | X15: =IF(P15="","",IF(N15="","",P15-N15)) -> 0.036111111 | Y15: =IF(N15="","",IF(Q15="","",Q15-N15)) -> 0.036111111
A16: =IF(B16="","",WEEKNUM(B16,21)) -> 3 | B16: 45306 | C16: 45308 | D16: =IF(E16="","",WEEKNUM(E16,21)) -> 3 | E16: 45309 | F16: 1 | G16: =IF(E16="","",IF(E16=B16,"Ja","Nein")) -> Nein | H16: 1000451783 | I16: Antwerpen | J16: 125979 | K16: 105 | L16: Leaf | M16: Entladen | N16: 0.30833333 | O16: 0.31666667 | P16: 0.34583333 | Q16: 0.43125 | R16: Yes | S16: docs issue: T1 fehlt; Kapazität von 6 St. erreicht, wird am 18.01. abgeladen; muss auch verladen werden | V16: =IF(N16="","",IF(O16="","",O16-N16)) -> 0.0083333333 | W16: =IF(O16="","",IF(P16="","",P16-O16)) -> 0.029166667 | X16: =IF(P16="","",IF(N16="","",P16-N16)) -> 0.0375 | Y16: =IF(N16="","",IF(Q16="","",Q16-N16)) -> 0.12291667
A17: =IF(B17="","",WEEKNUM(B17,21)) -> 3 | B17: 45306 | C17: 45308 | D17: =IF(E17="","",WEEKNUM(E17,21)) -> 3 | E17: 45308 | F17: 4 | G17: =IF(E17="","",IF(E17=B17,"Ja","Nein")) -> Nein | H17: 1000447753 | I17: Antwerpen | J17: 125980 | K17: 105 | L17: Leaf | M17: Entladen | N17: 0.37361111 | O17: 0.41388889 | P17: 0.44027778 | Q17: 0.50069444 | R17: Yes | S17: muss auch verladen werden | V17: =IF(N17="","",IF(O17="","",O17-N17)) -> 0.040277778 | W17: =IF(O17="","",IF(P17="","",P17-O17)) -> 0.026388889 | X17: =IF(P17="","",IF(N17="","",P17-N17)) -> 0.066666667 | Y17: =IF(N17="","",IF(Q17="","",Q17-N17)) -> 0.12708333
A18: =IF(B18="","",WEEKNUM(B18,21)) -> 3 | B18: 45307 | C18: 45307 | D18: =IF(E18="","",WEEKNUM(E18,21)) -> 3 | E18: 45307 | F18: 2 | G18: =IF(E18="","",IF(E18=B18,"Ja","Nein")) -> Ja | H18: 1000447746 | I18: Antwerpen | J18: 125973 | K18: 105 | L18: Leaf | M18: Entladen | N18: 0.39652778 | O18: 0.41458333 | P18: 0.44027778 | Q18: 0.53402778 | R18: Yes | S18: docs issue: keine Dokumente vorab erhalten; muss auch verladen werden | V18: =IF(N18="","",IF(O18="","",O18-N18)) -> 0.018055556 | W18: =IF(O18="","",IF(P18="","",P18-O18)) -> 0.025694444 | X18: =IF(P18="","",IF(N18="","",P18-N18)) -> 0.04375 | Y18: =IF(N18="","",IF(Q18="","",Q18-N18)) -> 0.1375
A19: =IF(B19="","",WEEKNUM(B19,21)) -> 3 | B19: 45307 | C19: 45307 | D19: =IF(E19="","",WEEKNUM(E19,21)) -> 3 | E19: 45307 | F19: 1 | G19: =IF(E19="","",IF(E19=B19,"Ja","Nein")) -> Ja | H19: 1000447748 | I19: Antwerpen | J19: 125975 | K19: 105 | L19: Leaf | M19: Entladen | N19: 0.30069444 | O19: 0.34305556 | P19: 0.37291667 | Q19: 0.45347222 | R19: Yes | S19: docs issue: keine Dokumente vorab erhalten; muss auch verladen werden | V19: =IF(N19="","",IF(O19="","",O19-N19)) -> 0.042361111 | W19: =IF(O19="","",IF(P19="","",P19-O19)) -> 0.029861111 | X19: =IF(P19="","",IF(N19="","",P19-N19)) -> 0.072222222 | Y19: =IF(N19="","",IF(Q19="","",Q19-N19)) -> 0.15277778
A20: =IF(B20="","",WEEKNUM(B20,21)) -> 3 | B20: 45307 | D20: =IF(E20="","",WEEKNUM(E20,21)) -> 3 | E20: 45308 | F20: 6 | G20: =IF(E20="","",IF(E20=B20,"Ja","Nein")) -> Nein | H20: 1000451103 | I20: Kroatien | J20: 4601387587 | K20: 100 | L20: Leaf | M20: Entladen | N20: 0.39652778 | O20: 0.50347222 | P20: 0.56805556 | Q20: 0.77083333 | R20: Yes | S20: muss auch verladen werden | V20: =IF(N20="","",IF(O20="","",O20-N20)) -> 0.10694444 | W20: =IF(O20="","",IF(P20="","",P20-O20)) -> 0.064583333 | X20: =IF(P20="","",IF(N20="","",P20-N20)) -> 0.17152778 | Y20: =IF(N20="","",IF(Q20="","",Q20-N20)) -> 0.37430556 | Z20: 38
A21: =IF(B21="","",WEEKNUM(B21,21)) -> 3 | B21: 45307 | D21: =IF(E21="","",WEEKNUM(E21,21)) -> 3 | E21: 45307 | F21: 3 | G21: =IF(E21="","",IF(E21=B21,"Ja","Nein")) -> Ja | H21: 1000451786 | I21: Kroatien | J21: 4702155228 | K21: 107 | L21: Leaf | M21: Entladen | N21: 0.48541667 | O21: 0.54791667 | P21: 0.57222222 | Q21: 0.58402778 | R21: Yes | S21: docs issue: CoA für Material 1027840X fehlt, kommt per Kurier | V21: =IF(N21="","",IF(O21="","",O21-N21)) -> 0.0625 | W21: =IF(O21="","",IF(P21="","",P21-O21)) -> 0.024305556 | X21: =IF(P21="","",IF(N21="","",P21-N21)) -> 0.086805556 | Y21: =IF(N21="","",IF(Q21="","",Q21-N21)) -> 0.098611111
A22: =IF(B22="","",WEEKNUM(B22,21)) -> 3 | B22: 45308 | C22: 45308 | D22: =IF(E22="","",WEEKNUM(E22,21)) -> 3 | E22: 45308 | F22: 5 | G22: =IF(E22="","",IF(E22=B22,"Ja","Nein")) -> Ja | H22: 1000447744 | I22: Antwerpen | J22: 125971 | K22: 102 | L22: Leaf | M22: Entladen | N22: 0.38541667 | O22: 0.49652778 | P22: 0.52638889 | Q22: 0.53125 | R22: Yes | V22: =IF(N22="","",IF(O22="","",O22-N22)) -> 0.11111111 | W22: =IF(O22="","",IF(P22="","",P22-O22)) -> 0.029861111 | X22: =IF(P22="","",IF(N22="","",P22-N22)) -> 0.14097222 | Y22: =IF(N22="","",IF(Q22="","",Q22-N22)) -> 0.14583333
A23: =IF(B23="","",WEEKNUM(B23,21)) -> 3 | B23: 45308 | C23: 45308 | D23: =IF(E23="","",WEEKNUM(E23,21)) -> 3 | E23: 45308 | F23: 1 | G23: =IF(E23="","",IF(E23=B23,"Ja","Nein")) -> Ja | H23: 1000447745 | I23: Antwerpen | J23: 125972 | K23: 94 | L23: Leaf | M23: Entladen | N23: 0.32569444 | O23: 0.33888889 | P23: 0.36458333 | Q23: 0.37222222 | R23: Yes | S23: docs issue: keine Dokumente vorab erhalten | V23: =IF(N23="","",IF(O23="","",O23-N23)) -> 0.013194444 | W23: =IF(O23="","",IF(P23="","",P23-O23)) -> 0.025694444 | X23: =IF(P23="","",IF(N23="","",P23-N23)) -> 0.038888889 | Y23: =IF(N23="","",IF(Q23="","",Q23-N23)) -> 0.046527778
A24: =IF(B24="","",WEEKNUM(B24,21)) -> 3 | B24: 45308 | C24: 45308 | D24: =IF(E24="","",WEEKNUM(E24,21)) -> 3 | E24: 45308 | F24: 3 | G24: =IF(E24="","",IF(E24=B24,"Ja","Nein")) -> Ja | H24: 1000447747 | I24: Antwerpen | J24: 125974 | K24: 105 | L24: Leaf | M24: Entladen | N24: 0.34652778 | O24: 0.37361111 | P24: 0.40069444 | Q24: 0.48055556 | R24: Yes | S24: muss auch verladen werden | V24: =IF(N24="","",IF(O24="","",O24-N24)) -> 0.027083333 | W24: =IF(O24="","",IF(P24="","",P24-O24)) -> 0.027083333 | X24: =IF(P24="","",IF(N24="","",P24-N24)) -> 0.054166667 | Y24: =IF(N24="","",IF(Q24="","",Q24-N24)) -> 0.13402778
A25: =IF(B25="","",WEEKNUM(B25,21)) -> 3 | B25: 45308 | C25: 45328 | D25: =IF(E25="","",WEEKNUM(E25,21)) -> 6 | E25: 45328 | F25: 3 | G25: =IF(E25="","",IF(E25=B25,"Ja","Nein")) -> Nein | H25: 1000456716 | I25: Kroatien | J25: 4601387588 | K25: 108 | L25: Leaf | M25: Entladen | N25: 0.37916667 | O25: 0.39583333 | P25: 0.42222222 | Q25: 0.43333333 | R25: Yes | V25: =IF(N25="","",IF(O25="","",O25-N25)) -> 0.016666667 | W25: =IF(O25="","",IF(P25="","",P25-O25)) -> 0.026388889 | X25: =IF(P25="","",IF(N25="","",P25-N25)) -> 0.043055556 | Y25: =IF(N25="","",IF(Q25="","",Q25-N25)) -> 0.054166667
A26: =IF(B26="","",WEEKNUM(B26,21)) -> 3 | B26: 45308 | E26: 45308 | G26: =IF(E26="","",IF(E26=B26,"Ja","Nein")) -> Ja | I26: Verbio | J26: 4500551034 | K26: 12 | L26: Rohware | M26: Entladen | N26: 0.51944444 | O26: 0.54166667 | P26: 0.55208333 | Q26: 0.55208333
A27: =IF(B27="","",WEEKNUM(B27,21)) -> 3 | B27: 45309 | C27: 45309 | D27: =IF(E27="","",WEEKNUM(E27,21)) -> 3 | E27: 45310 | F27: 2 | G27: =IF(E27="","",IF(E27=B27,"Ja","Nein")) -> Nein | H27: 1000447750 | I27: Antwerpen | J27: 125977 | K27: 105 | L27: Leaf | M27: Entladen | N27: 0.35555556 | O27: 0.36805556 | P27: 0.39583333 | Q27: 0.40694444 | R27: Yes | V27: =IF(N27="","",IF(O27="","",O27-N27)) -> 0.0125 | W27: =IF(O27="","",IF(P27="","",P27-O27)) -> 0.027777778 | X27: =IF(P27="","",IF(N27="","",P27-N27)) -> 0.040277778 | Y27: =IF(N27="","",IF(Q27="","",Q27-N27)) -> 0.051388889
A28: =IF(B28="","",WEEKNUM(B28,21)) -> 3 | B28: 45309 | C28: 45309 | D28: =IF(E28="","",WEEKNUM(E28,21)) -> 3 | E28: 45310 | F28: 3 | G28: =IF(E28="","",IF(E28=B28,"Ja","Nein")) -> Nein | H28: 1000447755 | I28: Antwerpen | J28: 125982 | K28: 104 | L28: Leaf | M28: Entladen | N28: 0.39375 | O28: 0.43958333 | P28: 0.475 | Q28: 0.48263889 | R28: Yes | S28: Fahrer kam zu spät, wird am 19.01. abgeladen | V28: =IF(N28="","",IF(O28="","",O28-N28)) -> 0.045833333 | W28: =IF(O28="","",IF(P28="","",P28-O28)) -> 0.035416667 | X28: =IF(P28="","",IF(N28="","",P28-N28)) -> 0.08125 | Y28: =IF(N28="","",IF(Q28="","",Q28-N28)) -> 0.088888889
A29: =IF(B29="","",WEEKNUM(B29,21)) -> 3 | B29: 45310 | C29: 45310 | D29: =IF(E29="","",WEEKNUM(E29,21)) -> 3 | E29: 45310 | F29: 1 | G29: =IF(E29="","",IF(E29=B29,"Ja","Nein")) -> Ja | H29: 1000447749 | I29: Antwerpen | J29: 125976 | K29: 75 | L29: Leaf | M29: Entladen | N29: 0.28958333 | O29: 0.32708333 | P29: 0.35486111 | Q29: 0.36041667 | R29: Yes | V29: =IF(N29="","",IF(O29="","",O29-N29)) -> 0.0375 | W29: =IF(O29="","",IF(P29="","",P29-O29)) -> 0.027777778 | X29: =IF(P29="","",IF(N29="","",P29-N29)) -> 0.065277778 | Y29: =IF(N29="","",IF(Q29="","",Q29-N29)) -> 0.070833333
A30: =IF(B30="","",WEEKNUM(B30,21)) -> 3 | B30: 45310 | D30: =IF(E30="","",WEEKNUM(E30,21)) -> 3 | E30: 45310 | G30: =IF(E30="","",IF(E30=B30,"Ja","Nein")) -> Ja | I30: Schütz | J30: 5700591582 | K30: 93 | L30: IBC | M30: Entladen | O30: 0.3125 | P30: 0.34027778 | Q30: 0.34027778 | S30: ist über Pforte Nord reingefahren, hat sich bei mir nicht gemeldet
A31: =IF(B31="","",WEEKNUM(B31,21)) -> 4 | B31: 45313 | C31: 45313 | D31: =IF(E31="","",WEEKNUM(E31,21)) -> 4 | E31: 45313 | F31: 2 | G31: =IF(E31="","",IF(E31=B31,"Ja","Nein")) -> Ja | H31: 1000451801 | I31: Antwerpen | J31: 126170 | K31: 105 | L31: Leaf | M31: Entladen | N31: 0.32708333 | O31: 0.43680556 | P31: 0.46041667 | Q31: 0.46875 | R31: Yes | S31: docs issue: keine Dokumente vorab erhalten | V31: =IF(N31="","",IF(O31="","",O31-N31)) -> 0.10972222 | W31: =IF(O31="","",IF(P31="","",P31-O31)) -> 0.023611111 | X31: =IF(P31="","",IF(N31="","",P31-N31)) -> 0.13333333 | Y31: =IF(N31="","",IF(Q31="","",Q31-N31)) -> 0.14166667
A32: =IF(B32="","",WEEKNUM(B32,21)) -> 4 | B32: 45313 | C32: 45313 | D32: =IF(E32="","",WEEKNUM(E32,21)) -> 4 | E32: 45313 | F32: 1 | G32: =IF(E32="","",IF(E32=B32,"Ja","Nein")) -> Ja | H32: 1000452401 | I32: Antwerpen | J32: 126174 | K32: 105 | L32: Leaf | M32: Entladen | N32: 0.32083333 | O32: 0.38958333 | P32: 0.42291667 | Q32: 0.43402778 | R32: Yes | S32: docs issue: keine Dokumente vorab erhalten | V32: =IF(N32="","",IF(O32="","",O32-N32)) -> 0.06875 | W32: =IF(O32="","",IF(P32="","",P32-O32)) -> 0.033333333 | X32: =IF(P32="","",IF(N32="","",P32-N32)) -> 0.10208333 | Y32: =IF(N32="","",IF(Q32="","",Q32-N32)) -> 0.11319444
A33: =IF(B33="","",WEEKNUM(B33,21)) -> 4 | B33: 45313 | C33: 45315 | D33: =IF(E33="","",WEEKNUM(E33,21)) -> 4 | E33: 45315 | F33: 1 | G33: =IF(E33="","",IF(E33=B33,"Ja","Nein")) -> Nein | H33: 1000452402 | I33: Antwerpen | J33: 126177 | K33: 105 | L33: Leaf | M33: Entladen | N33: 0.40208333 | O33: 0.41111111 | P33: 0.43402778 | Q33: 0.44166667 | R33: Yes | V33: =IF(N33="","",IF(O33="","",O33-N33)) -> 0.0090277778 | W33: =IF(O33="","",IF(P33="","",P33-O33)) -> 0.022916667 | X33: =IF(P33="","",IF(N33="","",P33-N33)) -> 0.031944444 | Y33: =IF(N33="","",IF(Q33="","",Q33-N33)) -> 0.039583333
A34: =IF(B34="","",WEEKNUM(B34,21)) -> 4 | B34: 45314 | C34: 45314 | D34: =IF(E34="","",WEEKNUM(E34,21)) -> 4 | E34: 45314 | F34: 2 | G34: =IF(E34="","",IF(E34=B34,"Ja","Nein")) -> Ja | H34: 1000453615 | I34: Antwerpen | J34: 126173 | K34: 100 | L34: Leaf | M34: Entladen | N34: 0.39513889 | O34: 0.42638889 | P34: 0.44791667 | Q34: 0.51805556 | R34: Yes | S34: docs issue: keine Dokumente vorab erhalten; muss auch verladen werden | V34: =IF(N34="","",IF(O34="","",O34-N34)) -> 0.03125 | W34: =IF(O34="","",IF(P34="","",P34-O34)) -> 0.021527778 | X34: =IF(P34="","",IF(N34="","",P34-N34)) -> 0.052777778 | Y34: =IF(N34="","",IF(Q34="","",Q34-N34)) -> 0.12291667
A35: =IF(B35="","",WEEKNUM(B35,21)) -> 4 | B35: 45314 | C35: 45314 | D35: =IF(E35="","",WEEKNUM(E35,21)) -> 4 | E35: 45314 | F35: 1 | G35: =IF(E35="","",IF(E35=B35,"Ja","Nein")) -> Ja | H35: 1000453616 | I35: Antwerpen | J35: 126180 | K35: 105 | L35: Leaf | M35: Entladen | N35: 0.31666667 | O35: 0.34861111 | P35: 0.37777778 | Q35: 0.38680556 | R35: Yes | S35: docs issue: keine Dokumente vorab erhalten | V35: =IF(N35="","",IF(O35="","",O35-N35)) -> 0.031944444 | W35: =IF(O35="","",IF(P35="","",P35-O35)) -> 0.029166667 | X35: =IF(P35="","",IF(N35="","",P35-N35)) -> 0.061111111 | Y35: =IF(N35="","",IF(Q35="","",Q35-N35)) -> 0.070138889
A36: =IF(B36="","",WEEKNUM(B36,21)) -> 4 | B36: 45314 | D36: =IF(E36="","",WEEKNUM(E36,21)) -> 4 | E36: 45314 | F36: 3 | G36: =IF(E36="","",IF(E36=B36,"Ja","Nein")) -> Ja | H36: 1000453873 | I36: Kroatien | J36: 4601390251 | K36: 108 | L36: Leaf | M36: Entladen | N36: 0.42708333 | O36: 0.45833333 | P36: 0.48333333 | Q36: 0.49791667 | R36: Yes | V36: =IF(N36="","",IF(O36="","",O36-N36)) -> 0.03125 | W36: =IF(O36="","",IF(P36="","",P36-O36)) -> 0.025 | X36: =IF(P36="","",IF(N36="","",P36-N36)) -> 0.05625 | Y36: =IF(N36="","",IF(Q36="","",Q36-N36)) -> 0.070833333
A37: =IF(B37="","",WEEKNUM(B37,21)) -> 4 | B37: 45314 | C37: 45328 | D37: =IF(E37="","",WEEKNUM(E37,21)) -> 6 | E37: 45328 | F37: 4 | G37: =IF(E37="","",IF(E37=B37,"Ja","Nein")) -> Nein | H37: 1000456717 | I37: Kroatien | J37: 4601387450 | K37: 108 | L37: Leaf | M37: Entladen | N37: 0.38888889 | O37: 0.47222222 | P37: 0.49791667 | Q37: 0.51180556 | R37: Yes | V37: =IF(N37="","",IF(O37="","",O37-N37)) -> 0.083333333 | W37: =IF(O37="","",IF(P37="","",P37-O37)) -> 0.025694444 | X37: =IF(P37="","",IF(N37="","",P37-N37)) -> 0.10902778 | Y37: =IF(N37="","",IF(Q37="","",Q37-N37)) -> 0.12291667
A38: =IF(B38="","",WEEKNUM(B38,21)) -> 4 | B38: 45315 | C38: 45315 | D38: =IF(E38="","",WEEKNUM(E38,21)) -> 4 | E38: 45316 | F38: 1 | G38: =IF(E38="","",IF(E38=B38,"Ja","Nein")) -> Nein | H38: 1000453974 | I38: Antwerpen | J38: 126171 | K38: 92 | L38: Leaf | M38: Entladen | N38: 0.3625 | O38: 0.36944444 | P38: 0.39652778 | Q38: 0.40416667 | R38: Yes | V38: =IF(N38="","",IF(O38="","",O38-N38)) -> 0.0069444444 | W38: =IF(O38="","",IF(P38="","",P38-O38)) -> 0.027083333 | X38: =IF(P38="","",IF(N38="","",P38-N38)) -> 0.034027778 | Y38: =IF(N38="","",IF(Q38="","",Q38-N38)) -> 0.041666667
A39: =IF(B39="","",WEEKNUM(B39,21)) -> 4 | B39: 45315 | C39: 45315 | D39: =IF(E39="","",WEEKNUM(E39,21)) -> 4 | E39: 45315 | F39: 2 | G39: =IF(E39="","",IF(E39=B39,"Ja","Nein")) -> Ja | H39: 1000453975 | I39: Antwerpen | J39: 126178 | K39: 96 | L39: Leaf | M39: Entladen | N39: 0.47291667 | O39: 0.49027778 | P39: 0.51666667 | Q39: 0.57291667 | R39: Yes | S39: muss auch verladen werden | V39: =IF(N39="","",IF(O39="","",O39-N39)) -> 0.017361111 | W39: =IF(O39="","",IF(P39="","",P39-O39)) -> 0.026388889 | X39: =IF(P39="","",IF(N39="","",P39-N39)) -> 0.04375 | Y39: =IF(N39="","",IF(Q39="","",Q39-N39)) -> 0.1
A40: =IF(B40="","",WEEKNUM(B40,21)) -> 4 | B40: 45316 | C40: 45316 | D40: =IF(E40="","",WEEKNUM(E40,21)) -> 4 | E40: 45316 | F40: 2 | G40: =IF(E40="","",IF(E40=B40,"Ja","Nein")) -> Ja | H40: 1000454079 | I40: Antwerpen | J40: 126175 | K40: 105 | L40: Leaf | M40: Entladen | N40: 0.55208333 | O40: 0.5625 | P40: 0.58333333 | Q40: 0.66736111 | R40: Yes | S40: docs issue: unkonform gemeldet, falsche Warenummer auf T1 (1030850X); muss auch verladen werden | V40: =IF(N40="","",IF(O40="","",O40-N40)) -> 0.010416667 | W40: =IF(O40="","",IF(P40="","",P40-O40)) -> 0.020833333 | X40: =IF(P40="","",IF(N40="","",P40-N40)) -> 0.03125 | Y40: =IF(N40="","",IF(Q40="","",Q40-N40)) -> 0.11527778
A41: =IF(B41="","",WEEKNUM(B41,21)) -> 4 | B41: 45316 | C41: 45316 | D41: =IF(E41="","",WEEKNUM(E41,21)) -> 4 | E41: 45316 | F41: 3 | G41: =IF(E41="","",IF(E41=B41,"Ja","Nein")) -> Ja | H41: 1000454080 | I41: Antwerpen | J41: 126179 | K41: 105 | L41: Leaf | M41: Entladen | N41: 0.55763889 | O41: 0.58958333 | P41: 0.61388889 | Q41: 0.62847222 | R41: Yes | S41: muss auch verladen werden | V41: =IF(N41="","",IF(O41="","",O41-N41)) -> 0.031944444 | W41: =IF(O41="","",IF(P41="","",P41-O41)) -> 0.024305556 | X41: =IF(P41="","",IF(N41="","",P41-N41)) -> 0.05625 | Y41: =IF(N41="","",IF(Q41="","",Q41-N41)) -> 0.070833333
A42: =IF(B42="","",WEEKNUM(B42,21)) -> 4 | B42: 45316 | D42: =IF(E42="","",WEEKNUM(E42,21)) -> 4 | E42: 45316 | G42: =IF(E42="","",IF(E42=B42,"Ja","Nein")) -> Ja | I42: Gardanne | J42: 4500553652 | K42: 1032 | L42: Rohware | M42: Entladen | N42: 0.34513889 | O42: 0.35416667 | P42: 0.40625 | Q42: 0.40625
A43: =IF(B43="","",WEEKNUM(B43,21)) -> 4 | B43: 45317 | C43: 45317 | D43: =IF(E43="","",WEEKNUM(E43,21)) -> 4 | E43: 45317 | F43: 1 | G43: =IF(E43="","",IF(E43=B43,"Ja","Nein")) -> Ja | H43: 1000454081 | I43: Antwerpen | J43: 126172 | K43: 105 | L43: Leaf | M43: Entladen | N43: 0.37569444 | O43: 0.38888889 | P43: 0.40833333 | Q43: 0.42152778 | R43: Yes | S43: docs issue: keine Dokumente vorab erhalten | V43: =IF(N43="","",IF(O43="","",O43-N43)) -> 0.013194444 | W43: =IF(O43="","",IF(P43="","",P43-O43)) -> 0.019444444 | X43: =IF(P43="","",IF(N43="","",P43-N43)) -> 0.032638889 | Y43: =IF(N43="","",IF(Q43="","",Q43-N43)) -> 0.045833333
A44: =IF(B44="","",WEEKNUM(B44,21)) -> 4 | B44: 45317 | C44: 45317 | D44: =IF(E44="","",WEEKNUM(E44,21)) -> 4 | E44: 45317 | F44: 2 | G44: =IF(E44="","",IF(E44=B44,"Ja","Nein")) -> Ja | H44: 1000454082 | I44: Antwerpen | J44: 126176 | K44: 105 | L44: Leaf | M44: Entladen | N44: 0.46180556 | O44: 0.49027778 | P44: 0.51180556 | Q44: 0.60902778 | R44: Yes | S44: docs issue: keine Dokumente vorab erhalten; muss auch verladen werden | V44: =IF(N44="","",IF(O44="","",O44-N44)) -> 0.028472222 | W44: =IF(O44="","",IF(P44="","",P44-O44)) -> 0.021527778 | X44: =IF(P44="","",IF(N44="","",P44-N44)) -> 0.05 | Y44: =IF(N44="","",IF(Q44="","",Q44-N44)) -> 0.14722222
A45: =IF(B45="","",WEEKNUM(B45,21)) -> 5 | B45: 45320 | C45: 45320 | D45: =IF(E45="","",WEEKNUM(E45,21)) -> 5 | E45: 45320 | F45: 1 | G45: =IF(E45="","",IF(E45=B45,"Ja","Nein")) -> Ja | H45: 1000454537 | I45: Antwerpen | J45: 126257 | K45: 102 | L45: Leaf | M45: Entladen | N45: 0.37083333 | O45: 0.40972222 | P45: 0.46458333 | Q45: 0.58263889 | R45: Yes | S45: docs issue: keine Dokumente vorab erhalten; muss auch verladen werden | V45: =IF(N45="","",IF(O45="","",O45-N45)) -> 0.038888889 | W45: =IF(O45="","",IF(P45="","",P45-O45)) -> 0.054861111 | X45: =IF(P45="","",IF(N45="","",P45-N45)) -> 0.09375 | Y45: =IF(N45="","",IF(Q45="","",Q45-N45)) -> 0.21180556
A46: =IF(B46="","",WEEKNUM(B46,21)) -> 5 | B46: 45320 | C46: 45320 | D46: =IF(E46="","",WEEKNUM(E46,21)) -> 5 | E46: 45320 | F46: 2 | G46: =IF(E46="","",IF(E46=B46,"Ja","Nein")) -> Ja | H46: 1000454540 | I46: Antwerpen | J46: 126260 | K46: 105 | L46: Leaf | M46: Entladen | N46: 0.38472222 | O46: 0.47291667 | P46: 0.52638889 | Q46: 0.66041667 | R46: Yes | S46: docs issue: keine Dokumente vorab erhalten; muss auch verladen werden | V46: =IF(N46="","",IF(O46="","",O46-N46)) -> 0.088194444 | W46: =IF(O46="","",IF(P46="","",P46-O46)) -> 0.053472222 | X46: =IF(P46="","",IF(N46="","",P46-N46)) -> 0.14166667 | Y46: =IF(N46="","",IF(Q46="","",Q46-N46)) -> 0.27569444
A47: =IF(B47="","",WEEKNUM(B47,21)) -> 5 | B47: 45320 | C47: 45320 | D47: =IF(E47="","",WEEKNUM(E47,21)) -> 5 | E47: 45324 | F47: 1 | G47: =IF(E47="","",IF(E47=B47,"Ja","Nein")) -> Nein | H47: 1000454541 | I47: Antwerpen | J47: 126261 | K47: 105 | L47: Leaf | M47: Entladen | N47: 0.31319444 | O47: 0.32708333 | P47: 0.37569444 | Q47: 0.3875 | R47: Yes | S47: docs issue: keine Dokumente vorab erhalten | V47: =IF(N47="","",IF(O47="","",O47-N47)) -> 0.013888889 | W47: =IF(O47="","",IF(P47="","",P47-O47)) -> 0.048611111 | X47: =IF(P47="","",IF(N47="","",P47-N47)) -> 0.0625 | Y47: =IF(N47="","",IF(Q47="","",Q47-N47)) -> 0.074305556
A48: =IF(B48="","",WEEKNUM(B48,21)) -> 5 | B48: 45320 | C48: 45321 | D48: =IF(E48="","",WEEKNUM(E48,21)) -> 5 | E48: 45323 | F48: 3 | G48: =IF(E48="","",IF(E48=B48,"Ja","Nein")) -> Nein | H48: 1000454546 | I48: Antwerpen | J48: 126266 | K48: 105 | L48: Leaf | M48: Entladen | N48: 0.37291667 | O48: 0.43402778 | P48: 0.45763889 | Q48: 0.46458333 | R48: Yes | S48: docs issue: keine Dokumente vorab erhalten | V48: =IF(N48="","",IF(O48="","",O48-N48)) -> 0.061111111 | W48: =IF(O48="","",IF(P48="","",P48-O48)) -> 0.023611111 | X48: =IF(P48="","",IF(N48="","",P48-N48)) -> 0.084722222 | Y48: =IF(N48="","",IF(Q48="","",Q48-N48)) -> 0.091666667
A49: =IF(B49="","",WEEKNUM(B49,21)) -> 5 | B49: 45320 | D49: =IF(E49="","",WEEKNUM(E49,21)) -> 5 | E49: 45321 | F49: 2 | G49: =IF(E49="","",IF(E49=B49,"Ja","Nein")) -> Nein | H49: 1000455199 | I49: Kroatien | J49: 4601390252 | K49: 108 | L49: Leaf | M49: Entladen | N49: 0.32847222 | O49: 0.35763889 | P49: 0.38402778 | Q49: 0.39513889 | R49: Yes | S49: Fahrer kam zu spät, wird am 30.01. abgeladen | V49: =IF(N49="","",IF(O49="","",O49-N49)) -> 0.029166667 | W49: =IF(O49="","",IF(P49="","",P49-O49)) -> 0.026388889 | X49: =IF(P49="","",IF(N49="","",P49-N49)) -> 0.055555556 | Y49: =IF(N49="","",IF(Q49="","",Q49-N49)) -> 0.066666667
A50: =IF(B50="","",WEEKNUM(B50,21)) -> 5 | B50: 45321 | C50: 45321 | D50: =IF(E50="","",WEEKNUM(E50,21)) -> 5 | E50: 45321 | F50: 3 | G50: =IF(E50="","",IF(E50=B50,"Ja","Nein")) -> Ja | H50: 1000454547 | I50: Antwerpen | J50: 126258 | K50: 105 | L50: Leaf | M50: Entladen | N50: 0.33888889 | O50: 0.40069444 | P50: 0.42708333 | Q50: 0.43819444 | R50: Yes | S50: docs issue: keine Dokumente vorab erhalten | V50: =IF(N50="","",IF(O50="","",O50-N50)) -> 0.061805556 | W50: =IF(O50="","",IF(P50="","",P50-O50)) -> 0.026388889 | X50: =IF(P50="","",IF(N50="","",P50-N50)) -> 0.088194444 | Y50: =IF(N50="","",IF(Q50="","",Q50-N50)) -> 0.099305556
A51: =IF(B51="","",WEEKNUM(B51,21)) -> 5 | B51: 45321 | C51: 45321 | D51: =IF(E51="","",WEEKNUM(E51,21)) -> 5 | E51: 45321 | F51: 1 | G51: =IF(E51="","",IF(E51=B51,"Ja","Nein")) -> Ja | H51: 1000454548 | I51: Antwerpen | J51: 126259 | K51: 105 | L51: Leaf | M51: Entladen | N51: 0.29583333 | O51: 0.32013889 | P51: 0.34375 | Q51: 0.46944444 | R51: Yes | S51: docs issue: keine Dokumente vorab erhalten; muss auch verladen werden | V51: =IF(N51="","",IF(O51="","",O51-N51)) -> 0.024305556 | W51: =IF(O51="","",IF(P51="","",P51-O51)) -> 0.023611111 | X51: =IF(P51="","",IF(N51="","",P51-N51)) -> 0.047916667 | Y51: =IF(N51="","",IF(Q51="","",Q51-N51)) -> 0.17361111
A52: =IF(B52="","",WEEKNUM(B52,21)) -> 5 | B52: 45321 | C52: 45321 | D52: =IF(E52="","",WEEKNUM(E52,21)) -> 5 | E52: 45321 | F52: 4 | G52: =IF(E52="","",IF(E52=B52,"Ja","Nein")) -> Ja | H52: 1000454549 | I52: Antwerpen | J52: 126263 | K52: 105 | L52: Leaf | M52: Entladen | N52: 0.51875 | O52: 0.52986111 | P52: 0.55416667 | Q52: 0.61736111 | R52: Yes | S52: docs issue: keine Dokumente vorab erhalten; muss auch verladen werden | V52: =IF(N52="","",IF(O52="","",O52-N52)) -> 0.011111111 | W52: =IF(O52="","",IF(P52="","",P52-O52)) -> 0.024305556 | X52: =IF(P52="","",IF(N52="","",P52-N52)) -> 0.035416667 | Y52: =IF(N52="","",IF(Q52="","",Q52-N52)) -> 0.098611111
A53: =IF(B53="","",WEEKNUM(B53,21)) -> 5 | B53: 45321 | D53: =IF(E53="","",WEEKNUM(E53,21)) -> 5 | E53: 45321 | F53: 4 | G53: =IF(E53="","",IF(E53=B53,"Ja","Nein")) -> Ja | H53: 1000455479 | I53: Kroatien | J53: 4601390253 | K53: 108 | L53: Leaf | M53: Entladen | N53: 0.56527778 | O53: 0.59027778 | P53: 0.61666667 | Q53: 0.625 | R53: Yes | V53: =IF(N53="","",IF(O53="","",O53-N53)) -> 0.025 | W53: =IF(O53="","",IF(P53="","",P53-O53)) -> 0.026388889 | X53: =IF(P53="","",IF(N53="","",P53-N53)) -> 0.051388889 | Y53: =IF(N53="","",IF(Q53="","",Q53-N53)) -> 0.059722222
A54: =IF(B54="","",WEEKNUM(B54,21)) -> 5 | B54: 45322 | C54: 45322 | D54: =IF(E54="","",WEEKNUM(E54,21)) -> 5 | E54: 45322 | F54: 1 | G54: =IF(E54="","",IF(E54=B54,"Ja","Nein")) -> Ja | H54: 1000455049 | I54: Antwerpen | J54: 126256 | K54: 105 | L54: Leaf | M54: Entladen | N54: 0.29375 | O54: 0.31180556 | P54: 0.33819444 | Q54: 0.34583333 | R54: Yes | V54: =IF(N54="","",IF(O54="","",O54-N54)) -> 0.018055556 | W54: =IF(O54="","",IF(P54="","",P54-O54)) -> 0.026388889 | X54: =IF(P54="","",IF(N54="","",P54-N54)) -> 0.044444444 | Y54: =IF(N54="","",IF(Q54="","",Q54-N54)) -> 0.052083333
A55: =IF(B55="","",WEEKNUM(B55,21)) -> 5 | B55: 45322 | C55: 45322 | D55: =IF(E55="","",WEEKNUM(E55,21)) -> 5 | E55: 45323 | F55: 1 | G55: =IF(E55="","",IF(E55=B55,"Ja","Nein")) -> Nein | H55: 1000455050 | I55: Antwerpen | J55: 126264 | K55: 105 | L55: Leaf | M55: Entladen | N55: 0.33402778 | O55: 0.35208333 | P55: 0.37708333 | Q55: 0.38541667 | R55: Yes | S55: docs issue: keine Dokumente vorab erhalten; falsche Warennummer bei Material 1030850X, unkonform gemeldet | V55: =IF(N55="","",IF(O55="","",O55-N55)) -> 0.018055556 | W55: =IF(O55="","",IF(P55="","",P55-O55)) -> 0.025 | X55: =IF(P55="","",IF(N55="","",P55-N55)) -> 0.043055556 | Y55: =IF(N55="","",IF(Q55="","",Q55-N55)) -> 0.051388889
A56: =IF(B56="","",WEEKNUM(B56,21)) -> 5 | B56: 45322 | C56: 44962 | D56: =IF(E56="","",WEEKNUM(E56,21)) -> 6 | E56: 45327 | F56: 1 | G56: =IF(E56="","",IF(E56=B56,"Ja","Nein")) -> Nein | H56: 1000455051 | I56: Antwerpen | J56: 126271 | K56: 105 | L56: Leaf | M56: Entladen | N56: 0.29930556 | O56: 0.33680556 | P56: 0.36597222 | Q56: 0.44722222 | R56: Yes | S56: docs issue: keine Dokumente vorab erhalten; muss auch verladen werden | V56: =IF(N56="","",IF(O56="","",O56-N56)) -> 0.0375 | W56: =IF(O56="","",IF(P56="","",P56-O56)) -> 0.029166667 | X56: =IF(P56="","",IF(N56="","",P56-N56)) -> 0.066666667 | Y56: =IF(N56="","",IF(Q56="","",Q56-N56)) -> 0.14791667
A57: =IF(B57="","",WEEKNUM(B57,21)) -> 5 | B57: 45323 | C57: 45323 | D57: =IF(E57="","",WEEKNUM(E57,21)) -> 5 | E57: 45324 | F57: 2 | G57: =IF(E57="","",IF(E57=B57,"Ja","Nein")) -> Nein | H57: 1000455052 | I57: Antwerpen | J57: 126267 | K57: 105 | L57: Leaf | M57: Entladen | N57: 0.47847222 | O57: 0.49444444 | P57: 0.51736111 | Q57: 0.525 | R57: Yes | S57: docs issue: keine Dokumente vorab erhalten | V57: =IF(N57="","",IF(O57="","",O57-N57)) -> 0.015972222 | W57: =IF(O57="","",IF(P57="","",P57-O57)) -> 0.022916667 | X57: =IF(P57="","",IF(N57="","",P57-N57)) -> 0.038888889 | Y57: =IF(N57="","",IF(Q57="","",Q57-N57)) -> 0.046527778
A58: =IF(B58="","",WEEKNUM(B58,21)) -> 5 | B58: 45323 | C58: 45323 | D58: =IF(E58="","",WEEKNUM(E58,21)) -> 5 | E58: 45323 | F58: 4 | G58: =IF(E58="","",IF(E58=B58,"Ja","Nein")) -> Ja | H58: 1000455053 | I58: Antwerpen | J58: 126268 | K58: 99 | L58: Leaf | M58: Entladen | N58: 0.42361111 | O58: 0.46736111 | P58: 0.49166667 | Q58: 0.49861111 | R58: Yes | S58: docs issue: keine Dokumente vorab erhalten | V58: =IF(N58="","",IF(O58="","",O58-N58)) -> 0.04375 | W58: =IF(O58="","",IF(P58="","",P58-O58)) -> 0.024305556 | X58: =IF(P58="","",IF(N58="","",P58-N58)) -> 0.068055556 | Y58: =IF(N58="","",IF(Q58="","",Q58-N58)) -> 0.075
A59: =IF(B59="","",WEEKNUM(B59,21)) -> 5 | B59: 45323 | C59: 45323 | D59: =IF(E59="","",WEEKNUM(E59,21)) -> 5 | E59: 45323 | F59: 2 | G59: =IF(E59="","",IF(E59=B59,"Ja","Nein")) -> Ja | H59: 1000455054 | I59: Antwerpen | J59: 126269 | K59: 105 | L59: Leaf | M59: Entladen | N59: 0.34583333 | O59: 0.38958333 | P59: 0.41805556 | Q59: 0.42986111 | R59: Yes | S59: docs issue: keine Dokumente vorab erhalten | V59: =IF(N59="","",IF(O59="","",O59-N59)) -> 0.04375 | W59: =IF(O59="","",IF(P59="","",P59-O59)) -> 0.028472222 | X59: =IF(P59="","",IF(N59="","",P59-N59)) -> 0.072222222 | Y59: =IF(N59="","",IF(Q59="","",Q59-N59)) -> 0.084027778
A60: =IF(B60="","",WEEKNUM(B60,21)) -> 5 | B60: 45324 | C60: 45327 | D60: =IF(E60="","",WEEKNUM(E60,21)) -> 6 | E60: 45330 | F60: 2 | G60: =IF(E60="","",IF(E60=B60,"Ja","Nein")) -> Nein | H60: 1000455291 | I60: Antwerpen | J60: 126262 | K60: 105 | L60: Leaf | M60: Entladen | N60: 0.32847222 | O60: 0.35277778 | P60: 0.37777778 | Q60: 0.38402778 | R60: Yes | V60: =IF(N60="","",IF(O60="","",O60-N60)) -> 0.024305556 | W60: =IF(O60="","",IF(P60="","",P60-O60)) -> 0.025 | X60: =IF(P60="","",IF(N60="","",P60-N60)) -> 0.049305556 | Y60: =IF(N60="","",IF(Q60="","",Q60-N60)) -> 0.055555556
A61: =IF(B61="","",WEEKNUM(B61,21)) -> 5 | B61: 45324 | C61: 45327 | D61: =IF(E61="","",WEEKNUM(E61,21)) -> 6 | E61: 45327 | F61: 2 | G61: =IF(E61="","",IF(E61=B61,"Ja","Nein")) -> Nein | H61: 1000455292 | I61: Antwerpen | J61: 126265 | K61: 105 | L61: Leaf | M61: Entladen | N61: 0.32708333 | O61: 0.45069444 | P61: 0.475 | Q61: 0.48611111 | R61: Yes | S61: docs issue: keine Dokumente vorab erhalten | V61: =IF(N61="","",IF(O61="","",O61-N61)) -> 0.12361111 | W61: =IF(O61="","",IF(P61="","",P61-O61)) -> 0.024305556 | X61: =IF(P61="","",IF(N61="","",P61-N61)) -> 0.14791667 | Y61: =IF(N61="","",IF(Q61="","",Q61-N61)) -> 0.15902778
A62: =IF(B62="","",WEEKNUM(B62,21)) -> 5 | B62: 45324 | C62: 45328 | D62: =IF(E62="","",WEEKNUM(E62,21)) -> 6 | E62: 45329 | F62: 2 | G62: =IF(E62="","",IF(E62=B62,"Ja","Nein")) -> Nein | H62: 1000455394 | I62: Antwerpen | J62: 126270 | K62: 104 | L62: Leaf | M62: Entladen | N62: 0.27777778 | O62: 0.37013889 | P62: 0.39861111 | Q62: 0.40416667 | R62: Yes | S62: docs issue: keine Dokumente vorab erhalten; Kapazität von 6 St. erreicht, wird am 07.02. abgeladen | V62: =IF(N62="","",IF(O62="","",O62-N62)) -> 0.092361111 | W62: =IF(O62="","",IF(P62="","",P62-O62)) -> 0.028472222 | X62: =IF(P62="","",IF(N62="","",P62-N62)) -> 0.12083333 | Y62: =IF(N62="","",IF(Q62="","",Q62-N62)) -> 0.12638889
A63: =IF(B63="","",WEEKNUM(B63,21)) -> 6 | B63: 45327 | C63: 45328 | D63: =IF(E63="","",WEEKNUM(E63,21)) -> 6 | E63: 45329 | F63: 3 | G63: =IF(E63="","",IF(E63=B63,"Ja","Nein")) -> Nein | H63: 1000455293 | I63: Antwerpen | J63: 126272 | K63: 105 | L63: Leaf | M63: Entladen | N63: 0.27777778 | O63: 0.40694444 | P63: 0.43055556 | Q63: 0.44027778 | R63: Yes | S63: docs issue: keine Dokumente vorab erhalten; Kapazität von 6 St. erreicht, wird am 07.02. abgeladen | V63: =IF(N63="","",IF(O63="","",O63-N63)) -> 0.12916667 | W63: =IF(O63="","",IF(P63="","",P63-O63)) -> 0.023611111 | X63: =IF(P63="","",IF(N63="","",P63-N63)) -> 0.15277778 | Y63: =IF(N63="","",IF(Q63="","",Q63-N63)) -> 0.1625
A64: =IF(B64="","",WEEKNUM(B64,21)) -> 6 | B64: 45327 | C64: 45328 | D64: =IF(E64="","",WEEKNUM(E64,21)) -> 6 | E64: 45328 | F64: 2 | G64: =IF(E64="","",IF(E64=B64,"Ja","Nein")) -> Nein | H64: 1000455396 | I64: Antwerpen | J64: 126276 | K64: 105 | L64: Leaf | M64: Entladen | N64: 0.29791667 | O64: 0.31111111 | P64: 0.33541667 | Q64: 0.34583333 | R64: Yes | S64: docs issue: keine Dokumente vorab erhalten | V64: =IF(N64="","",IF(O64="","",O64-N64)) -> 0.013194444 | W64: =IF(O64="","",IF(P64="","",P64-O64)) -> 0.024305556 | X64: =IF(P64="","",IF(N64="","",P64-N64)) -> 0.0375 | Y64: =IF(N64="","",IF(Q64="","",Q64-N64)) -> 0.047916667
A65: =IF(B65="","",WEEKNUM(B65,21)) -> 6 | B65: 45328 | C65: 45328 | D65: =IF(E65="","",WEEKNUM(E65,21)) -> 6 | E65: 45328 | F65: 6 | G65: =IF(E65="","",IF(E65=B65,"Ja","Nein")) -> Ja | H65: 1000457287 | I65: Antwerpen | J65: 126275 | K65: 105 | L65: Leaf | M65: Entladen | N65: 0.44236111 | O65: 0.54722222 | P65: 0.57013889 | Q65: 0.58194444 | R65: Yes | S65: docs issue: keine Dokumente vorab erhalten | V65: =IF(N65="","",IF(O65="","",O65-N65)) -> 0.10486111 | W65: =IF(O65="","",IF(P65="","",P65-O65)) -> 0.022916667 | X65: =IF(P65="","",IF(N65="","",P65-N65)) -> 0.12777778 | Y65: =IF(N65="","",IF(Q65="","",Q65-N65)) -> 0.13958333
A66: =IF(B66="","",WEEKNUM(B66,21)) -> 6 | B66: 45328 | C66: 45328 | D66: =IF(E66="","",WEEKNUM(E66,21)) -> 6 | E66: 45328 | F66: 5 | G66: =IF(E66="","",IF(E66=B66,"Ja","Nein")) -> Ja | H66: 1000457289 | I66: Antwerpen | J66: 126277 | K66: 107 | L66: Leaf | M66: Entladen | N66: 0.39791667 | O66: 0.43333333 | P66: 0.45972222 | Q66: 0.47013889 | R66: Yes | S66: docs issue: keine Dokumente vorab erhalten; muss auch verladen werden | V66: =IF(N66="","",IF(O66="","",O66-N66)) -> 0.035416667 | W66: =IF(O66="","",IF(P66="","",P66-O66)) -> 0.026388889 | X66: =IF(P66="","",IF(N66="","",P66-N66)) -> 0.061805556 | Y66: =IF(N66="","",IF(Q66="","",Q66-N66)) -> 0.072222222
A67: =IF(B67="","",WEEKNUM(B67,21)) -> 6 | B67: 45328 | C67: 45329 | D67: =IF(E67="","",WEEKNUM(E67,21)) -> 6 | E67: 45329 | F67: 6 | G67: =IF(E67="","",IF(E67=B67,"Ja","Nein")) -> Nein | H67: 1000457316 | I67: Antwerpen | J67: 126280 | K67: 105 | L67: Leaf | M67: Entladen | N67: 0.38402778 | O67: 0.5125 | P67: 0.53888889 | Q67: 0.55694444 | R67: Yes | S67: docs issue: keine Dokumente vorab erhalten | V67: =IF(N67="","",IF(O67="","",O67-N67)) -> 0.12847222 | W67: =IF(O67="","",IF(P67="","",P67-O67)) -> 0.026388889 | X67: =IF(P67="","",IF(N67="","",P67-N67)) -> 0.15486111 | Y67: =IF(N67="","",IF(Q67="","",Q67-N67)) -> 0.17291667
A68: =IF(B68="","",WEEKNUM(B68,21)) -> 6 | B68: 45328 | D68: =IF(E68="","",WEEKNUM(E68,21)) -> 6 | E68: 45328 | F68: 1 | G68: =IF(E68="","",IF(E68=B68,"Ja","Nein")) -> Ja | H68: 1000456907 | I68: Antwerpen | J68: 4702164990 | K68: 89 | L68: Leaf | M68: Entladen | N68: 0.27847222 | O68: 0.50694444 | P68: 0.53055556 | Q68: 0.53958333 | R68: Yes | S68: docs issue: keine Dokumente vorab erhalten | U68: T1- u. T2-Materialien auf einer Rechnung, muss getrennt sein, Mail an Verteiler um 7.10 Uhr
A69: =IF(B69="","",WEEKNUM(B69,21)) -> 6 | B69: 45329 | C69: 45329 | D69: =IF(E69="","",WEEKNUM(E69,21)) -> 6 | E69: 45329 | F69: 4 | G69: =IF(E69="","",IF(E69=B69,"Ja","Nein")) -> Ja | H69: 1000457314 | I69: Antwerpen | J69: 126274 | K69: 105 | L69: Leaf | M69: Entladen | N69: 0.33333333 | O69: 0.44583333 | P69: 0.46736111 | Q69: 0.55625 | R69: Yes | S69: docs issue: keine Dokumente vorab erhalten; muss auch verladen werden | V69: =IF(N69="","",IF(O69="","",O69-N69)) -> 0.1125 | W69: =IF(O69="","",IF(P69="","",P69-O69)) -> 0.021527778 | X69: =IF(P69="","",IF(N69="","",P69-N69)) -> 0.13402778 | Y69: =IF(N69="","",IF(Q69="","",Q69-N69)) -> 0.22291667
A70: =IF(B70="","",WEEKNUM(B70,21)) -> 6 | B70: 45329 | C70: 45329 | D70: =IF(E70="","",WEEKNUM(E70,21)) -> 6 | E70: 45329 | F70: 1 | G70: =IF(E70="","",IF(E70=B70,"Ja","Nein")) -> Ja | H70: 1000457315 | I70: Antwerpen | J70: 126278 | K70: 105 | L70: Leaf | M70: Entladen | N70: 0.27777778 | O70: 0.33888889 | P70: 0.36319444 | Q70: 0.45694444 | R70: Yes | S70: docs issue: keine Dokumente vorab erhalten; muss auch verladen werden | V70: =IF(N70="","",IF(O70="","",O70-N70)) -> 0.061111111 | W70: =IF(O70="","",IF(P70="","",P70-O70)) -> 0.024305556 | X70: =IF(P70="","",IF(N70="","",P70-N70)) -> 0.085416667 | Y70: =IF(N70="","",IF(Q70="","",Q70-N70)) -> 0.17916667
A71: =IF(B71="","",WEEKNUM(B71,21)) -> 6 | B71: 45329 | C71: 45329 | D71: =IF(E71="","",WEEKNUM(E71,21)) -> 6 | E71: 45329 | F71: 5 | G71: =IF(E71="","",IF(E71=B71,"Ja","Nein")) -> Ja | H71: 1000457321 | I71: Antwerpen | J71: 126279 | K71: 105 | L71: Leaf | M71: Entladen | N71: 0.37569444 | O71: 0.475 | P71: 0.50069444 | Q71: 0.60694444 | R71: Yes | S71: docs issue: keine Dokumente vorab erhalten; muss auch verladen werden | V71: =IF(N71="","",IF(O71="","",O71-N71)) -> 0.099305556 | W71: =IF(O71="","",IF(P71="","",P71-O71)) -> 0.025694444 | X71: =IF(P71="","",IF(N71="","",P71-N71)) -> 0.125 | Y71: =IF(N71="","",IF(Q71="","",Q71-N71)) -> 0.23125
A72: =IF(B72="","",WEEKNUM(B72,21)) -> 6 | B72: 45330 | C72: 45330 | D72: =IF(E72="","",WEEKNUM(E72,21)) -> 6 | E72: 45330 | F72: 1 | G72: =IF(E72="","",IF(E72=B72,"Ja","Nein")) -> Ja | H72: 1000457329 | I72: Antwerpen | J72: 126273 | K72: 105 | L72: Leaf | M72: Entladen | N72: 0.28958333 | O72: 0.32708333 | P72: 0.34583333 | Q72: 0.35277778 | R72: Yes | V72: =IF(N72="","",IF(O72="","",O72-N72)) -> 0.0375 | W72: =IF(O72="","",IF(P72="","",P72-O72)) -> 0.01875 | X72: =IF(P72="","",IF(N72="","",P72-N72)) -> 0.05625 | Y72: =IF(N72="","",IF(Q72="","",Q72-N72)) -> 0.063194444
A73: =IF(B73="","",WEEKNUM(B73,21)) -> 6 | B73: 45330 | C73: 45330 | D73: =IF(E73="","",WEEKNUM(E73,21)) -> 6 | E73: 45330 | F73: 3 | G73: =IF(E73="","",IF(E73=B73,"Ja","Nein")) -> Ja | H73: 1000457337 | I73: Antwerpen | J73: 126281 | K73: 105 | L73: Leaf | M73: Entladen | N73: 0.33819444 | O73: 0.39861111 | P73: 0.42569444 | Q73: 0.53125 | R73: Yes | S73: muss auch verladen werden | V73: =IF(N73="","",IF(O73="","",O73-N73)) -> 0.060416667 | W73: =IF(O73="","",IF(P73="","",P73-O73)) -> 0.027083333 | X73: =IF(P73="","",IF(N73="","",P73-N73)) -> 0.0875 | Y73: =IF(N73="","",IF(Q73="","",Q73-N73)) -> 0.19305556
A74: =IF(B74="","",WEEKNUM(B74,21)) -> 6 | B74: 45330 | D74: =IF(E74="","",WEEKNUM(E74,21)) -> 6 | E74: 45330 | G74: =IF(E74="","",IF(E74=B74,"Ja","Nein")) -> Ja | H74: 1000458097 | I74: Ploiesti | K74: 66 | L74: IBC | M74: Entladen | N74: 0.45486111 | O74: 0.46527778 | P74: 0.49305556 | Q74: 0.49305556 | V74: =IF(N74="","",IF(O74="","",O74-N74)) -> 0.010416667 | W74: =IF(O74="","",IF(P74="","",P74-O74)) -> 0.027777778 | X74: =IF(P74="","",IF(N74="","",P74-N74)) -> 0.038194444 | Y74: =IF(N74="","",IF(Q74="","",Q74-N74)) -> 0.038194444
A75: =IF(B75="","",WEEKNUM(B75,21)) -> 6 | B75: 45330 | D75: =IF(E75="","",WEEKNUM(E75,21)) -> 6 | E75: 45330 | G75: =IF(E75="","",IF(E75=B75,"Ja","Nein")) -> Ja | H75: 1000456454 | I75: Augustow | J75: 4702152891 | K75: 94 | L75: STEM | M75: Entladen | N75: 0.5 | O75: 0.52083333 | P75: 0.54166667 | Q75: 0.54166667 | V75: =IF(N75="","",IF(O75="","",O75-N75)) -> 0.020833333 | W75: =IF(O75="","",IF(P75="","",P75-O75)) -> 0.020833333 | X75: =IF(P75="","",IF(N75="","",P75-N75)) -> 0.041666667 | Y75: =IF(N75="","",IF(Q75="","",Q75-N75)) -> 0.041666667
A76: =IF(B76="","",WEEKNUM(B76,21)) -> 7 | B76: 45334 | C76: 45334 | D76: =IF(E76="","",WEEKNUM(E76,21)) -> 7 | E76: 45334 | F76: 2 | G76: =IF(E76="","",IF(E76=B76,"Ja","Nein")) -> Ja | H76: 1000457354 | I76: Antwerpen | J76: 126490 | K76: 100 | L76: Leaf | M76: Entladen | N76: 0.43333333 | O76: 0.45277778 | P76: 0.47847222 | Q76: 0.55555556 | R76: Yes | S76: docs issue: keine Dokumente vorab erhalten; muss auch verladen werden | V76: =IF(N76="","",IF(O76="","",O76-N76)) -> 0.019444444 | W76: =IF(O76="","",IF(P76="","",P76-O76)) -> 0.025694444 | X76: =IF(P76="","",IF(N76="","",P76-N76)) -> 0.045138889 | Y76: =IF(N76="","",IF(Q76="","",Q76-N76)) -> 0.12222222
A77: =IF(B77="","",WEEKNUM(B77,21)) -> 7 | B77: 45334 | C77: 45334 | D77: =IF(E77="","",WEEKNUM(E77,21)) -> 7 | E77: 45334 | F77: 1 | G77: =IF(E77="","",IF(E77=B77,"Ja","Nein")) -> Ja | H77: 1000457356 | I77: Antwerpen | J77: 126491 | K77: 105 | L77: Leaf | M77: Entladen | N77: 0.29236111 | O77: 0.33055556 | P77: 0.36180556 | Q77: 0.42430556 | R77: Yes | S77: docs issue: keine Dokumente vorab erhalten; muss auch verladen werden | V77: =IF(N77="","",IF(O77="","",O77-N77)) -> 0.038194444 | W77: =IF(O77="","",IF(P77="","",P77-O77)) -> 0.03125 | X77: =IF(P77="","",IF(N77="","",P77-N77)) -> 0.069444444 | Y77: =IF(N77="","",IF(Q77="","",Q77-N77)) -> 0.13194444
A78: =IF(B78="","",WEEKNUM(B78,21)) -> 7 | B78: 45334 | C78: 45335 | D78: =IF(E78="","",WEEKNUM(E78,21)) -> 7 | E78: 45338 | F78: 1 | G78: =IF(E78="","",IF(E78=B78,"Ja","Nein")) -> Nein | H78: 1000458357 | I78: Antwerpen | J78: 126592 | K78: 105 | L78: Leaf | M78: Entladen | N78: 0.27986111 | O78: 0.30208333 | P78: 0.32847222 | Q78: 0.44097222 | R78: Yes | S78: muss auch verladen werden | V78: =IF(N78="","",IF(O78="","",O78-N78)) -> 0.022222222 | W78: =IF(O78="","",IF(P78="","",P78-O78)) -> 0.026388889 | X78: =IF(P78="","",IF(N78="","",P78-N78)) -> 0.048611111 | Y78: =IF(N78="","",IF(Q78="","",Q78-N78)) -> 0.16111111
A79: =IF(B79="","",WEEKNUM(B79,21)) -> 7 | B79: 45335 | C79: 45335 | D79: =IF(E79="","",WEEKNUM(E79,21)) -> 7 | E79: 45335 | F79: 1 | G79: =IF(E79="","",IF(E79=B79,"Ja","Nein")) -> Ja | H79: 1000457512 | I79: Antwerpen | J79: 126493 | K79: 105 | L79: Leaf | M79: Entladen | N79: 0.37291667 | O79: 0.38611111 | P79: 0.40694444 | Q79: 0.49305556 | R79: Yes | S79: muss auch verladen werden | V79: =IF(N79="","",IF(O79="","",O79-N79)) -> 0.013194444 | W79: =IF(O79="","",IF(P79="","",P79-O79)) -> 0.020833333 | X79: =IF(P79="","",IF(N79="","",P79-N79)) -> 0.034027778 | Y79: =IF(N79="","",IF(Q79="","",Q79-N79)) -> 0.12013889
A80: =IF(B80="","",WEEKNUM(B80,21)) -> 7 | B80: 45335 | C80: 45335 | D80: =IF(E80="","",WEEKNUM(E80,21)) -> 7 | E80: 45335 | F80: 2 | G80: =IF(E80="","",IF(E80=B80,"Ja","Nein")) -> Ja | H80: 1000457511 | I80: Antwerpen | J80: 126492 | K80: 105 | L80: Leaf | M80: Entladen | N80: 0.37986111 | O80: 0.41458333 | P80: 0.44166667 | Q80: 0.45208333 | R80: Yes | V80: =IF(N80="","",IF(O80="","",O80-N80)) -> 0.034722222 | W80: =IF(O80="","",IF(P80="","",P80-O80)) -> 0.027083333 | X80: =IF(P80="","",IF(N80="","",P80-N80)) -> 0.061805556 | Y80: =IF(N80="","",IF(Q80="","",Q80-N80)) -> 0.072222222
A81: =IF(B81="","",WEEKNUM(B81,21)) -> 7 | B81: 45335 | D81: =IF(E81="","",WEEKNUM(E81,21)) -> 7 | E81: 45335 | F81: 3 | G81: =IF(E81="","",IF(E81=B81,"Ja","Nein")) -> Ja | H81: 1000459486 | I81: Kroatien | J81: 4601387583 | K81: 100 | L81: Leaf | M81: Entladen | N81: 0.49930556 | O81: 0.51388889 | P81: 0.52986111 | Q81: 0.61041667 | R81: Yes | S81: muss auch verladen werden | V81: =IF(N81="","",IF(O81="","",O81-N81)) -> 0.014583333 | W81: =IF(O81="","",IF(P81="","",P81-O81)) -> 0.015972222 | X81: =IF(P81="","",IF(N81="","",P81-N81)) -> 0.030555556 | Y81: =IF(N81="","",IF(Q81="","",Q81-N81)) -> 0.11111111
A82: =IF(B82="","",WEEKNUM(B82,21)) -> 7 | B82: 45336 | C82: 45336 | D82: =IF(E82="","",WEEKNUM(E82,21)) -> 7 | E82: 45337 | F82: 1 | G82: =IF(E82="","",IF(E82=B82,"Ja","Nein")) -> Nein | H82: 1000457513 | I82: Antwerpen | J82: 126495 | K82: 105 | L82: Leaf | M82: Entladen | N82: 0.30347222 | O82: 0.32569444 | P82: 0.34861111 | Q82: 0.35625 | R82: Yes | S82: docs issue: keine Dokumente vorab erhalten; Fahrer kam zu spät, wird am 15.02. abgeladen | V82: =IF(N82="","",IF(O82="","",O82-N82)) -> 0.022222222 | W82: =IF(O82="","",IF(P82="","",P82-O82)) -> 0.022916667 | X82: =IF(P82="","",IF(N82="","",P82-N82)) -> 0.045138889 | Y82: =IF(N82="","",IF(Q82="","",Q82-N82)) -> 0.052777778
A83: =IF(B83="","",WEEKNUM(B83,21)) -> 7 | B83: 45336 | C83: 45336 | D83: =IF(E83="","",WEEKNUM(E83,21)) -> 7 | E83: 45337 | F83: 2 | G83: =IF(E83="","",IF(E83=B83,"Ja","Nein")) -> Nein | H83: 1000457514 | I83: Antwerpen | J83: 126496 | K83: 105 | L83: Leaf | M83: Entladen | N83: 0.30902778 | O83: 0.35555556 | P83: 0.38055556 | Q83: 0.39097222 | R83: Yes | S83: docs issue: keine Dokumente vorab erhalten | V83: =IF(N83="","",IF(O83="","",O83-N83)) -> 0.046527778 | W83: =IF(O83="","",IF(P83="","",P83-O83)) -> 0.025 | X83: =IF(P83="","",IF(N83="","",P83-N83)) -> 0.071527778 | Y83: =IF(N83="","",IF(Q83="","",Q83-N83)) -> 0.081944444
A84: =IF(B84="","",WEEKNUM(B84,21)) -> 7 | B84: 45336 | C84: 45336 | D84: =IF(E84="","",WEEKNUM(E84,21)) -> 7 | E84: 45336 | F84: 1 | G84: =IF(E84="","",IF(E84=B84,"Ja","Nein")) -> Ja | H84: 1000458362 | I84: Antwerpen | J84: 126593 | K84: 105 | L84: Leaf | M84: Entladen | N84: 0.30833333 | O84: 0.32152778 | P84: 0.34722222 | Q84: 0.45069444 | R84: Yes | S84: docs issue: keine Dokumente vorab erhalten; muss auch verladen werden | V84: =IF(N84="","",IF(O84="","",O84-N84)) -> 0.013194444 | W84: =IF(O84="","",IF(P84="","",P84-O84)) -> 0.025694444 | X84: =IF(P84="","",IF(N84="","",P84-N84)) -> 0.038888889 | Y84: =IF(N84="","",IF(Q84="","",Q84-N84)) -> 0.14236111
A85: =IF(B85="","",WEEKNUM(B85,21)) -> 7 | B85: 45337 | C85: 45337 | D85: =IF(E85="","",WEEKNUM(E85,21)) -> 7 | E85: 45337 | F85: 3 | G85: =IF(E85="","",IF(E85=B85,"Ja","Nein")) -> Ja | H85: 1000457515 | I85: Antwerpen | J85: 126494 | K85: 105 | L85: Leaf | M85: Entladen | N85: 0.37777778 | O85: 0.39375 | P85: 0.42291667 | Q85: 0.51180556 | R85: Yes | S85: docs issue: keine Dokumente vorab erhalten; muss auch verladen werden | V85: =IF(N85="","",IF(O85="","",O85-N85)) -> 0.015972222 | W85: =IF(O85="","",IF(P85="","",P85-O85)) -> 0.029166667 | X85: =IF(P85="","",IF(N85="","",P85-N85)) -> 0.045138889 | Y85: =IF(N85="","",IF(Q85="","",Q85-N85)) -> 0.13402778
A86: =IF(B86="","",WEEKNUM(B86,21)) -> 7 | B86: 45337 | D86: =IF(E86="","",WEEKNUM(E86,21)) -> 7 | E86: 45337 | F86: 4 | G86: =IF(E86="","",IF(E86=B86,"Ja","Nein")) -> Ja | H86: 1000460053 | I86: Kroatien | J86: 4601387584 | K86: 108 | L86: Leaf | M86: Entladen | N86: 0.52708333 | O86: 0.53819444 | P86: 0.56388889 | Q86: 0.57291667 | R86: Yes | V86: =IF(N86="","",IF(O86="","",O86-N86)) -> 0.011111111 | W86: =IF(O86="","",IF(P86="","",P86-O86)) -> 0.025694444 | X86: =IF(P86="","",IF(N86="","",P86-N86)) -> 0.036805556 | Y86: =IF(N86="","",IF(Q86="","",Q86-N86)) -> 0.045833333
A87: =IF(B87="","",WEEKNUM(B87,21)) -> 7 | B87: 45337 | D87: =IF(E87="","",WEEKNUM(E87,21)) -> 7 | E87: 45337 | G87: =IF(E87="","",IF(E87=B87,"Ja","Nein")) -> Ja | I87: BASF | J87: 4500561460 | K87: 40 | L87: Rohware | M87: Entladen | N87: 0.36388889 | O87: 0.38194444 | P87: 0.39583333 | Q87: 0.39583333
A88: =IF(B88="","",WEEKNUM(B88,21)) -> 7 | B88: 45337 | D88: =IF(E88="","",WEEKNUM(E88,21)) -> 7 | E88: 45337 | G88: =IF(E88="","",IF(E88=B88,"Ja","Nein")) -> Ja | I88: Fehrbellin | J88: 4500558440 | K88: 10 | L88: Rohware | M88: Entladen | N88: 0.42638889 | O88: 0.43402778 | P88: 0.44791667 | Q88: 0.44791667
A89: =IF(B89="","",WEEKNUM(B89,21)) -> 7 | B89: 45338 | D89: =IF(E89="","",WEEKNUM(E89,21)) -> 7 | E89: 45338 | G89: =IF(E89="","",IF(E89=B89,"Ja","Nein")) -> Ja | I89: Schütz | K89: 93 | L89: IBC | M89: Entladen | O89: 0.35416667 | P89: 0.38888889 | Q89: 0.38888889 | S89: Fahrer hat sich nicht bei der Pforte Ost gemeldet!
A90: =IF(B90="","",WEEKNUM(B90,21)) -> 8 | B90: 45341 | C90: 45341 | D90: =IF(E90="","",WEEKNUM(E90,21)) -> 8 | E90: 45341 | F90: 1 | G90: =IF(E90="","",IF(E90=B90,"Ja","Nein")) -> Ja | H90: 1000458368 | I90: Antwerpen | J90: 126585 | K90: 105 | L90: Leaf | M90: Entladen | N90: 0.32361111 | O90: 0.33819444 | P90: 0.36597222 | Q90: 0.375 | R90: Yes | S90: docs issue: keine Dokumente vorab erhalten | V90: =IF(N90="","",IF(O90="","",O90-N90)) -> 0.014583333 | W90: =IF(O90="","",IF(P90="","",P90-O90)) -> 0.027777778 | X90: =IF(P90="","",IF(N90="","",P90-N90)) -> 0.042361111 | Y90: =IF(N90="","",IF(Q90="","",Q90-N90)) -> 0.051388889
A91: =IF(B91="","",WEEKNUM(B91,21)) -> 8 | B91: 45341 | C91: 45341 | D91: =IF(E91="","",WEEKNUM(E91,21)) -> 8 | E91: 45341 | F91: 2 | G91: =IF(E91="","",IF(E91=B91,"Ja","Nein")) -> Ja | H91: 1000458369 | I91: Antwerpen | J91: 126586 | K91: 105 | L91: Leaf | M91: Entladen | N91: 0.34513889 | O91: 0.375 | P91: 0.39791667 | Q91: 0.41041667 | R91: Yes | S91: docs issue: keine Dokumente vorab erhalten | V91: =IF(N91="","",IF(O91="","",O91-N91)) -> 0.029861111 | W91: =IF(O91="","",IF(P91="","",P91-O91)) -> 0.022916667 | X91: =IF(P91="","",IF(N91="","",P91-N91)) -> 0.052777778 | Y91: =IF(N91="","",IF(Q91="","",Q91-N91)) -> 0.065277778
A92: =IF(B92="","",WEEKNUM(B92,21)) -> 8 | B92: 45341 | D92: =IF(E92="","",WEEKNUM(E92,21)) -> 8 | E92: 45341 | F92: 3 | G92: =IF(E92="","",IF(E92=B92,"Ja","Nein")) -> Ja | H92: 1000460722 | I92: Kroatien | J92: 4702165952 | K92: 90 | L92: Leaf | M92: Entladen | N92: 0.34930556 | O92: 0.40277778 | P92: 0.42916667 | Q92: 0.43958333 | R92: Yes | V92: =IF(N92="","",IF(O92="","",O92-N92)) -> 0.053472222 | W92: =IF(O92="","",IF(P92="","",P92-O92)) -> 0.026388889 | X92: =IF(P92="","",IF(N92="","",P92-N92)) -> 0.079861111 | Y92: =IF(N92="","",IF(Q92="","",Q92-N92)) -> 0.090277778
A93: =IF(B93="","",WEEKNUM(B93,21)) -> 8 | B93: 45341 | C93: 45343 | D93: =IF(E93="","",WEEKNUM(E93,21)) -> 8 | E93: 45344 | F93: 1 | G93: =IF(E93="","",IF(E93=B93,"Ja","Nein")) -> Nein | H93: 1000458373 | I93: Antwerpen | J93: 126590 | K93: 105 | L93: Leaf | M93: Entladen | N93: 0.30208333 | O93: 0.33680556 | P93: 0.37013889 | Q93: 0.37638889 | R93: Yes | S93: docs issue: keine Dokumente vorab erhalten | V93: =IF(N93="","",IF(O93="","",O93-N93)) -> 0.034722222 | W93: =IF(O93="","",IF(P93="","",P93-O93)) -> 0.033333333 | X93: =IF(P93="","",IF(N93="","",P93-N93)) -> 0.068055556 | Y93: =IF(N93="","",IF(Q93="","",Q93-N93)) -> 0.074305556
A94: =IF(B94="","",WEEKNUM(B94,21)) -> 8 | B94: 45342 | C94: 45342 | D94: =IF(E94="","",WEEKNUM(E94,21)) -> 8 | E94: 45342 | F94: 1 | G94: =IF(E94="","",IF(E94=B94,"Ja","Nein")) -> Ja | H94: 1000458375 | I94: Antwerpen | J94: 126582 | K94: 105 | L94: Leaf | M94: Entladen | N94: 0.28263889 | O94: 0.30972222 | P94: 0.33333333 | Q94: 0.40416667 | R94: Yes | S94: muss auch verladen werden | V94: =IF(N94="","",IF(O94="","",O94-N94)) -> 0.027083333 | W94: =IF(O94="","",IF(P94="","",P94-O94)) -> 0.023611111 | X94: =IF(P94="","",IF(N94="","",P94-N94)) -> 0.050694444 | Y94: =IF(N94="","",IF(Q94="","",Q94-N94)) -> 0.12152778
A95: =IF(B95="","",WEEKNUM(B95,21)) -> 8 | B95: 45342 | C95: 45342 | D95: =IF(E95="","",WEEKNUM(E95,21)) -> 8 | E95: 45342 | F95: 2 | G95: =IF(E95="","",IF(E95=B95,"Ja","Nein")) -> Ja | H95: 1000458376 | I95: Antwerpen | J95: 126583 | K95: 105 | L95: Leaf | M95: Entladen | N95: 0.28263889 | O95: 0.34375 | P95: 0.36805556 | Q95: 0.38541667 | R95: Yes | V95: =IF(N95="","",IF(O95="","",O95-N95)) -> 0.061111111 | W95: =IF(O95="","",IF(P95="","",P95-O95)) -> 0.024305556 | X95: =IF(P95="","",IF(N95="","",P95-N95)) -> 0.085416667 | Y95: =IF(N95="","",IF(Q95="","",Q95-N95)) -> 0.10277778
A96: =IF(B96="","",WEEKNUM(B96,21)) -> 8 | B96: 45342 | C96: 45342 | D96: =IF(E96="","",WEEKNUM(E96,21)) -> 8 | E96: 45342 | F96: 3 | G96: =IF(E96="","",IF(E96=B96,"Ja","Nein")) -> Ja | H96: 1000458377 | I96: Antwerpen | J96: 126584 | K96: 105 | L96: Leaf | M96: Entladen | N96: 0.47430556 | O96: 0.48888889 | P96: 0.51319444 | Q96: 0.55902778 | R96: Yes | S96: muss auch verladen werden | V96: =IF(N96="","",IF(O96="","",O96-N96)) -> 0.014583333 | W96: =IF(O96="","",IF(P96="","",P96-O96)) -> 0.024305556 | X96: =IF(P96="","",IF(N96="","",P96-N96)) -> 0.038888889 | Y96: =IF(N96="","",IF(Q96="","",Q96-N96)) -> 0.084722222
A97: =IF(B97="","",WEEKNUM(B97,21)) -> 8 | B97: 45343 | C97: 45343 | D97: =IF(E97="","",WEEKNUM(E97,21)) -> 8 | E97: 45343 | F97: 1 | G97: =IF(E97="","",IF(E97=B97,"Ja","Nein")) -> Ja | H97: 1000459274 | I97: Antwerpen | J97: 126577 | K97: 105 | L97: Leaf | M97: Entladen | N97: 0.28125 | O97: 0.32986111 | P97: 0.35763889 | Q97: 0.36458333 | R97: Yes | S97: docs issue: keine Dokumente vorab erhalten | V97: =IF(N97="","",IF(O97="","",O97-N97)) -> 0.048611111 | W97: =IF(O97="","",IF(P97="","",P97-O97)) -> 0.027777778 | X97: =IF(P97="","",IF(N97="","",P97-N97)) -> 0.076388889 | Y97: =IF(N97="","",IF(Q97="","",Q97-N97)) -> 0.083333333
A98: =IF(B98="","",WEEKNUM(B98,21)) -> 8 | B98: 45343 | C98: 45343 | D98: =IF(E98="","",WEEKNUM(E98,21)) -> 8 | E98: 45343 | F98: 2 | G98: =IF(E98="","",IF(E98=B98,"Ja","Nein")) -> Ja | H98: 1000459275 | I98: Antwerpen | J98: 126578 | K98: 103 | L98: Leaf | M98: Entladen | N98: 0.29513889 | O98: 0.37152778 | P98: 0.40555556 | Q98: 0.41666667 | R98: Yes | S98: docs issue: keine Dokumente vorab erhalten | V98: =IF(N98="","",IF(O98="","",O98-N98)) -> 0.076388889 | W98: =IF(O98="","",IF(P98="","",P98-O98)) -> 0.034027778 | X98: =IF(P98="","",IF(N98="","",P98-N98)) -> 0.11041667 | Y98: =IF(N98="","",IF(Q98="","",Q98-N98)) -> 0.12152778
A99: =IF(B99="","",WEEKNUM(B99,21)) -> 8 | B99: 45343 | C99: 45343 | D99: =IF(E99="","",WEEKNUM(E99,21)) -> 8 | E99: 45343 | F99: 3 | G99: =IF(E99="","",IF(E99=B99,"Ja","Nein")) -> Ja | H99: 1000459276 | I99: Antwerpen | J99: 126587 | K99: 103 | L99: Leaf | M99: Entladen | N99: 0.46180556 | O99: 0.47986111 | P99: 0.51180556 | Q99: 0.51736111 | R99: Yes | S99: docs issue: keine Dokumente vorab erhalten | V99: =IF(N99="","",IF(O99="","",O99-N99)) -> 0.018055556 | W99: =IF(O99="","",IF(P99="","",P99-O99)) -> 0.031944444 | X99: =IF(P99="","",IF(N99="","",P99-N99)) -> 0.05 | Y99: =IF(N99="","",IF(Q99="","",Q99-N99)) -> 0.055555556
A100: =IF(B100="","",WEEKNUM(B100,21)) -> 8 | B100: 45343 | D100: =IF(E100="","",WEEKNUM(E100,21)) -> 8 | E100: 45343 | F100: 4 | G100: =IF(E100="","",IF(E100=B100,"Ja","Nein")) -> Ja | H100: 1000460804 | I100: Kroatien | J100: 4601394577 | K100: 108 | L100: Leaf | M100: Entladen | N100: 0.53611111 | O100: 0.54861111 | P100: 13:48 | Q100: 0.57986111 | R100: Yes | S100: docs issue: keine Dokumente vorab erhalten | V100: =IF(N100="","",IF(O100="","",O100-N100)) -> 0.0125 | W100: =IF(O100="","",IF(P100="","",P100-O100)) -> #VALUE! | X100: =IF(P100="","",IF(N100="","",P100-N100)) -> #VALUE! | Y100: =IF(N100="","",IF(Q100="","",Q100-N100)) -> 0.04375
...

Sheet Outbound_Monitor
A1: Auto | B1: Auto | C1: Auto | D1: Ladeplan | E1: Büro | F1: Ladeplan | G1: Büro/Ladeplan | H1: Ladeplan | I1: Ladeplan | J1: Ladeplan | K1: Ladeplan | L1: Ladeplan | M1: Ladeplan | N1: Büro | O1: Büro | P1: Ladeplan | Q1: Ladeplan | R1: Büro | S1: Büro | T1: Büro | U1: Büro | V1: Büro | W1: Büro | X1: Büro | Y1: Büro | Z1: Büro | AA1: Echtzeit Büro | AB1: Echtzeit Büro | AC1: Echtzeit Büro | AD1: Echtzeit Büro | AE1: Echtzeit Lager | AF1: Echtzeit Lager | AG1: Echtzeit Lager | AH1: Büro | AI1: Büro | AJ1: Echtzeit Büro | AK1: Echtzeit Büro | AL1: Echtzeit Büro | AM1: Echtzeit Büro | AN1: Auto | AO1: Auto | AP1: Auto | AQ1: Büro | AR1: Auto | AS1: Büro
A2: KW Plan | B2: KW Update | C2: Timeslot getroffen (Ja / Nein) | D2: PO | E2: Name Navi + kleine Notizen | F2: Plant | G2: Pal/Box | H2: Material Group: Diet CAF Staub Presize Rohware | I2: Source | J2: Destination | K2: Container Type Luftfracht = "AIR" Seefracht = "SEA" | L2: Loading date week | M2: Loading Date Plan DHL | N2: Loading time | O2: SCI | P2: Carrier | Q2: Status | R2: Delivery Note + MISSING STOCK | S2: Abholdatum Update | T2: DN erhalten Datum | U2: DN erhalten Uhrzeit | V2: GI | W2: DHL Express Tracker | X2: Ort Süden/Norden | Y2: Status Verladung | Z2: Verschoben | AA2: Auftrag fertig fürs Lager | AB2: Ankunft Office Datum | AC2: Ankunft Office Uhrzeit | AD2: Ladebeginn | AE2: Ladeende | AF2: Dokumente fertig und dem Fahrer überreicht | AG2: Störungen beim Förderband | AH2: Bemerkungen Büro | AI2: OTM Probleme | AJ2: 1. Ankunft Office Datum | AK2: Ankunft Office Uhrzeit | AL2: 2. Ankunft Office Datum | AM2: Ankunft Office Uhrzeit | AN2: Wartezeit bis Ladebeginn | AO2: Dauer der Verladung | AP2: Dauer von Ankuft bis Ladeende | AQ2: Bemerkungen Lager | AR2: Wochentag lt. Plan | AS2: Ursprüngliches Ladedatum
A3: nn | B3: nn | C3: Ja/Nein | D3: No. | E3: Text | G3: nn | H3: Mat. | I3: City/Country | J3: City/Country | K3: Text | M3: dd.mm.yy | N3: hh:mm | O3: 10000xxxxx | P3: Text | Q3: Text | R3: No. | S3: dd.mm.yy | T3: dd.mm.yy | U3: hh:mm | V3: x | W3: x | X3: Text | Y3: Auswahlliste | Z3: x | AA3: dd:mm:yy | AB3: dd:mm:yy | AC3: hh:mm | AD3: hh:mm | AE3: hh:mm | AF3: hh:mm | AG3: Freitext | AH3: Freitext | AI3: Freitext | AJ3: dd:mm:yy | AK3: hh:mm | AL3: dd:mm:yy | AM3: hh:mm | AN3: hh:mm | AO3: hh:mm | AP3: hh:mm | AQ3: Freitext | AR3: ? | AS3: dd.mm.yy
A4: =IF(M4="","",WEEKNUM(M4,21)) -> 50 | B4: =IF(S4="","",WEEKNUM(S4,21)) -> 1 | D4: 4200211640 | E4: Magda Zusatzaufkleber? Mail "Request to attach warning sign on shipment" | G4: 1 | H4: CAF | J4: Korea 3 | K4: AIR | M4: 45275 | O4: - | P4: DHL Express | R4: 9185059263 | S4: 45294 | V4: x | W4: x | Y4: Verladen | AA4: 45293 | AC4: 0.48680556 | AD4: 0.49027778 | AE4: 0.49166667 | AN4: =IF(AC4="","Kein Eintrag",IF(AD4="","Kein Eintrag",AD4-AC4)) -> 0.0034722222 | AO4: =IF(AF4="","Kein Eintrag",IF(AD4="","Kein Eintrag",AF4-AD4)) -> Kein Eintrag | AP4: =IF(AF4="","Kein Eintrag",IF(AC4="","Kein Eintrag",AF4-AC4)) -> Kein Eintrag
A5: =IF(M5="","",WEEKNUM(M5,21)) -> 51 | B5: =IF(S5="","",WEEKNUM(S5,21)) -> 1 | D5: 4500505491 | E5: Magda Rücksendung 25 KG Lubrin | G5: 1 | H5: Rohware | J5: Givaudan 1 | K5: AIR | M5: 45280 | P5: DHL Express | R5: 9185078064 | S5: 45294 | V5: x | W5: x | Y5: Verladen | AA5: 45293 | AC5: 0.48680556 | AD5: 0.49513889 | AE5: 0.49861111 | AN5: =IF(AC5="","Kein Eintrag",IF(AD5="","Kein Eintrag",AD5-AC5)) -> 0.0083333333 | AO5: =IF(AF5="","Kein Eintrag",IF(AD5="","Kein Eintrag",AF5-AD5)) -> Kein Eintrag | AP5: =IF(AF5="","Kein Eintrag",IF(AC5="","Kein Eintrag",AF5-AC5)) -> Kein Eintrag
A6: =IF(M6="","",WEEKNUM(M6,21)) -> 1 | B6: =IF(S6="","",WEEKNUM(S6,21)) -> 1 | D6: 4702146147 | E6: Inga | G6: 1 | H6: CAF | J6: Kanfanar 1 | K6: AIR | M6: 45294 | O6: - | P6: DHL Express | R6: 9184943892 | S6: 45294 | V6: x | W6: x | Y6: Verladen | AA6: 45293 | AC6: 0.48680556 | AD6: 0.49236111 | AE6: 0.49444444
A7: =IF(M7="","",WEEKNUM(M7,21)) -> 1 | B7: =IF(S7="","",WEEKNUM(S7,21)) -> 1 | D7: 4100038296 | E7: Magda Preise passen jetzt - kann navigiert werden, E-Mail by Annie am 03.01. um 13:15 Uhr | F7: TR45 | G7: 102 | H7: Diet | I7: Bayreuth | J7: Gebze 1 | K7: Box Trailer | L7: 1 | M7: 45295 | O7: 1000448075 | P7: GOPET | Q7: CONFIRMED | R7: 9185038111 | S7: 45295 | V7: x | X7: süden | Y7: Verladen | AA7: 45294 | AB7: 45295 | AC7: 0.39236111 | AD7: 0.45833333 | AE7: 0.5 | AF7: 0.59722222 | AN7: =IF(AC7="","Kein Eintrag",IF(AD7="","Kein Eintrag",AD7-AC7)) -> 0.065972222 | AO7: =IF(AF7="","Kein Eintrag",IF(AD7="","Kein Eintrag",AF7-AD7)) -> 0.13888889 | AP7: =IF(AF7="","Kein Eintrag",IF(AC7="","Kein Eintrag",AF7-AC7)) -> 0.20486111
A8: =IF(M8="","",WEEKNUM(M8,21)) -> 1 | B8: =IF(S8="","",WEEKNUM(S8,21)) -> 1 | D8: 4100038301 | E8: Magda Preise passen jetzt - kann navigiert werden, E-Mail by Annie am 03.01. um 13:15 Uhr | F8: TR45 | G8: 102 | H8: Diet | I8: Bayreuth | J8: Gebze 2 | K8: Box Trailer | L8: 1 | M8: 45295 | O8: 1000448076 | P8: ASSTRA | Q8: CONFIRMED | R8: 9185088748 | S8: 45295 | V8: x | X8: Süden | Y8: Verladen | AA8: 45294 | AB8: 45295 | AC8: 0.28125 | AD8: 0.30208333 | AE8: 0.38888889 | AF8: 0.45833333 | AN8: =IF(AC8="","Kein Eintrag",IF(AD8="","Kein Eintrag",AD8-AC8)) -> 0.020833333 | AO8: =IF(AF8="","Kein Eintrag",IF(AD8="","Kein Eintrag",AF8-AD8)) -> 0.15625 | AP8: =IF(AF8="","Kein Eintrag",IF(AC8="","Kein Eintrag",AF8-AC8)) -> 0.17708333
A9: =IF(M9="","",WEEKNUM(M9,21)) -> 1 | B9: =IF(S9="","",WEEKNUM(S9,21)) -> 1 | D9: 4702083669 | E9: Alexander | F9: PL37 | G9: 102 | H9: Diet | I9: Bayreuth | J9: Poznan 1 | K9: Box Trailer | L9: 1 | M9: 45295 | O9: 1000448278 | P9: EUROGATE | Q9: CONFIRMED | R9: 9185035992 | S9: 45295 | V9: x | X9: süden | Y9: Verladen | AA9: 45293 | AB9: 45295 | AC9: 0.46875 | AD9: 0.52083333 | AE9: 0.55902778 | AF9: 0.6 | AN9: =IF(AC9="","Kein Eintrag",IF(AD9="","Kein Eintrag",AD9-AC9)) -> 0.052083333 | AO9: =IF(AF9="","Kein Eintrag",IF(AD9="","Kein Eintrag",AF9-AD9)) -> 0.079166667 | AP9: =IF(AF9="","Kein Eintrag",IF(AC9="","Kein Eintrag",AF9-AC9)) -> 0.13125
A10: =IF(M10="","",WEEKNUM(M10,21)) -> 1 | B10: =IF(S10="","",WEEKNUM(S10,21)) -> 1 | D10: 4702083687 | E10: Alexander | F10: PL37 | G10: 102 | H10: Diet | I10: Bayreuth | J10: Poznan 2 | K10: Box Trailer | L10: 1 | M10: 45295 | O10: 1000448279 | P10: EUROGATE | Q10: CONFIRMED | R10: 9185035993 | S10: 45295 | V10: x | X10: Süden | Y10: Verladen | AA10: 45293 | AB10: 45295 | AC10: 0.38541667 | AD10: 0.40625 | AE10: 0.4375 | AF10: 0.47638889 | AN10: =IF(AC10="","Kein Eintrag",IF(AD10="","Kein Eintrag",AD10-AC10)) -> 0.020833333 | AO10: =IF(AF10="","Kein Eintrag",IF(AD10="","Kein Eintrag",AF10-AD10)) -> 0.070138889 | AP10: =IF(AF10="","Kein Eintrag",IF(AC10="","Kein Eintrag",AF10-AC10)) -> 0.090972222
A11: =IF(M11="","",WEEKNUM(M11,21)) -> 1 | B11: =IF(S11="","",WEEKNUM(S11,21)) -> 1 | D11: 4702108619 | E11: Alexander | F11: HU12 | G11: 102 | H11: Diet | I11: Bayreuth | J11: Pecs 1 | K11: Box Trailer | L11: 1 | M11: 45295 | O11: 1000448867 | P11: LOG-IN | Q11: CONFIRMED | R11: 9185057402 | S11: 45295 | V11: x | X11: süden | Y11: Verladen | AA11: 45293 | AB11: 45295 | AC11: 0.52083333 | AD11: 0.57291667 | AE11: 0.59375 | AF11: 0.64166667 | AN11: =IF(AC11="","Kein Eintrag",IF(AD11="","Kein Eintrag",AD11-AC11)) -> 0.052083333 | AO11: =IF(AF11="","Kein Eintrag",IF(AD11="","Kein Eintrag",AF11-AD11)) -> 0.06875 | AP11: =IF(AF11="","Kein Eintrag",IF(AC11="","Kein Eintrag",AF11-AC11)) -> 0.12083333
A12: =IF(M12="","",WEEKNUM(M12,21)) -> 1 | B12: =IF(S12="","",WEEKNUM(S12,21)) -> 1 | D12: 4100038303 | E12: Magda | F12: TR45 | G12: 102 | H12: Diet | I12: Bayreuth | J12: Gebze 4 | K12: Box Trailer | L12: 1 | M12: 45296 | O12: 1000448271 | P12: DHL TURKEY | Q12: CONFIRMED | R12: 9185033172 | S12: 45295 | X12: süden | Y12: Verladen | AA12: 45295 | AB12: 45295 | AC12: 0.39583333 | AD12: 0.60416667 | AF12: 0.72777778 | AN12: =IF(AC12="","Kein Eintrag",IF(AD12="","Kein Eintrag",AD12-AC12)) -> 0.20833333 | AO12: =IF(AF12="","Kein Eintrag",IF(AD12="","Kein Eintrag",AF12-AD12)) -> 0.12361111 | AP12: =IF(AF12="","Kein Eintrag",IF(AC12="","Kein Eintrag",AF12-AC12)) -> 0.33194444
A13: =IF(M13="","",WEEKNUM(M13,21)) -> 1 | B13: =IF(S13="","",WEEKNUM(S13,21)) -> 1 | D13: 4200209553 | E13: Inga / Preise für 2024 sind ok | G13: 2 | H13: CAF | J13: Jordan 1 | K13: 20 FT | M13: 45294 | N13: 0.375 | O13: 1000448716 | P13: MSC | R13: 9184945836 | S13: 45295 | V13: x | X13: Süden | Y13: Verladen | AA13: 45293 | AB13: 45295 | AC13: 0.35763889 | AD13: 0.38194444 | AE13: 0.40625 | AN13: =IF(AC13="","Kein Eintrag",IF(AD13="","Kein Eintrag",AD13-AC13)) -> 0.024305556 | AO13: =IF(AF13="","Kein Eintrag",IF(AD13="","Kein Eintrag",AF13-AD13)) -> Kein Eintrag | AP13: =IF(AF13="","Kein Eintrag",IF(AC13="","Kein Eintrag",AF13-AC13)) -> Kein Eintrag
A14: =IF(M14="","",WEEKNUM(M14,21)) -> 1 | B14: =IF(S14="","",WEEKNUM(S14,21)) -> 1 | D14: 4100038302 | E14: Magda | F14: TR45 | G14: 102 | H14: Diet | I14: Bayreuth | J14: Gebze 3 | K14: Box Trailer | L14: 1 | M14: 45296 | O14: 1000448270 | P14: ASSTRA | Q14: CONFIRMED | R14: 9185085514 | S14: 45296 | V14: x | X14: Süden | Y14: Verladen | AA14: 45295 | AB14: 45296 | AC14: 0.26736111 | AD14: 0.29166667 | AE14: 0.35763889 | AF14: 0.44791667 | AN14: =IF(AC14="","Kein Eintrag",IF(AD14="","Kein Eintrag",AD14-AC14)) -> 0.024305556 | AO14: =IF(AF14="","Kein Eintrag",IF(AD14="","Kein Eintrag",AF14-AD14)) -> 0.15625 | AP14: =IF(AF14="","Kein Eintrag",IF(AC14="","Kein Eintrag",AF14-AC14)) -> 0.18055556
A15: =IF(M15="","",WEEKNUM(M15,21)) -> 1 | B15: =IF(S15="","",WEEKNUM(S15,21)) -> 1 | D15: 4702081695 | E15: Brauni, Fahrer hatte später seine Dokumente kommen, aufgrund eines Fehlers in SAP /isuse with GI posting on 05.01.2024 at 09:30 h | F15: HU12 | G15: 102 | H15: Diet | I15: Bayreuth | J15: Pecs 3 | K15: Box Trailer | L15: 1 | M15: 45296 | O15: 1000448868 | P15: LOG-IN | Q15: CONFIRMED | R15: 9184971913 | S15: 45296 | V15: x | X15: Süden | Y15: Verladen | AA15: 45294 | AB15: 45296 | AC15: 0.34027778 | AD15: 0.375 | AE15: 0.42708333 | AF15: 0.57291667 | AN15: =IF(AC15="","Kein Eintrag",IF(AD15="","Kein Eintrag",AD15-AC15)) -> 0.034722222 | AO15: =IF(AF15="","Kein Eintrag",IF(AD15="","Kein Eintrag",AF15-AD15)) -> 0.19791667 | AP15: =IF(AF15="","Kein Eintrag",IF(AC15="","Kein Eintrag",AF15-AC15)) -> 0.23263889
A16: =IF(M16="","",WEEKNUM(M16,21)) -> 1 | B16: =IF(S16="","",WEEKNUM(S16,21)) -> 1 | D16: 4702113220 | E16: Brauni | F16: RO33 | G16: 102 | H16: Diet | I16: Bayreuth | J16: Ploiesti 2 | K16: Box Trailer | L16: 1 | M16: 45296 | O16: 1000448277 | P16: AQUILA | Q16: CONFIRMED | R16: 9185067814 | S16: 45296 | V16: x | X16: Süden | Y16: Verladen | AA16: 45294 | AB16: 45296 | AC16: 0.38541667 | AD16: 0.4375 | AE16: 0.47222222 | AF16: 0.59375 | AN16: =IF(AC16="","Kein Eintrag",IF(AD16="","Kein Eintrag",AD16-AC16)) -> 0.052083333 | AO16: =IF(AF16="","Kein Eintrag",IF(AD16="","Kein Eintrag",AF16-AD16)) -> 0.15625 | AP16: =IF(AF16="","Kein Eintrag",IF(AC16="","Kein Eintrag",AF16-AC16)) -> 0.20833333
A17: =IF(M17="","",WEEKNUM(M17,21)) -> 1 | B17: =IF(S17="","",WEEKNUM(S17,21)) -> 1 | D17: 4702144181 | E17: Brauni | F17: PL37 | G17: 102 | H17: Diet | I17: Bayreuth | J17: Poznan 3 | K17: Box Trailer | L17: 1 | M17: 45296 | O17: 1000448280 | P17: EUROGATE | Q17: CONFIRMED | R17: 9185077314 | S17: 45296 | V17: x | X17: Süden | Y17: Verladen | AA17: 45294 | AB17: 45296 | AC17: 0.51041667 | AD17: 0.54166667 | AE17: 0.59375 | AF17: 0.64236111 | AN17: =IF(AC17="","Kein Eintrag",IF(AD17="","Kein Eintrag",AD17-AC17)) -> 0.03125 | AO17: =IF(AF17="","Kein Eintrag",IF(AD17="","Kein Eintrag",AF17-AD17)) -> 0.10069444 | AP17: =IF(AF17="","Kein Eintrag",IF(AC17="","Kein Eintrag",AF17-AC17)) -> 0.13194444
A18: =IF(M18="","",WEEKNUM(M18,21)) -> 1 | B18: =IF(S18="","",WEEKNUM(S18,21)) -> 1 | D18: 4702144183 | E18: Brauni | F18: PL37 | G18: 102 | H18: Diet | I18: Bayreuth | J18: Poznan 4 | K18: Box Trailer | L18: 1 | M18: 45296 | O18: 1000448281 | P18: EUROGATE | Q18: CONFIRMED | R18: 9185076411 | S18: 45296 | V18: x | X18: Süden | Y18: Verladen | AA18: 45294 | AB18: 45296 | AC18: 0.52777778 | AD18: 0.60416667 | AE18: 0.675 | AF18: 0.69097222 | AN18: =IF(AC18="","Kein Eintrag",IF(AD18="","Kein Eintrag",AD18-AC18)) -> 0.076388889 | AO18: =IF(AF18="","Kein Eintrag",IF(AD18="","Kein Eintrag",AF18-AD18)) -> 0.086805556 | AP18: =IF(AF18="","Kein Eintrag",IF(AC18="","Kein Eintrag",AF18-AC18)) -> 0.16319444
A19: =IF(M19="","",WEEKNUM(M19,21)) -> 1 | B19: =IF(S19="","",WEEKNUM(S19,21)) -> 2 | D19: 4702081694 | E19: Alexander | F19: HU12 | G19: 102 | H19: Diet | I19: Bayreuth | J19: Pecs 2 | K19: Box Trailer | L19: 1 | M19: 45296 | O19: 1000448870 | P19: LOG-IN | Q19: CONFIRMED | R19: 9185080997 | S19: 45299 | V19: x | X19: Süden | Y19: Verladen | AA19: 45293 | AB19: 45299 | AC19: 0.27777778 | AD19: 0.29166667 | AE19: 0.32291667 | AN19: =IF(AC19="","Kein Eintrag",IF(AD19="","Kein Eintrag",AD19-AC19)) -> 0.013888889 | AO19: =IF(AF19="","Kein Eintrag",IF(AD19="","Kein Eintrag",AF19-AD19)) -> Kein Eintrag | AP19: =IF(AF19="","Kein Eintrag",IF(AC19="","Kein Eintrag",AF19-AC19)) -> Kein Eintrag
A20: =IF(M20="","",WEEKNUM(M20,21)) -> 1 | B20: =IF(S20="","",WEEKNUM(S20,21)) -> 2 | D20: 4702108629 | E20: Brauni, kurze Fahr- und Schichtzeit hatte der LKW Fahrer am Freitag, 05.01.2024 | F20: HU12 | G20: 102 | H20: Diet | I20: Bayreuth | J20: Pecs 4 | K20: Box Trailer | L20: 1 | M20: 45296 | O20: 1000448869 | P20: LOG-IN | Q20: CONFIRMED | R20: 9185076410 | S20: 45299 | V20: x | X20: Süden | Y20: Verladen | AA20: 45294 | AB20: 45299 | AC20: 0.27777778 | AD20: 0.33333333 | AE20: 0.40625 | AJ20: 45296 | AK20: 0.54166667 | AN20: =IF(AC20="","Kein Eintrag",IF(AD20="","Kein Eintrag",AD20-AC20)) -> 0.055555556 | AO20: =IF(AF20="","Kein Eintrag",IF(AD20="","Kein Eintrag",AF20-AD20)) -> Kein Eintrag | AP20: =IF(AF20="","Kein Eintrag",IF(AC20="","Kein Eintrag",AF20-AC20)) -> Kein Eintrag
A21: =IF(M21="","",WEEKNUM(M21,21)) -> 2 | B21: =IF(S21="","",WEEKNUM(S21,21)) -> 2 | D21: 4702116766 | E21: Magda | G21: 68 | H21: Presize | J21: Ploiesti 12 | K21: Box Trailer | M21: 45299 | O21: 1000449066 | P21: SC VIOTRANS | R21: 9185092435 | S21: 45299 | V21: x | X21: Süden | Y21: Verladen | AA21: 45295 | AB21: 45299 | AC21: 0.29861111 | AD21: 0.375 | AE21: 0.41666667 | AN21: =IF(AC21="","Kein Eintrag",IF(AD21="","Kein Eintrag",AD21-AC21)) -> 0.076388889 | AO21: =IF(AF21="","Kein Eintrag",IF(AD21="","Kein Eintrag",AF21-AD21)) -> Kein Eintrag | AP21: =IF(AF21="","Kein Eintrag",IF(AC21="","Kein Eintrag",AF21-AC21)) -> Kein Eintrag
A22: =IF(M22="","",WEEKNUM(M22,21)) -> 2 | B22: =IF(S22="","",WEEKNUM(S22,21)) -> 2 | D22: 4702143217 | E22: Magda Siehe E-Mail STO TRACKER 4702143217 BAY>PECS 1 pallet 120 KG | G22: 1 | H22: Rohware | J22: Pecs 5 | K22: Thermo VAN | M22: 45299 | O22: 1000449195 | P22: UNIFLEX HUNGARY | R22: 9184850379 | S22: 45299 | V22: x | X22: Süden | Y22: Verladen | AA22: 45295 | AB22: 45299 | AC22: 0.61111111 | AD22: 0.625 | AE22: 0.62847222 | AH22: KT 19.12: Siehe E-Mail - bzgl. Personalmangel auf Januar verschoben | AN22: =IF(AC22="","Kein Eintrag",IF(AD22="","Kein Eintrag",AD22-AC22)) -> 0.013888889 | AO22: =IF(AF22="","Kein Eintrag",IF(AD22="","Kein Eintrag",AF22-AD22)) -> Kein Eintrag | AP22: =IF(AF22="","Kein Eintrag",IF(AC22="","Kein Eintrag",AF22-AC22)) -> Kein Eintrag
A23: =IF(M23="","",WEEKNUM(M23,21)) -> 2 | B23: =IF(S23="","",WEEKNUM(S23,21)) -> 2 | D23: 4702120119 | E23: Magda | G23: 1 | H23: CAF | J23: Kanfanar 31 | M23: 45299 | O23: 1000449382 | P23: Trans East | R23: 9185103876 | S23: 45299 | T23: 45299 | X23: Süden | Y23: Verladen | AA23: 45299 | AB23: 45299 | AC23: 0.48611111 | AD23: 0.51388889 | AE23: 0.52083333 | AF23: 0.52430556 | AN23: =IF(AC23="","Kein Eintrag",IF(AD23="","Kein Eintrag",AD23-AC23)) -> 0.027777778 | AO23: =IF(AF23="","Kein Eintrag",IF(AD23="","Kein Eintrag",AF23-AD23)) -> 0.010416667 | AP23: =IF(AF23="","Kein Eintrag",IF(AC23="","Kein Eintrag",AF23-AC23)) -> 0.038194444
A24: =IF(M24="","",WEEKNUM(M24,21)) -> 2 | B24: =IF(S24="","",WEEKNUM(S24,21)) -> 2 | D24: 4702081653 | E24: Brauni, LKW ist am 08-01-2024 nicht gekommen | F24: HR12 | G24: 102 | H24: Diet | I24: Bayreuth | J24: Kanfanar 1 | K24: Box Trailer | L24: 2 | M24: 45299 | N24: 45597 | O24: 1000449524 | P24: TRANSEAST | Q24: CONFIRMED | R24: 9185019274 | S24: 45300 | V24: x | X24: Süden | Y24: Verladen | AA24: 45299 | AB24: 45300 | AC24: 0.31597222 | AD24: 0.35555556 | AE24: 0.39722222 | AF24: 0.41875 | AN24: =IF(AC24="","Kein Eintrag",IF(AD24="","Kein Eintrag",AD24-AC24)) -> 0.039583333 | AO24: =IF(AF24="","Kein Eintrag",IF(AD24="","Kein Eintrag",AF24-AD24)) -> 0.063194444 | AP24: =IF(AF24="","Kein Eintrag",IF(AC24="","Kein Eintrag",AF24-AC24)) -> 0.10277778
A25: =IF(M25="","",WEEKNUM(M25,21)) -> 2 | B25: =IF(S25="","",WEEKNUM(S25,21)) -> 2 | D25: 4702081673 | E25: Inga | F25: HU12 | G25: 102 | H25: Diet | I25: Bayreuth | J25: Pecs 1 | K25: Box Trailer | L25: 2 | M25: 45300 | N25: 45597 | O25: 1000450126 | P25: LOG-IN | Q25: REQUESTED | R25: 9185129976 | S25: 45300 | V25: x | X25: süden | Y25: Verladen | AA25: 45299 | AB25: 45300 | AC25: 0.42708333 | AD25: 0.5 | AE25: 0.53472222 | AF25: 0.55416667 | AN25: =IF(AC25="","Kein Eintrag",IF(AD25="","Kein Eintrag",AD25-AC25)) -> 0.072916667 | AO25: =IF(AF25="","Kein Eintrag",IF(AD25="","Kein Eintrag",AF25-AD25)) -> 0.054166667 | AP25: =IF(AF25="","Kein Eintrag",IF(AC25="","Kein Eintrag",AF25-AC25)) -> 0.12708333
A26: =IF(M26="","",WEEKNUM(M26,21)) -> 2 | B26: =IF(S26="","",WEEKNUM(S26,21)) -> 2 | D26: 4702081675 | E26: Inga | F26: HU12 | G26: 102 | H26: Diet | I26: Bayreuth | J26: Pecs 2 | K26: Box Trailer | L26: 2 | M26: 45300 | N26: 45597 | O26: 1000449526 | P26: ESSERS | Q26: CONFIRMED | R26: 9185132517 | S26: 45300 | V26: x | X26: Süden | Y26: Verladen | AA26: 45299 | AB26: 45300 | AC26: 0.3125 | AD26: 0.33333333 | AE26: 0.36111111 | AF26: 0.38333333 | AN26: =IF(AC26="","Kein Eintrag",IF(AD26="","Kein Eintrag",AD26-AC26)) -> 0.020833333 | AO26: =IF(AF26="","Kein Eintrag",IF(AD26="","Kein Eintrag",AF26-AD26)) -> 0.05 | AP26: =IF(AF26="","Kein Eintrag",IF(AC26="","Kein Eintrag",AF26-AC26)) -> 0.070833333
A27: =IF(M27="","",WEEKNUM(M27,21)) -> 2 | B27: =IF(S27="","",WEEKNUM(S27,21)) -> 2 | D27: 4702112510 | E27: Inga | F27: RO33 | G27: 102 | H27: Diet | I27: Bayreuth | J27: Ploiesti 1 | K27: Box Trailer | L27: 2 | M27: 45300 | N27: 45627 | O27: 1000449527 | P27: AQUILA | Q27: CONFIRMED | R27: 9185101942 | S27: 45300 | V27: x | X27: Süden | Y27: Verladen | AA27: 45299 | AB27: 45300 | AC27: 0.32638889 | AD27: 0.41666667 | AE27: 0.46527778 | AF27: 0.49236111 | AN27: =IF(AC27="","Kein Eintrag",IF(AD27="","Kein Eintrag",AD27-AC27)) -> 0.090277778 | AO27: =IF(AF27="","Kein Eintrag",IF(AD27="","Kein Eintrag",AF27-AD27)) -> 0.075694444 | AP27: =IF(AF27="","Kein Eintrag",IF(AC27="","Kein Eintrag",AF27-AC27)) -> 0.16597222
A28: =IF(M28="","",WEEKNUM(M28,21)) -> 2 | B28: =IF(S28="","",WEEKNUM(S28,21)) -> 2 | D28: 4702120083 | E28: Magda war nicht gemeldet v. DHL am 08.01.2024 | F28: CAF | G28: 23 | H28: CAF | I28: Bayreuth | J28: Augustow 1 | K28: Thermo Truck | L28: Yes | M28: 45299 | O28: 1000449375 | P28: EUROGATE | Q28: 1000449375 | R28: 9185093949 | S28: 45300 | V28: x | X28: Süden | Y28: Verladen | AA28: 44934 | AB28: 45300 | AC28: 0.51388889 | AD28: 0.53125 | AE28: 0.55208333 | AF28: 0.57291667 | AN28: =IF(AC28="","Kein Eintrag",IF(AD28="","Kein Eintrag",AD28-AC28)) -> 0.017361111 | AO28: =IF(AF28="","Kein Eintrag",IF(AD28="","Kein Eintrag",AF28-AD28)) -> 0.041666667 | AP28: =IF(AF28="","Kein Eintrag",IF(AC28="","Kein Eintrag",AF28-AC28)) -> 0.059027778
A29: =IF(M29="","",WEEKNUM(M29,21)) -> 2 | B29: =IF(S29="","",WEEKNUM(S29,21)) -> 2 | D29: 4702116572 | E29: Magda war nicht gemeldet v. DHL am 08.01.2024 | G29: 37 | H29: CAF | J29: Ploiesti 35 | K29: Thermo Truck | M29: 45299 | O29: 1000449992 | P29: SC VIOTRANS | R29: 9185128540 | S29: 45300 | V29: x | X29: Süden | Y29: Verladen | AA29: 45299 | AB29: 45300 | AC29: 0.35763889 | AD29: 0.36805556 | AE29: 0.39583333 | AF29: 0.43055556 | AJ29: 45299 | AK29: 0.375 | AN29: =IF(AC29="","Kein Eintrag",IF(AD29="","Kein Eintrag",AD29-AC29)) -> 0.010416667 | AO29: =IF(AF29="","Kein Eintrag",IF(AD29="","Kein Eintrag",AF29-AD29)) -> 0.0625 | AP29: =IF(AF29="","Kein Eintrag",IF(AC29="","Kein Eintrag",AF29-AC29)) -> 0.072916667
A30: =IF(M30="","",WEEKNUM(M30,21)) -> 2 | B30: =IF(S30="","",WEEKNUM(S30,21)) -> 2 | D30: 4200208883 | E30: Inga war nicht gemeldet v. DHL am 08.01.2024 | F30: CAF | G30: 7 | H30: CAF | I30: Bayreuth | J30: Landskrona 1 | K30: Thermo Van | L30: Yes | M30: 45300 | O30: 1000449861 | P30: ASSTRA | Q30: 1000449861 | R30: 9185121530 | S30: 45300 | V30: x | X30: Süden | Y30: Verladen | AA30: 45300 | AB30: 45300 | AC30: 0.41666667 | AD30: 0.47569444 | AE30: 0.48263889 | AF30: 0.48958333 | AN30: =IF(AC30="","Kein Eintrag",IF(AD30="","Kein Eintrag",AD30-AC30)) -> 0.059027778 | AO30: =IF(AF30="","Kein Eintrag",IF(AD30="","Kein Eintrag",AF30-AD30)) -> 0.013888889 | AP30: =IF(AF30="","Kein Eintrag",IF(AC30="","Kein Eintrag",AF30-AC30)) -> 0.072916667
A31: =IF(M31="","",WEEKNUM(M31,21)) -> 2 | B31: =IF(S31="","",WEEKNUM(S31,21)) -> 2 | D31: 4200211128 | E31: Magda, LKW ist am 08-01-2024 nicht gekommen | F31: RS04 | G31: 102 | H31: Diet | I31: Bayreuth | J31: Vranje 1 | K31: Box Trailer | L31: 2 | M31: 45299 | N31: 45597 | O31: 1000449530 | P31: FERCAM | Q31: CONFIRMED | R31: 9185108040 | S31: 45301 | V31: x | X31: Süden | Y31: Verladen | AA31: 45296 | AB31: 45301 | AC31: 0.37847222 | AD31: 0.39583333 | AE31: 0.47222222 | AF31: 0.5625 | AN31: =IF(AC31="","Kein Eintrag",IF(AD31="","Kein Eintrag",AD31-AC31)) -> 0.017361111 | AO31: =IF(AF31="","Kein Eintrag",IF(AD31="","Kein Eintrag",AF31-AD31)) -> 0.16666667 | AP31: =IF(AF31="","Kein Eintrag",IF(AC31="","Kein Eintrag",AF31-AC31)) -> 0.18402778
A32: =IF(M32="","",WEEKNUM(M32,21)) -> 2 | B32: =IF(S32="","",WEEKNUM(S32,21)) -> 2 | D32: 4702081765 | E32: muss LEAF abladen Magda, LKW ist am 08-01-2024 nicht gekommen | F32: PL37 | G32: 102 | H32: Diet | I32: Bayreuth | J32: Poznan 1 | K32: Box Trailer | L32: 2 | M32: 45299 | N32: 45536 | O32: 1000449528 | P32: EUROGATE | Q32: CONFIRMED | R32: 9185078963 | S32: 45301 | V32: x | X32: Süden | Y32: Verladen | AA32: 45296 | AB32: 45301 | AC32: 0.38888889 | AD32: 0.52083333 | AE32: 0.55208333 | AF32: 0.58333333 | AN32: =IF(AC32="","Kein Eintrag",IF(AD32="","Kein Eintrag",AD32-AC32)) -> 0.13194444 | AO32: =IF(AF32="","Kein Eintrag",IF(AD32="","Kein Eintrag",AF32-AD32)) -> 0.0625 | AP32: =IF(AF32="","Kein Eintrag",IF(AC32="","Kein Eintrag",AF32-AC32)) -> 0.19444444
A33: =IF(M33="","",WEEKNUM(M33,21)) -> 2 | B33: =IF(S33="","",WEEKNUM(S33,21)) -> 2 | D33: 4702081654 | E33: Inga | F33: HR12 | G33: 102 | H33: Diet | I33: Bayreuth | J33: Kanfanar 2 | K33: Box Trailer | L33: 2 | M33: 45300 | N33: 45597 | O33: 1000449525 | P33: TRANSEAST | Q33: CONFIRMED | R33: 9185132516 | S33: 45301 | V33: x | X33: Süden | Y33: Verladen | AA33: 45299 | AB33: 45301 | AC33: 0.61458333 | AE33: 0.65277778 | AF33: 0.6875 | AN33: =IF(AC33="","Kein Eintrag",IF(AD33="","Kein Eintrag",AD33-AC33)) -> Kein Eintrag | AO33: =IF(AF33="","Kein Eintrag",IF(AD33="","Kein Eintrag",AF33-AD33)) -> Kein Eintrag | AP33: =IF(AF33="","Kein Eintrag",IF(AC33="","Kein Eintrag",AF33-AC33)) -> 0.072916667
A34: =IF(M34="","",WEEKNUM(M34,21)) -> 2 | B34: =IF(S34="","",WEEKNUM(S34,21)) -> 2 | D34: 4702083631 | E34: Inga | F34: PL37 | G34: 102 | H34: Diet | I34: Bayreuth | J34: Poznan 3 | K34: Box Trailer | L34: 2 | M34: 45300 | N34: 45566 | O34: 1000449529 | P34: EUROGATE | Q34: CONFIRMED | R34: 9185114494 | S34: 45301 | V34: x | X34: Süden | Y34: Verladen | AA34: 45299 | AB34: 45301 | AC34: 0.43055556 | AD34: 0.47916667 | AE34: 0.51041667 | AF34: 0.54166667 | AN34: =IF(AC34="","Kein Eintrag",IF(AD34="","Kein Eintrag",AD34-AC34)) -> 0.048611111 | AO34: =IF(AF34="","Kein Eintrag",IF(AD34="","Kein Eintrag",AF34-AD34)) -> 0.0625 | AP34: =IF(AF34="","Kein Eintrag",IF(AC34="","Kein Eintrag",AF34-AC34)) -> 0.11111111
A35: =IF(M35="","",WEEKNUM(M35,21)) -> 2 | B35: =IF(S35="","",WEEKNUM(S35,21)) -> 2 | D35: 4702116749 | E35: muss LEAF abladen Inga | G35: 68 | H35: Presize | J35: Poznan 20 | K35: Box Trailer | M35: 45300 | O35: 1000449462 | R35: 9185111010 | S35: 45301 | V35: x | X35: Süden | Y35: Verladen | AA35: 45299 | AB35: 45301 | AC35: 0.37152778 | AD35: 0.40972222 | AE35: 0.42708333 | AN35: =IF(AC35="","Kein Eintrag",IF(AD35="","Kein Eintrag",AD35-AC35)) -> 0.038194444 | AO35: =IF(AF35="","Kein Eintrag",IF(AD35="","Kein Eintrag",AF35-AD35)) -> Kein Eintrag | AP35: =IF(AF35="","Kein Eintrag",IF(AC35="","Kein Eintrag",AF35-AC35)) -> Kein Eintrag
A36: =IF(M36="","",WEEKNUM(M36,21)) -> 2 | B36: =IF(S36="","",WEEKNUM(S36,21)) -> 2 | D36: 4702083689 | E36: Magda | F36: PL37 | G36: 102 | H36: Diet | I36: Bayreuth | J36: Poznan 6 | K36: Box Trailer | L36: 2 | M36: 45302 | O36: 1000450125 | P36: FT LOGISTICS | Q36: CONFIRMED | R36: 9185114283 | S36: 45302 | V36: x | X36: Süden | Y36: Verladen | AA36: 45300 | AB36: 45302 | AC36: 0.56597222 | AD36: 0.58333333 | AE36: 0.60763889 | AF36: 0.64791667 | AN36: =IF(AC36="","Kein Eintrag",IF(AD36="","Kein Eintrag",AD36-AC36)) -> 0.017361111 | AO36: =IF(AF36="","Kein Eintrag",IF(AD36="","Kein Eintrag",AF36-AD36)) -> 0.064583333 | AP36: =IF(AF36="","Kein Eintrag",IF(AC36="","Kein Eintrag",AF36-AC36)) -> 0.081944444
A37: =IF(M37="","",WEEKNUM(M37,21)) -> 2 | B37: =IF(S37="","",WEEKNUM(S37,21)) -> 2 | D37: 4702146931 | E37: Magda / PRIO Soll am 10.01. abgeholt werden, Preis fehlt!!!!! E-Mail Am 10.01.2023 um 13:10 Uhr | F37: CH16 | G37: 18 | H37: Diet | I37: Bayreuth | J37: Boncourt 2 | K37: Box Trailer | L37: 2 | M37: 45302 | N37: PRIO | O37: 1000451078 | P37: LOG-IN | R37: 9185191090 | S37: 45302 | V37: x | X37: Süden | Y37: Verladen | AA37: 45301 | AB37: 45302 | AC37: 0.33333333 | AD37: 0.35416667 | AE37: 0.375 | AF37: 10:;15 | AN37: =IF(AC37="","Kein Eintrag",IF(AD37="","Kein Eintrag",AD37-AC37)) -> 0.020833333 | AO37: =IF(AF37="","Kein Eintrag",IF(AD37="","Kein Eintrag",AF37-AD37)) -> #VALUE! | AP37: =IF(AF37="","Kein Eintrag",IF(AC37="","Kein Eintrag",AF37-AC37)) -> #VALUE!
A38: =IF(M38="","",WEEKNUM(M38,21)) -> 2 | B38: =IF(S38="","",WEEKNUM(S38,21)) -> 2 | D38: 4200209665 | E38: Inga Driver: Roman Moravek Truck Plate: TIR-ZL-144 Chassi-Plate: HO-CT-3027 Cont. TXGU5524673 | G38: 19 | H38: CAF | J38: Samsun 1 | K38: SEA | M38: 45302 | N38: 0.41666667 | O38: 1000449952 | R38: 9185014113 | S38: 45302 | V38: x | X38: Süden | Y38: Verladen | AA38: 45300 | AB38: 45302 | AC38: 0.40277778 | AD38: 0.41666667 | AE38: 0.44791667 | AF38: 0.52083333 | AN38: =IF(AC38="","Kein Eintrag",IF(AD38="","Kein Eintrag",AD38-AC38)) -> 0.013888889 | AO38: =IF(AF38="","Kein Eintrag",IF(AD38="","Kein Eintrag",AF38-AD38)) -> 0.10416667 | AP38: =IF(AF38="","Kein Eintrag",IF(AC38="","Kein Eintrag",AF38-AC38)) -> 0.11805556 | AS38: 45302
A39: =IF(M39="","",WEEKNUM(M39,21)) -> 2 | B39: =IF(S39="","",WEEKNUM(S39,21)) -> 2 | D39: 4702154353 | E39: Inga | G39: 1 | H39: BBK | J39: Boncourt 2 | K39: Thermo Van | M39: 45302 | O39: 1000451155 | R39: 9185158487 | S39: 45302 | V39: x | X39: Süden | Y39: Verladen | AA39: 45302 | AB39: 45302 | AC39: 0.53819444 | AD39: 0.56944444 | AE39: 0.57291667 | AF39: 0.72916667
A40: =IF(M40="","",WEEKNUM(M40,21)) -> 2 | B40: =IF(S40="","",WEEKNUM(S40,21)) -> 2 | D40: 4702145226 | E40: ADR vorhanden Inga /ADR! Über 1000 Punkte! | F40: CAF | G40: 4 | H40: CAF | I40: Bayreuth | J40: Boncourt 1 | K40: Thermo Van | L40: Yes | M40: 45302 | O40: 1000450598 | P40: ASSTRA | R40: 9185119069 | S40: 45302 | V40: x | X40: Süden | Y40: Verladen | AA40: 45302 | AB40: 45302 | AC40: 0.52083333 | AD40: 0.53125 | AE40: 0.53472222 | AF40: 0.61458333 | AN40: =IF(AC40="","Kein Eintrag",IF(AD40="","Kein Eintrag",AD40-AC40)) -> 0.010416667 | AO40: =IF(AF40="","Kein Eintrag",IF(AD40="","Kein Eintrag",AF40-AD40)) -> 0.083333333 | AP40: =IF(AF40="","Kein Eintrag",IF(AC40="","Kein Eintrag",AF40-AC40)) -> 0.09375
A41: =IF(M41="","",WEEKNUM(M41,21)) -> 2 | B41: =IF(S41="","",WEEKNUM(S41,21)) -> 2 | D41: 4702081767 | E41: Magda,LKW ist am 10.01.24 und 11.01 nicht gekommen / Heike | F41: PL37 | G41: 102 | H41: Diet | I41: Bayreuth | J41: Poznan 2 | K41: Box Trailer | L41: 2 | M41: 45301 | N41: 45566 | O41: 1000450122 | P41: EUROGATE | Q41: REQUESTED | R41: 9185124246 | S41: 45303 | V41: x | X41: Süden | Y41: Verladen | AA41: 45300 | AB41: 45303 | AC41: 0.29513889 | AD41: 0.34375 | AE41: 0.375 | AN41: =IF(AC41="","Kein Eintrag",IF(AD41="","Kein Eintrag",AD41-AC41)) -> 0.048611111 | AO41: =IF(AF41="","Kein Eintrag",IF(AD41="","Kein Eintrag",AF41-AD41)) -> Kein Eintrag | AP41: =IF(AF41="","Kein Eintrag",IF(AC41="","Kein Eintrag",AF41-AC41)) -> Kein Eintrag
A42: =IF(M42="","",WEEKNUM(M42,21)) -> 2 | B42: =IF(S42="","",WEEKNUM(S42,21)) -> 2 | D42: 4702083633 | E42: Magda, LKW ist am 10.01-2024 und 11.01. nicht gekommen / Heike | F42: PL37 | G42: 102 | H42: Diet | I42: Bayreuth | J42: Poznan 5 | K42: Box Trailer | L42: 2 | M42: 45301 | N42: 45597 | O42: 1000450123 | P42: EUROGATE | Q42: CONFIRMED | R42: 9185114282 | S42: 45303 | V42: x | X42: Süden | Y42: Verladen | AA42: 45300 | AB42: 45303 | AC42: 0.42013889 | AD42: 0.4375 | AE42: 0.46875 | AN42: =IF(AC42="","Kein Eintrag",IF(AD42="","Kein Eintrag",AD42-AC42)) -> 0.017361111 | AO42: =IF(AF42="","Kein Eintrag",IF(AD42="","Kein Eintrag",AF42-AD42)) -> Kein Eintrag | AP42: =IF(AF42="","Kein Eintrag",IF(AC42="","Kein Eintrag",AF42-AC42)) -> Kein Eintrag
A43: =IF(M43="","",WEEKNUM(M43,21)) -> 2 | B43: =IF(S43="","",WEEKNUM(S43,21)) -> 2 | D43: 4702081696 | E43: Magda | F43: HU12 | G43: 102 | H43: Diet | I43: Bayreuth | J43: Pecs 3 | K43: Box Trailer | L43: 2 | M43: 45303 | O43: 1000450634 | P43: LOG-IN | Q43: CONFIRMED | R43: 9185132775 | S43: 45303 | V43: x | X43: Süden | Y43: Verladen | AA43: 45302 | AB43: 45303 | AC43: 0.55208333 | AD43: 0.56597222 | AE43: 0.59027778 | AN43: =IF(AC43="","Kein Eintrag",IF(AD43="","Kein Eintrag",AD43-AC43)) -> 0.013888889 | AO43: =IF(AF43="","Kein Eintrag",IF(AD43="","Kein Eintrag",AF43-AD43)) -> Kein Eintrag | AP43: =IF(AF43="","Kein Eintrag",IF(AC43="","Kein Eintrag",AF43-AC43)) -> Kein Eintrag
A44: =IF(M44="","",WEEKNUM(M44,21)) -> 2 | B44: =IF(S44="","",WEEKNUM(S44,21)) -> 2 | D44: 4702083637 | E44: Brauni | F44: PL37 | G44: 102 | H44: Diet | I44: Bayreuth | J44: Poznan 7 | K44: Box Trailer | L44: 2 | M44: 45303 | O44: 1000450649 | P44: FT LOGISTICS | Q44: CONFIRMED | R44: 9185112354 | S44: 45303 | V44: x | X44: Süden | Y44: Verladen | AA44: 45301 | AB44: 45303 | AC44: 0.27777778 | AD44: 0.29166667 | AE44: 0.32777778 | AN44: =IF(AC44="","Kein Eintrag",IF(AD44="","Kein Eintrag",AD44-AC44)) -> 0.013888889 | AO44: =IF(AF44="","Kein Eintrag",IF(AD44="","Kein Eintrag",AF44-AD44)) -> Kein Eintrag | AP44: =IF(AF44="","Kein Eintrag",IF(AC44="","Kein Eintrag",AF44-AC44)) -> Kein Eintrag
A45: =IF(M45="","",WEEKNUM(M45,21)) -> 2 | B45: =IF(S45="","",WEEKNUM(S45,21)) -> 2 | D45: 4200208817 | E45: Magda, docs also die PFI ist okay 10.01.2024 um 10:01 Uhr Please take note of the below customs details for 4200208817 // 1000450772 which should be included with the dispatch documentation. Dispatch will be on 11/01. Crossing border point (leaving EU) - HU Zahony / UA Chop HU 724000 Customs office of destination in Ukraine - UA305060 / zu spöt gekommen 16:35) Heike | G45: 39 | H45: CAF | J45: Prilucky 1 | K45: Thermo Truck | M45: 45302 | N45: PRIO | O45: 1000450772 | R45: 9185166544 | S45: 45303 | V45: x | X45: Süden | Y45: Verladen | AA45: 45301 | AB45: 45303 | AC45: 0.29166667 | AD45: 0.3125 | AE45: 0.34375 | AF45: 0.46875 | AN45: =IF(AC45="","Kein Eintrag",IF(AD45="","Kein Eintrag",AD45-AC45)) -> 0.020833333 | AO45: =IF(AF45="","Kein Eintrag",IF(AD45="","Kein Eintrag",AF45-AD45)) -> 0.15625 | AP45: =IF(AF45="","Kein Eintrag",IF(AC45="","Kein Eintrag",AF45-AC45)) -> 0.17708333
A46: =IF(M46="","",WEEKNUM(M46,21)) -> 2 | B46: =IF(S46="","",WEEKNUM(S46,21)) -> 2 | D46: 4702117920 | E46: ADR vorhanden!! 12.01.24 IT / Magda 9185174205 is for HU06 and 9185174206 is for HU08 Natcheva – Please note driver will need to go to HU06 first and then HU08. HU06: 7622, PÉCS DOHÁNY STR. 2 HU08: 7630, PÉCS FRANCIA STR. 2. | F46: CAF | G46: 21 + 11 | H46: CAF | I46: Bayreuth | J46: Pecs 50 | K46: Thermo Truck | L46: Yes | M46: 45303 | O46: 1000450645 | P46: BSJ LOGISTICS | Q46: ADR | R46: 9185174205 HU6/ 9185174206 HU8 | S46: 45303 | V46: x | X46: Süden | Y46: Verladen | AA46: 45302 | AB46: 45394 | AC46: 0.53472222 | AD46: 0.54513889 | AE46: 0.55555556 | AF46: 0.65972222 | AH46: Fahrer hatte kein ADR, deshalb Fahrer und Truck getauscht! 12.01.2024 IT | AJ46: 45394 | AK46: 0.41319444 | AN46: =IF(AC46="","Kein Eintrag",IF(AD46="","Kein Eintrag",AD46-AC46)) -> 0.010416667 | AO46: =IF(AF46="","Kein Eintrag",IF(AD46="","Kein Eintrag",AF46-AD46)) -> 0.11458333 | AP46: =IF(AF46="","Kein Eintrag",IF(AC46="","Kein Eintrag",AF46-AC46)) -> 0.125
A47: =IF(M47="","",WEEKNUM(M47,21)) -> 2 | B47: =IF(S47="","",WEEKNUM(S47,21)) -> 2 | D47: 4200209616 | E47: ADR vorhanden Inga / ADR! Über 1000 Punkte | F47: CAF | G47: 20 | H47: CAF | I47: Bayreuth | J47: Vranje 3 | K47: Thermo Truck | L47: Yes | M47: 45303 | O47: 1000450740 | P47: BSJ LOGISTICS | Q47: ADR | R47: 9185177157 | S47: 45303 | V47: x | X47: Süden | Y47: Verladen | AA47: 45301 | AB47: 45303 | AC47: 0.5 | AD47: 0.51388889 | AE47: 0.53819444 | AF47: 0.63194444 | AN47: =IF(AC47="","Kein Eintrag",IF(AD47="","Kein Eintrag",AD47-AC47)) -> 0.013888889 | AO47: =IF(AF47="","Kein Eintrag",IF(AD47="","Kein Eintrag",AF47-AD47)) -> 0.11805556 | AP47: =IF(AF47="","Kein Eintrag",IF(AC47="","Kein Eintrag",AF47-AC47)) -> 0.13194444
A48: =IF(M48="","",WEEKNUM(M48,21)) -> 2 | B48: =IF(S48="","",WEEKNUM(S48,21)) -> 2 | D48: 4200207969 | E48: Inga | F48: CAF | G48: 28 | H48: CAF | I48: Bayreuth | J48: Gebze 1 | K48: Thermo Truck | L48: No | M48: 45303 | O48: 1000450613 | P48: ASSTRA | R48: 9185167550 / 9185167551 | S48: 45303 | V48: x/x | X48: Süden | Y48: Verladen | AA48: 45302 | AB48: 45303 | AC48: 0.30902778 | AD48: 0.375 | AE48: 0.40625 | AF48: 0.625 | AN48: =IF(AC48="","Kein Eintrag",IF(AD48="","Kein Eintrag",AD48-AC48)) -> 0.065972222 | AO48: =IF(AF48="","Kein Eintrag",IF(AD48="","Kein Eintrag",AF48-AD48)) -> 0.25 | AP48: =IF(AF48="","Kein Eintrag",IF(AC48="","Kein Eintrag",AF48-AC48)) -> 0.31597222
A49: =IF(M49="","",WEEKNUM(M49,21)) -> 2 | B49: =IF(S49="","",WEEKNUM(S49,21)) -> 2 | D49: 4702120069 | E49: Inga | F49: CAF | G49: 20 | H49: CAF | I49: Bayreuth | J49: Ploiesti 2 | K49: Thermo Truck | L49: Yes | M49: 45303 | O49: 1000450616 | P49: SC VIOTRANS | R49: 9185161181 | S49: 45303 | V49: x | X49: Süden | Y49: Verladen | AA49: 45302 | AB49: 45303 | AC49: 0.37847222 | AD49: 0.42361111 | AE49: 0.44097222 | AF49: 0.47222222 | AN49: =IF(AC49="","Kein Eintrag",IF(AD49="","Kein Eintrag",AD49-AC49)) -> 0.045138889 | AO49: =IF(AF49="","Kein Eintrag",IF(AD49="","Kein Eintrag",AF49-AD49)) -> 0.048611111 | AP49: =IF(AF49="","Kein Eintrag",IF(AC49="","Kein Eintrag",AF49-AC49)) -> 0.09375
A50: =IF(M50="","",WEEKNUM(M50,21)) -> 2 | B50: =IF(S50="","",WEEKNUM(S50,21)) -> 3 | D50: 4100038739 | E50: Brauni | F50: RS04 | G50: 102 | H50: Diet | I50: Bayreuth | J50: Vranje 2 | K50: Box Trailer | L50: 2 | M50: 45303 | O50: 1000450719 | P50: FERCAM | Q50: CONFIRMED | R50: 9185114284 | S50: 45306 | X50: Süden | Y50: Verladen | AA50: 45302 | AB50: 45306 | AC50: 0.55902778 | AE50: 0.58333333 | AF50: 0.60763889 | AN50: =IF(AC50="","Kein Eintrag",IF(AD50="","Kein Eintrag",AD50-AC50)) -> Kein Eintrag | AO50: =IF(AF50="","Kein Eintrag",IF(AD50="","Kein Eintrag",AF50-AD50)) -> Kein Eintrag | AP50: =IF(AF50="","Kein Eintrag",IF(AC50="","Kein Eintrag",AF50-AC50)) -> 0.048611111
A51: =IF(M51="","",WEEKNUM(M51,21)) -> 2 | B51: =IF(S51="","",WEEKNUM(S51,21)) -> 3 | D51: 4200206526 | E51: Magda / ADR über 1000 P. | G51: 25 | H51: CAF | J51: KOREA 10 / Daten fehlen im OTM / 10:54 heike | K51: 40FT | M51: 45299 | N51: 0.45833333 | O51: 1000451768 | P51: MSC | R51: 9185122745 | S51: 45306 | V51: x | X51: Süden | Y51: Verladen | AA51: 45296 | AB51: 45306 | AC51: 0.54166667 | AD51: 0.55555556 | AE51: 0.59027778 | AF51: 0.73611111 | AN51: =IF(AC51="","Kein Eintrag",IF(AD51="","Kein Eintrag",AD51-AC51)) -> 0.013888889 | AO51: =IF(AF51="","Kein Eintrag",IF(AD51="","Kein Eintrag",AF51-AD51)) -> 0.18055556 | AP51: =IF(AF51="","Kein Eintrag",IF(AC51="","Kein Eintrag",AF51-AC51)) -> 0.19444444 | AS51: 45299
A52: =IF(M52="","",WEEKNUM(M52,21)) -> 2 | B52: =IF(S52="","",WEEKNUM(S52,21)) -> 3 | D52: 4702120118 | E52: Magda am 12.01.2024 nicht gekommen / Heike | F52: CAF | G52: 12 | H52: CAF | I52: Bayreuth | J52: Kanfanar 2 | K52: Thermo Van | L52: Yes | M52: 45303 | O52: 1000450770 | P52: TRANSEAST | R52: 9185176988 | S52: 45306 | V52: x | X52: Süden | Y52: Verladen | AA52: 45302 | AB52: 45306 | AC52: 0.53819444 | AD52: 0.59722222 | AE52: 0.61111111 | AF52: 0.66319444 | AN52: =IF(AC52="","Kein Eintrag",IF(AD52="","Kein Eintrag",AD52-AC52)) -> 0.059027778 | AO52: =IF(AF52="","Kein Eintrag",IF(AD52="","Kein Eintrag",AF52-AD52)) -> 0.065972222 | AP52: =IF(AF52="","Kein Eintrag",IF(AC52="","Kein Eintrag",AF52-AC52)) -> 0.125
A53: =IF(M53="","",WEEKNUM(M53,21)) -> 2 | B53: =IF(S53="","",WEEKNUM(S53,21)) -> 3 | D53: 4702135715 | E53: Brauni (v. 2023) | F53: CAF | G53: 5 | H53: CAF | I53: Bayreuth | J53: Southampton (R&D) | K53: Thermo Van | L53: No | M53: 45303 | O53: 1000451096 | P53: ART-SPEED | R53: 9184688983 | S53: 45306 | V53: x | X53: Süden | Y53: Verladen | AA53: 45268 | AB53: 45306 | AC53: 0.36805556 | AD53: 0.38541667 | AE53: 0.38888889 | AF53: 0.65277778 | AN53: =IF(AC53="","Kein Eintrag",IF(AD53="","Kein Eintrag",AD53-AC53)) -> 0.017361111 | AO53: =IF(AF53="","Kein Eintrag",IF(AD53="","Kein Eintrag",AF53-AD53)) -> 0.26736111 | AP53: =IF(AF53="","Kein Eintrag",IF(AC53="","Kein Eintrag",AF53-AC53)) -> 0.28472222
A54: =IF(M54="","",WEEKNUM(M54,21)) -> 3 | B54: =IF(S54="","",WEEKNUM(S54,21)) -> 3 | D54: 4200205564 | E54: Magda - PRIO, Zusatzaufkleber? Mail "Request to attach warning sign on shipment" - Neue Preise aktualisiert | G54: 23 | H54: CAF | J54: Korea 1 | K54: 40FT | M54: 45306 | N54: 0.375 | O54: 1000451443 | P54: MSC | R54: 9184837388 (neu 9185202350) | S54: 45306 | V54: x | X54: Süden | Y54: Verladen | AA54: 45278 | AB54: 45306 | AC54: 0.36458333 | AD54: 0.375 | AE54: 0.40625 | AF54: 0.58333333 | AJ54: 45278 | AK54: 0.33680556 | AN54: =IF(AC54="","Kein Eintrag",IF(AD54="","Kein Eintrag",AD54-AC54)) -> 0.010416667 | AO54: =IF(AF54="","Kein Eintrag",IF(AD54="","Kein Eintrag",AF54-AD54)) -> 0.20833333 | AP54: =IF(AF54="","Kein Eintrag",IF(AC54="","Kein Eintrag",AF54-AC54)) -> 0.21875 | AS54: 45278
A55: =IF(M55="","",WEEKNUM(M55,21)) -> 3 | B55: =IF(S55="","",WEEKNUM(S55,21)) -> 3 | D55: 4200205563 | E55: Magda - PRIO, Zusatzaufkleber? Mail "Request to attach warning sign on shipment" - Neue Preise aktualisiert | G55: 17 | H55: CAF | J55: Korea 2 / Daten im OTM nicht gepflegt bzw. dann falsch hinterlegt / 10:29 Heike | K55: 40FT | M55: 45306 | N55: 0.41666667 | O55: 1000451444 | P55: MSC | R55: 9184813297 (neu 9185200798) | S55: 45306 | V55: x | X55: Süden | Y55: Verladen | AA55: 45278 | AB55: 45306 | AC55: 0.60416667 | AD55: 0.625 | AE55: 0.65277778 | AF55: 0.63888889 | AN55: =IF(AC55="","Kein Eintrag",IF(AD55="","Kein Eintrag",AD55-AC55)) -> 0.020833333 | AO55: =IF(AF55="","Kein Eintrag",IF(AD55="","Kein Eintrag",AF55-AD55)) -> 0.013888889 | AP55: =IF(AF55="","Kein Eintrag",IF(AC55="","Kein Eintrag",AF55-AC55)) -> 0.034722222 | AS55: 45278
A56: =IF(M56="","",WEEKNUM(M56,21)) -> 3 | B56: =IF(S56="","",WEEKNUM(S56,21)) -> 3 | D56: 4702120081 | E56: Magda | F56: PL19 | G56: 12 | H56: CAF | I56: Bayreuth | J56: Augustow 1 | K56: Thermo Truck | L56: 3 | M56: 45306 | O56: 1000451457 | P56: EUROGATE | Q56: CONFIRMED | R56: 9185213311 | S56: 45306 | V56: x | X56: Süden | Y56: Verladen | AA56: 45303 | AB56: 45306 | AC56: 0.65625 | AD56: 0.67361111 | AE56: 0.69444444 | AF56: 0.73263889 | AN56: =IF(AC56="","Kein Eintrag",IF(AD56="","Kein Eintrag",AD56-AC56)) -> 0.017361111 | AO56: =IF(AF56="","Kein Eintrag",IF(AD56="","Kein Eintrag",AF56-AD56)) -> 0.059027778 | AP56: =IF(AF56="","Kein Eintrag",IF(AC56="","Kein Eintrag",AF56-AC56)) -> 0.076388889
A57: =IF(M57="","",WEEKNUM(M57,21)) -> 3 | B57: =IF(S57="","",WEEKNUM(S57,21)) -> 3 | D57: 4702083694 | E57: Magda | F57: PL37 | G57: 102 | H57: Diet | I57: Bayreuth | J57: Poznan 1 | K57: Box Trailer | L57: 3 | M57: 45306 | O57: 1000452195 | P57: FT LOGISTICS | Q57: REQUESTED | R57: 9185178004 | S57: 45307 | V57: x | X57: süden | Y57: Verladen | AA57: 45303 | AB57: 45307 | AC57: 0.35763889 | AD57: 0.41666667 | AE57: 0.45138889 | AF57: 0.47638889 | AN57: =IF(AC57="","Kein Eintrag",IF(AD57="","Kein Eintrag",AD57-AC57)) -> 0.059027778 | AO57: =IF(AF57="","Kein Eintrag",IF(AD57="","Kein Eintrag",AF57-AD57)) -> 0.059722222 | AP57: =IF(AF57="","Kein Eintrag",IF(AC57="","Kein Eintrag",AF57-AC57)) -> 0.11875
A58: =IF(M58="","",WEEKNUM(M58,21)) -> 3 | B58: =IF(S58="","",WEEKNUM(S58,21)) -> 3 | D58: 4702108630 | E58: Magda | F58: HU12 | G58: 102 | H58: Diet | I58: Bayreuth | J58: Pecs 1 | K58: Box Trailer | L58: 3 | M58: 45306 | O58: 1000452188 | P58: LOG-IN | Q58: CONFIRMED | R58: 9185197151 | S58: 45307 | V58: x | X58: Süden | Y58: Verladen | AA58: 45303 | AB58: 45307 | AC58: 0.33333333 | AD58: 0.34722222 | AE58: 0.375 | AF58: 0.41319444 | AN58: =IF(AC58="","Kein Eintrag",IF(AD58="","Kein Eintrag",AD58-AC58)) -> 0.013888889 | AO58: =IF(AF58="","Kein Eintrag",IF(AD58="","Kein Eintrag",AF58-AD58)) -> 0.065972222 | AP58: =IF(AF58="","Kein Eintrag",IF(AC58="","Kein Eintrag",AF58-AC58)) -> 0.079861111
A59: =IF(M59="","",WEEKNUM(M59,21)) -> 3 | B59: =IF(S59="","",WEEKNUM(S59,21)) -> 3 | D59: 4702081768 | E59: muss LEAF abladen missing stock for DN 9185199247 | F59: PL37 | G59: 102 | H59: Diet | I59: Bayreuth | J59: Poznan 2 | K59: Box Trailer | L59: 3 | M59: 45307 | O59: 1000452262 | P59: EUROGATE | Q59: CONFIRMED | R59: 9185199246/9185199247 | S59: 45307 | V59: x/x | X59: Süden | Y59: Verladen | AA59: 45307 | AB59: 45307 | AC59: 0.30208333 | AD59: 0.38541667 | AE59: 0.41319444 | AF59: 0.44791667 | AN59: =IF(AC59="","Kein Eintrag",IF(AD59="","Kein Eintrag",AD59-AC59)) -> 0.083333333 | AO59: =IF(AF59="","Kein Eintrag",IF(AD59="","Kein Eintrag",AF59-AD59)) -> 0.0625 | AP59: =IF(AF59="","Kein Eintrag",IF(AC59="","Kein Eintrag",AF59-AC59)) -> 0.14583333
A60: =IF(M60="","",WEEKNUM(M60,21)) -> 3 | B60: =IF(S60="","",WEEKNUM(S60,21)) -> 3 | D60: 4702083668 | E60: muss LEAF abladen Magda | F60: PL37 | G60: 102 | H60: Diet | I60: Bayreuth | J60: Poznan 3 | K60: Box Trailer | L60: 3 | M60: 45307 | O60: 1000452263 | P60: EUROGATE | Q60: CONFIRMED | R60: 9185189544 | S60: 45307 | V60: x | X60: Süden | Y60: Verladen | AA60: 45306 | AB60: 45307 | AC60: 0.39583333 | AD60: 0.46527778 | AE60: 0.5 | AF60: 0.52847222 | AN60: =IF(AC60="","Kein Eintrag",IF(AD60="","Kein Eintrag",AD60-AC60)) -> 0.069444444 | AO60: =IF(AF60="","Kein Eintrag",IF(AD60="","Kein Eintrag",AF60-AD60)) -> 0.063194444 | AP60: =IF(AF60="","Kein Eintrag",IF(AC60="","Kein Eintrag",AF60-AC60)) -> 0.13263889
A61: =IF(M61="","",WEEKNUM(M61,21)) -> 3 | B61: =IF(S61="","",WEEKNUM(S61,21)) -> 3 | D61: 4200208943 | E61: Inga | G61: 4 | H61: CAF | J61: Indonesia 1 | K61: 20FT | M61: 45307 | N61: 0.45833333 | O61: 1000446685 | P61: MSC | R61: 9184825136 | S61: 45307 | V61: x | X61: Süden | Y61: Verladen | AA61: 45275 | AB61: 45307 | AC61: 0.375 | AD61: 0.38541667 | AE61: 0.40625 | AF61: 0.55555556 | AN61: =IF(AC61="","Kein Eintrag",IF(AD61="","Kein Eintrag",AD61-AC61)) -> 0.010416667 | AO61: =IF(AF61="","Kein Eintrag",IF(AD61="","Kein Eintrag",AF61-AD61)) -> 0.17013889 | AP61: =IF(AF61="","Kein Eintrag",IF(AC61="","Kein Eintrag",AF61-AC61)) -> 0.18055556 | AS61: 45278
A62: =IF(M62="","",WEEKNUM(M62,21)) -> 2 | B62: =IF(S62="","",WEEKNUM(S62,21)) -> 3 | D62: 4702144185 | E62: muss LEAF abladen Magda am 12.01. nicht gekommen / Heike | F62: PL37 | G62: 102 | H62: Diet | I62: Bayreuth | J62: Poznan 4 | K62: Box Trailer | L62: 2 | M62: 45302 | O62: 1000450124 | P62: EUROGATE | Q62: REQUESTED | R62: 9185132765 | S62: 45308 | V62: x | X62: Süden | Y62: Verladen | AA62: 45300 | AB62: 45308 | AC62: 0.375 | AD62: 0.44791667 | AE62: 0.46875 | AF62: 0.5 | AN62: =IF(AC62="","Kein Eintrag",IF(AD62="","Kein Eintrag",AD62-AC62)) -> 0.072916667 | AO62: =IF(AF62="","Kein Eintrag",IF(AD62="","Kein Eintrag",AF62-AD62)) -> 0.052083333 | AP62: =IF(AF62="","Kein Eintrag",IF(AC62="","Kein Eintrag",AF62-AC62)) -> 0.125
A63: =IF(M63="","",WEEKNUM(M63,21)) -> 2 | B63: =IF(S63="","",WEEKNUM(S63,21)) -> 3 | D63: 4702083690 | E63: muss LEAF abladen Brauni am 12.01.2024 nicht gekommen / Heike | F63: PL37 | G63: 102 | H63: Diet | I63: Bayreuth | J63: Poznan 8 | K63: Box Trailer | L63: 2 | M63: 45303 | O63: 1000450718 | P63: EUROGATE | Q63: CONFIRMED | R63: 9185125311 | S63: 45308 | V63: x | X63: Süden | Y63: Verladen | AA63: 45301 | AB63: 45308 | AC63: 0.34722222 | AD63: 0.40625 | AE63: 0.43055556 | AF63: 0.48958333 | AN63: =IF(AC63="","Kein Eintrag",IF(AD63="","Kein Eintrag",AD63-AC63)) -> 0.059027778 | AO63: =IF(AF63="","Kein Eintrag",IF(AD63="","Kein Eintrag",AF63-AD63)) -> 0.083333333 | AP63: =IF(AF63="","Kein Eintrag",IF(AC63="","Kein Eintrag",AF63-AC63)) -> 0.14236111
A64: =IF(M64="","",WEEKNUM(M64,21)) -> 3 | B64: =IF(S64="","",WEEKNUM(S64,21)) -> 3 | D64: 4702108608 | E64: Magda / geladen aber kein eVD kommt am 18.01. wider | F64: HR12 | G64: 102 | H64: Diet | I64: Bayreuth | J64: Kanfanar 1 | K64: Box Trailer | L64: 3 | M64: 45308 | O64: 1000452265 | P64: TRANSEAST | Q64: CONFIRMED | R64: 9185205306 | S64: 45308 | X64: Süden | Y64: Verladen | AA64: 45307 | AB64: 45308 | AC64: 0.50347222 | AF64: 0.38541667 | AN64: =IF(AC64="","Kein Eintrag",IF(AD64="","Kein Eintrag",AD64-AC64)) -> Kein Eintrag | AO64: =IF(AF64="","Kein Eintrag",IF(AD64="","Kein Eintrag",AF64-AD64)) -> Kein Eintrag | AP64: =IF(AF64="","Kein Eintrag",IF(AC64="","Kein Eintrag",AF64-AC64)) -> -0.11805556
A65: =IF(M65="","",WEEKNUM(M65,21)) -> 3 | B65: =IF(S65="","",WEEKNUM(S65,21)) -> 3 | D65: 4200209234 | E65: Inga | F65: SE14 | G65: 2 | H65: CAF | I65: Bayreuth | J65: Landskrona 1 | K65: Thermo Van | L65: 3 | M65: 45308 | O65: 1000452140 | P65: ASSTRA | Q65: CONFIRMED | R65: 9185236289 | S65: 45308 | V65: x | X65: Süden | Y65: Verladen | AA65: 45306 | AB65: 45308 | AC65: 0.48263889 | AD65: 0.49305556 | AE65: 0.49652778 | AF65: 0.51041667 | AN65: =IF(AC65="","Kein Eintrag",IF(AD65="","Kein Eintrag",AD65-AC65)) -> 0.010416667 | AO65: =IF(AF65="","Kein Eintrag",IF(AD65="","Kein Eintrag",AF65-AD65)) -> 0.017361111 | AP65: =IF(AF65="","Kein Eintrag",IF(AC65="","Kein Eintrag",AF65-AC65)) -> 0.027777778
A66: =IF(M66="","",WEEKNUM(M66,21)) -> 3 | B66: =IF(S66="","",WEEKNUM(S66,21)) -> 3 | D66: 4702156069 | E66: ADR vorhanden Inga / Über 1000 Punkte / ADR! / kombi mit AUG 2 | G66: 3 | H66: CAF | J66: Augustow 3 | K66: Thermo Van | M66: 45308 | O66: 1000452646 | P66: ART-SPEED | R66: 9185255748 | S66: 45308 | V66: x | X66: Süden | Y66: Verladen | AA66: 45307 | AB66: 45308 | AC66: 0.40277778 | AD66: 0.57291667 | AE66: 0.58333333 | AF66: 0.65625
A67: =IF(M67="","",WEEKNUM(M67,21)) -> 3 | B67: =IF(S67="","",WEEKNUM(S67,21)) -> 3 | D67: 4702155842 | E67: Magda / Kombie mit AUG 3 | G67: 7 | H67: Rohware | J67: Augustow 2 | K67: Thermo VAN | M67: 45308 | O67: 1000452455 | P67: ??? | R67: 9185264942 | S67: 45308 | V67: x | X67: Süden | Y67: Verladen | AA67: 45306 | AB67: 45308 | AC67: 0.40277778 | AD67: 0.57291667 | AE67: 0.58333333 | AF67: 0.65625 | AN67: =IF(AC67="","Kein Eintrag",IF(AD67="","Kein Eintrag",AD67-AC67)) -> 0.17013889 | AO67: =IF(AF67="","Kein Eintrag",IF(AD67="","Kein Eintrag",AF67-AD67)) -> 0.083333333 | AP67: =IF(AF67="","Kein Eintrag",IF(AC67="","Kein Eintrag",AF67-AC67)) -> 0.25347222
A68: =IF(M68="","",WEEKNUM(M68,21)) -> 3 | B68: =IF(S68="","",WEEKNUM(S68,21)) -> 3 | D68: EMCS | E68: Wartungsarbeiten EMCS von 12:00 - 22:00 Uhr | J68: DBH | M68: 45308 | R68: INFO | S68: 45308 | Y68: Gestrichen | AN68: =IF(AC68="","Kein Eintrag",IF(AD68="","Kein Eintrag",AD68-AC68)) -> Kein Eintrag | AO68: =IF(AF68="","Kein Eintrag",IF(AD68="","Kein Eintrag",AF68-AD68)) -> Kein Eintrag | AP68: =IF(AF68="","Kein Eintrag",IF(AC68="","Kein Eintrag",AF68-AC68)) -> Kein Eintrag
A69: =IF(M69="","",WEEKNUM(M69,21)) -> 3 | B69: =IF(S69="","",WEEKNUM(S69,21)) -> 3 | D69: 4702081770 | E69: muss LEAF abladen Magda | F69: PL37 | G69: 102 | H69: Diet | I69: Bayreuth | J69: Poznan 5 | K69: Box Trailer | L69: 3 | M69: 45308 | O69: 1000452264 | P69: EUROGATE | Q69: CONFIRMED | R69: 9185208765 | S69: 45309 | V69: x | X69: Süden | Y69: Verladen | AA69: 45307 | AB69: 45309 | AC69: 0.30902778 | AD69: 0.35416667 | AE69: 0.38888889 | AF69: 0.42361111 | AN69: =IF(AC69="","Kein Eintrag",IF(AD69="","Kein Eintrag",AD69-AC69)) -> 0.045138889 | AO69: =IF(AF69="","Kein Eintrag",IF(AD69="","Kein Eintrag",AF69-AD69)) -> 0.069444444 | AP69: =IF(AF69="","Kein Eintrag",IF(AC69="","Kein Eintrag",AF69-AC69)) -> 0.11458333
A70: =IF(M70="","",WEEKNUM(M70,21)) -> 3 | B70: =IF(S70="","",WEEKNUM(S70,21)) -> 3 | D70: 4702112516 | E70: Magda | F70: PL37 | G70: 102 | H70: Diet | I70: Bayreuth | J70: Poznan 4 | K70: Box Trailer | L70: 3 | M70: 45309 | O70: 1000452273 | P70: FT LOGISTICS | Q70: REQUESTED | R70: 9185200707 | S70: 45309 | V70: x | X70: Süden | Y70: Verladen | AA70: 45308 | AB70: 45309 | AC70: 0.33333333 | AD70: 0.40625 | AE70: 0.43541667 | AN70: =IF(AC70="","Kein Eintrag",IF(AD70="","Kein Eintrag",AD70-AC70)) -> 0.072916667 | AO70: =IF(AF70="","Kein Eintrag",IF(AD70="","Kein Eintrag",AF70-AD70)) -> Kein Eintrag | AP70: =IF(AF70="","Kein Eintrag",IF(AC70="","Kein Eintrag",AF70-AC70)) -> Kein Eintrag
A71: =IF(M71="","",WEEKNUM(M71,21)) -> 3 | B71: =IF(S71="","",WEEKNUM(S71,21)) -> 3 | D71: 4702083648 | E71: missing stock for SKU 31185407, only 1680 kgs - Ben is informed about it 17.01. at 11:03 Uhr | F71: PL37 | G71: 102 | H71: Diet | I71: Bayreuth | J71: Poznan 6 | K71: Box Trailer | L71: 3 | M71: 45309 | O71: 1000452272 | P71: FT LOGISTICS | Q71: REQUESTED | R71: 9185188639 | S71: 45309 | V71: x | X71: süden | Y71: Verladen | AA71: 45309 | AB71: 45309 | AC71: 0.45833333 | AD71: 0.5 | AE71: 0.53819444 | AN71: =IF(AC71="","Kein Eintrag",IF(AD71="","Kein Eintrag",AD71-AC71)) -> 0.041666667 | AO71: =IF(AF71="","Kein Eintrag",IF(AD71="","Kein Eintrag",AF71-AD71)) -> Kein Eintrag | AP71: =IF(AF71="","Kein Eintrag",IF(AC71="","Kein Eintrag",AF71-AC71)) -> Kein Eintrag
A72: =IF(M72="","",WEEKNUM(M72,21)) -> 3 | B72: =IF(S72="","",WEEKNUM(S72,21)) -> 3 | D72: 4200210250 | E72: ADR vorhanden Inga / Über 1000 Punkte / ADR! | G72: 10 | H72: CAF | J72: Gebze 1 | K72: 20FT | M72: 45309 | N72: 0.375 | O72: 1000453108 | P72: MSC | R72: 9185234329 | S72: 45309 | V72: x | X72: Süden | Y72: Verladen | AA72: 45306 | AB72: 45309 | AC72: 0.39583333 | AD72: 0.42708333 | AE72: 0.45833333 | AF72: 0.54861111 | AN72: =IF(AC72="","Kein Eintrag",IF(AD72="","Kein Eintrag",AD72-AC72)) -> 0.03125 | AO72: =IF(AF72="","Kein Eintrag",IF(AD72="","Kein Eintrag",AF72-AD72)) -> 0.12152778 | AP72: =IF(AF72="","Kein Eintrag",IF(AC72="","Kein Eintrag",AF72-AC72)) -> 0.15277778
A73: =IF(M73="","",WEEKNUM(M73,21)) -> 3 | B73: =IF(S73="","",WEEKNUM(S73,21)) -> 3 | D73: 4200208952 | E73: Inga | H73: CAF | J73: Samsun 3 | K73: 40FT | M73: 45309 | N73: 0.45833333 | O73: 1000453180 | P73: MSC | R73: 9185226050 | S73: 45309 | V73: x | X73: Süden | Y73: Verladen | AB73: 45309 | AC73: 0.47222222 | AD73: 0.48263889 | AE73: 0.50694444 | AF73: 0.67708333 | AN73: =IF(AC73="","Kein Eintrag",IF(AD73="","Kein Eintrag",AD73-AC73)) -> 0.010416667 | AO73: =IF(AF73="","Kein Eintrag",IF(AD73="","Kein Eintrag",AF73-AD73)) -> 0.19444444 | AP73: =IF(AF73="","Kein Eintrag",IF(AC73="","Kein Eintrag",AF73-AC73)) -> 0.20486111
A74: =IF(M74="","",WEEKNUM(M74,21)) -> 3 | B74: =IF(S74="","",WEEKNUM(S74,21)) -> 3 | D74: 4702117946 | E74: ADR vorhanden ADR!!!!!!!!!!!! missing stock for TF-MUGGIN 220 kgs, still missing stock on 17.01. at 10:56 h, ART. ONEJAN mit 25 kgs wurde mit 20 kgs geplant, E-Mail an Jamie geschrieben, 17.01. um 11:13 Uhr | F74: RO33 | G74: 34 | H74: CAF | I74: Bayreuth | J74: Ploiesti 1 | K74: Thermo Truck | L74: 3 | M74: 45309 | O74: 1000452647 | P74: SORCANI | Q74: CONFIRMED | R74: 9185286029 / 9185308240 | S74: 45309 | V74: x/x | X74: Süden | Y74: Verladen | AA74: 45308 | AB74: 45309 | AC74: 0.32638889 | AD74: 0.33333333 | AE74: 0.375 | AF74: 0.45486111 | AJ74: 45308 | AK74: 0.4375 | AN74: =IF(AC74="","Kein Eintrag",IF(AD74="","Kein Eintrag",AD74-AC74)) -> 0.0069444444 | AO74: =IF(AF74="","Kein Eintrag",IF(AD74="","Kein Eintrag",AF74-AD74)) -> 0.12152778 | AP74: =IF(AF74="","Kein Eintrag",IF(AC74="","Kein Eintrag",AF74-AC74)) -> 0.12847222
A75: =IF(M75="","",WEEKNUM(M75,21)) -> 3 | B75: =IF(S75="","",WEEKNUM(S75,21)) -> 3 | D75: 4200209640 | E75: Magda, docs okay 16.01. at 14:24 Uhr | F75: UA01 | G75: 15 | H75: CAF | I75: Bayreuth | J75: Prilucky 1 | K75: Thermo Truck | L75: 3 | M75: 45309 | O75: 1000451802 | P75: EUROGATE | Q75: CONFIRMED | R75: 9185254222 | S75: 45309 | V75: x | X75: Süden | Y75: Verladen | AA75: 45308 | AB75: 45309 | AC75: 0.38888889 | AD75: 0.40625 | AE75: 0.41666667 | AF75: 0.65277778 | AN75: =IF(AC75="","Kein Eintrag",IF(AD75="","Kein Eintrag",AD75-AC75)) -> 0.017361111 | AO75: =IF(AF75="","Kein Eintrag",IF(AD75="","Kein Eintrag",AF75-AD75)) -> 0.24652778 | AP75: =IF(AF75="","Kein Eintrag",IF(AC75="","Kein Eintrag",AF75-AC75)) -> 0.26388889
A76: =IF(M76="","",WEEKNUM(M76,21)) -> 3 | B76: =IF(S76="","",WEEKNUM(S76,21)) -> 3 | D76: 4702112512 | E76: Brauni | F76: RO33 | G76: 102 | H76: Diet | I76: Bayreuth | J76: Ploiesti 2 | K76: Box Trailer | L76: 3 | M76: 45310 | O76: 1000452275 | P76: SC VIOTRANS | Q76: CONFIRMED | R76: 9185201558 | S76: 45310 | V76: x | X76: Süden | Y76: Verladen | AA76: 45309 | AB76: 45310 | AC76: 0.48263889 | AD76: 0.5 | AE76: 0.52083333 | AF76: 0.54166667 | AN76: =IF(AC76="","Kein Eintrag",IF(AD76="","Kein Eintrag",AD76-AC76)) -> 0.017361111 | AO76: =IF(AF76="","Kein Eintrag",IF(AD76="","Kein Eintrag",AF76-AD76)) -> 0.041666667 | AP76: =IF(AF76="","Kein Eintrag",IF(AC76="","Kein Eintrag",AF76-AC76)) -> 0.059027778
A77: =IF(M77="","",WEEKNUM(M77,21)) -> 3 | B77: =IF(S77="","",WEEKNUM(S77,21)) -> 3 | D77: 4702112513 | E77: Brauni | F77: RO33 | G77: 102 | H77: Diet | I77: Bayreuth | J77: Ploiesti 3 | K77: Box Trailer | L77: 3 | M77: 45310 | O77: 1000452276 | P77: AQUILA | Q77: CONFIRMED | R77: 9185197849 | S77: 45310 | V77: x | X77: Süden | Y77: Verladen | AA77: 45309 | AB77: 45310 | AC77: 0.63888889 | AD77: 0.64583333 | AE77: 0.65625 | AF77: 0.68194444 | AN77: =IF(AC77="","Kein Eintrag",IF(AD77="","Kein Eintrag",AD77-AC77)) -> 0.0069444444 | AO77: =IF(AF77="","Kein Eintrag",IF(AD77="","Kein Eintrag",AF77-AD77)) -> 0.036111111 | AP77: =IF(AF77="","Kein Eintrag",IF(AC77="","Kein Eintrag",AF77-AC77)) -> 0.043055556
A78: =IF(M78="","",WEEKNUM(M78,21)) -> 3 | B78: =IF(S78="","",WEEKNUM(S78,21)) -> 3 | D78: 4702131236 | E78: Brauni | F78: PL37 | G78: 102 | H78: Diet | I78: Bayreuth | J78: Poznan 7 | K78: Box Trailer | L78: 3 | M78: 45310 | O78: 1000452274 | P78: EUROGATE | Q78: CONFIRMED | R78: 9185302837 | S78: 45310 | V78: x | Y78: Verladen | AA78: 45309 | AB78: 45310 | AC78: 0.35416667 | AD78: 0.37361111 | AE78: 0.39930556 | AF78: 0.42013889 | AN78: =IF(AC78="","Kein Eintrag",IF(AD78="","Kein Eintrag",AD78-AC78)) -> 0.019444444 | AO78: =IF(AF78="","Kein Eintrag",IF(AD78="","Kein Eintrag",AF78-AD78)) -> 0.046527778 | AP78: =IF(AF78="","Kein Eintrag",IF(AC78="","Kein Eintrag",AF78-AC78)) -> 0.065972222
A79: =IF(M79="","",WEEKNUM(M79,21)) -> 3 | B79: =IF(S79="","",WEEKNUM(S79,21)) -> 3 | D79: 4200208951 | E79: ADR ist jetzt vorhanden 190124 IT/ KEIN ADR vorhanden Inga / Über 1000 Punkte / ADR! ist rausgefahren | G79: 21 | H79: CAF | J79: Gebze 2 | K79: 40FT | M79: 45309 | N79: 0.41666667 | O79: 1000453107 | P79: MSC | R79: 9185245415 | S79: 45310 | V79: x | X79: Süden | Y79: Verladen | AB79: 45310 | AC79: 0.36805556 | AD79: 0.38888889 | AE79: 0.41666667 | AF79: 0.48958333 | AJ79: 45309 | AK79: 0.40277778 | AN79: =IF(AC79="","Kein Eintrag",IF(AD79="","Kein Eintrag",AD79-AC79)) -> 0.020833333 | AO79: =IF(AF79="","Kein Eintrag",IF(AD79="","Kein Eintrag",AF79-AD79)) -> 0.10069444 | AP79: =IF(AF79="","Kein Eintrag",IF(AC79="","Kein Eintrag",AF79-AC79)) -> 0.12152778
A80: =IF(M80="","",WEEKNUM(M80,21)) -> 3 | B80: =IF(S80="","",WEEKNUM(S80,21)) -> 3 | D80: 4200209662 | E80: Inga Achtung! T2 mit final customs Dilovasi!!!-wie machen wir es? | F80: TR45 | G80: 21 | H80: CAF | I80: Bayreuth | J80: Gebze 4 | K80: Thermo Truck | L80: 3 | M80: 45310 | O80: 1000453069 | P80: ASSTRA | Q80: CONFIRMED | R80: 9185292969 | S80: 45310 | V80: x | X80: Süden | Y80: Verladen | AA80: 45308 | AB80: 45310 | AC80: 0.34722222 | AD80: 0.36111111 | AE80: 0.38194444 | AF80: 0.51041667 | AN80: =IF(AC80="","Kein Eintrag",IF(AD80="","Kein Eintrag",AD80-AC80)) -> 0.013888889 | AO80: =IF(AF80="","Kein Eintrag",IF(AD80="","Kein Eintrag",AF80-AD80)) -> 0.14930556 | AP80: =IF(AF80="","Kein Eintrag",IF(AC80="","Kein Eintrag",AF80-AC80)) -> 0.16319444
A81: =IF(M81="","",WEEKNUM(M81,21)) -> 4 | B81: =IF(S81="","",WEEKNUM(S81,21)) -> 4 | D81: 4100038319 | E81: Magda | G81: 102 | H81: Diet | I81: Bayreuth | J81: Samsun 2 truck | K81: Box Trailer | L81: 4 | M81: 45313 | O81: 1000453551 | P81: ASSTRA | Q81: CONFIRMED | S81: 45313 | V81: x | X81: Norden | Y81: Verladen | AA81: 45310 | AB81: 45313 | AC81: 0.34375 | AD81: 0.46875 | AE81: 0.48958333 | AF81: 0.58333333 | AN81: =IF(AC81="","Kein Eintrag",IF(AD81="","Kein Eintrag",AD81-AC81)) -> 0.125 | AO81: =IF(AF81="","Kein Eintrag",IF(AD81="","Kein Eintrag",AF81-AD81)) -> 0.11458333 | AP81: =IF(AF81="","Kein Eintrag",IF(AC81="","Kein Eintrag",AF81-AC81)) -> 0.23958333
A82: =IF(M82="","",WEEKNUM(M82,21)) -> 4 | B82: =IF(S82="","",WEEKNUM(S82,21)) -> 4 | D82: 4702083726 | E82: Brauni / Mengen passen nicht! Mail an A. Dasi am 19.01.24 / Mengen wurden geändert! | G82: 72 | H82: Diet | I82: Bayreuth | J82: Ploiesti 1 | K82: Box Trailer | L82: 4 | M82: 45313 | O82: 1000453600 | P82: AQUILA | Q82: CONFIRMED | R82: 9185271643 | S82: 45313 | V82: x | X82: süden | Y82: Verladen | AA82: 45313 | AB82: 45313 | AC82: 0.29861111 | AD82: 0.47916667 | AE82: 0.5 | AF82: 0.61875 | AN82: =IF(AC82="","Kein Eintrag",IF(AD82="","Kein Eintrag",AD82-AC82)) -> 0.18055556 | AO82: =IF(AF82="","Kein Eintrag",IF(AD82="","Kein Eintrag",AF82-AD82)) -> 0.13958333 | AP82: =IF(AF82="","Kein Eintrag",IF(AC82="","Kein Eintrag",AF82-AC82)) -> 0.32013889
A83: =IF(M83="","",WEEKNUM(M83,21)) -> 4 | B83: =IF(S83="","",WEEKNUM(S83,21)) -> 4 | D83: 4702131239 | E83: Inga | G83: 102 | H83: Diet | I83: Bayreuth | J83: Poznan 1 | K83: Box Trailer | L83: 4 | M83: 45313 | O83: 1000453620 | P83: FT LOGISTICS | Q83: REQUESTED | R83: 9185271644 | S83: 45313 | V83: x | X83: süden | Y83: Verladen | AA83: 45309 | AB83: 45313 | AC83: 0.49652778 | AD83: 0.55555556 | AE83: 0.58541667 | AF83: 0.61805556 | AN83: =IF(AC83="","Kein Eintrag",IF(AD83="","Kein Eintrag",AD83-AC83)) -> 0.059027778 | AO83: =IF(AF83="","Kein Eintrag",IF(AD83="","Kein Eintrag",AF83-AD83)) -> 0.0625 | AP83: =IF(AF83="","Kein Eintrag",IF(AC83="","Kein Eintrag",AF83-AC83)) -> 0.12152778
A84: =IF(M84="","",WEEKNUM(M84,21)) -> 4 | B84: =IF(S84="","",WEEKNUM(S84,21)) -> 4 | D84: 4200208537 | E84: Brauni / Contract erhalten/COO bitte in Farbe scannen! / Docs geschickt / Docs OK / PO9U066/KOL2CR7, Sobol Sergey / kommt am 23.1. wegen Docs | G84: 102 | H84: Diet | J84: Samarkand 1 | M84: 45313 | O84: Selbstabholer | R84: 9185350231 | S84: 45313 | V84: x | X84: süden | Y84: Verladen | AA84: 45313 | AB84: 45313 | AC84: 0.59027778 | AD84: 0.64583333 | AE84: 0.68402778 | AF84: 0.51388889 | AN84: =IF(AC84="","Kein Eintrag",IF(AD84="","Kein Eintrag",AD84-AC84)) -> 0.055555556 | AO84: =IF(AF84="","Kein Eintrag",IF(AD84="","Kein Eintrag",AF84-AD84)) -> -0.13194444 | AP84: =IF(AF84="","Kein Eintrag",IF(AC84="","Kein Eintrag",AF84-AC84)) -> -0.076388889
A85: =IF(M85="","",WEEKNUM(M85,21)) -> 4 | B85: =IF(S85="","",WEEKNUM(S85,21)) -> 4 | D85: 4200212243 | E85: Brauni / Contract erhalten/COO bitte in Farbe scannen! / WLS33772/WLS62AR , SIZHOK DZMITRY / Docs geschickt / Docs OK | G85: 102 | H85: Diet | J85: Samarkand 7 | M85: 45313 | O85: Selbstabholer | R85: 9185373326 | S85: 45313 | V85: x | X85: Süden | Y85: Verladen | AA85: 45313 | AB85: 45313 | AC85: 0.36805556 | AD85: 0.40625 | AE85: 0.43611111 | AF85: 0.59375 | AN85: =IF(AC85="","Kein Eintrag",IF(AD85="","Kein Eintrag",AD85-AC85)) -> 0.038194444 | AO85: =IF(AF85="","Kein Eintrag",IF(AD85="","Kein Eintrag",AF85-AD85)) -> 0.1875 | AP85: =IF(AF85="","Kein Eintrag",IF(AC85="","Kein Eintrag",AF85-AC85)) -> 0.22569444
A86: =IF(M86="","",WEEKNUM(M86,21)) -> 4 | B86: =IF(S86="","",WEEKNUM(S86,21)) -> 4 | D86: 4702120076 | E86: ADR vorhanden Inga / Über 1000 Punkte! ADR! | G86: 23 | H86: CAF | I86: Bayreuth | J86: Augustow 1 | K86: Thermo Truck | L86: 4 | M86: 45313 | O86: 1000453701 | P86: EUROGATE | Q86: CONFIRMED | R86: 9185324081/9185324082/9185324083 | S86: 45313 | V86: x | X86: Süden | Y86: Verladen | AA86: 45310 | AB86: 45313 | AC86: 0.41666667 | AD86: 0.43402778 | AE86: 0.44791667 | AF86: 0.48958333 | AN86: =IF(AC86="","Kein Eintrag",IF(AD86="","Kein Eintrag",AD86-AC86)) -> 0.017361111 | AO86: =IF(AF86="","Kein Eintrag",IF(AD86="","Kein Eintrag",AF86-AD86)) -> 0.055555556 | AP86: =IF(AF86="","Kein Eintrag",IF(AC86="","Kein Eintrag",AF86-AC86)) -> 0.072916667
A87: =IF(M87="","",WEEKNUM(M87,21)) -> 4 | B87: =IF(S87="","",WEEKNUM(S87,21)) -> 4 | D87: 4200209615 | E87: added to STO 4200209925 which will load on the 29/01 | H87: CAF | I87: Bayreuth | J87: Landskrona 1 | K87: Thermo Van | L87: 4 | M87: 45313 | P87: ASSTRA | Q87: CONFIRMED | S87: 45313 | Y87: Gestrichen | AN87: =IF(AC87="","Kein Eintrag",IF(AD87="","Kein Eintrag",AD87-AC87)) -> Kein Eintrag | AO87: =IF(AF87="","Kein Eintrag",IF(AD87="","Kein Eintrag",AF87-AD87)) -> Kein Eintrag | AP87: =IF(AF87="","Kein Eintrag",IF(AC87="","Kein Eintrag",AF87-AC87)) -> Kein Eintrag
A88: =IF(M88="","",WEEKNUM(M88,21)) -> 4 | B88: =IF(S88="","",WEEKNUM(S88,21)) -> 4 | D88: 4100038251 | E88: ist navigiert, jedoch ist die komplette Ware nicht verzollt also keine Vst Ware -> kein A.TR. / Info v. Sebastian A. This problem occurred because the delivery 4200210963 was brought forward and not loaded on 30.01.23 as planned in MD04. We will clear the missing quantity today. As mention in our last call we clear the planned amount as per MD04 between Tuesday and Thursday for the next week - on 22.01. at 10:21 h / am 22.1 nicht gekommen / Heike | G88: 93 | H88: Diet | I88: Bayreuth | J88: Samsun 1 truck | K88: Box Trailer | L88: 4 | M88: 45313 | O88: 1000453552 | P88: GOPET | Q88: CONFIRMED | R88: 9185266794 | S88: 45314 | V88: x | X88: süden | Y88: Verladen | AB88: 45314 | AC88: 0.30208333 | AD88: 0.63541667 | AE88: 0.67708333 | AF88: 0.76388889 | AN88: =IF(AC88="","Kein Eintrag",IF(AD88="","Kein Eintrag",AD88-AC88)) -> 0.33333333 | AO88: =IF(AF88="","Kein Eintrag",IF(AD88="","Kein Eintrag",AF88-AD88)) -> 0.12847222 | AP88: =IF(AF88="","Kein Eintrag",IF(AC88="","Kein Eintrag",AF88-AC88)) -> 0.46180556
A89: =IF(M89="","",WEEKNUM(M89,21)) -> 4 | B89: =IF(S89="","",WEEKNUM(S89,21)) -> 4 | D89: 4702108610 | E89: Brauni / am 22.1. nicht gekommen | G89: 102 | H89: Diet | I89: Bayreuth | J89: Kanfanar 1 | K89: Box Trailer | L89: 4 | M89: 45313 | O89: 1000453585 | P89: TRANSEAST | Q89: CONFIRMED | R89: 9185280032 | S89: 45314 | V89: x | X89: süden | Y89: Verladen | AA89: 45310 | AB89: 45314 | AC89: 0.32291667 | AD89: 0.34375 | AE89: 0.36527778 | AF89: 0.40486111 | AN89: =IF(AC89="","Kein Eintrag",IF(AD89="","Kein Eintrag",AD89-AC89)) -> 0.020833333 | AO89: =IF(AF89="","Kein Eintrag",IF(AD89="","Kein Eintrag",AF89-AD89)) -> 0.061111111 | AP89: =IF(AF89="","Kein Eintrag",IF(AC89="","Kein Eintrag",AF89-AC89)) -> 0.081944444
A90: =IF(M90="","",WEEKNUM(M90,21)) -> 4 | B90: =IF(S90="","",WEEKNUM(S90,21)) -> 4 | D90: 4100038320 | E90: Magda | G90: 102 | H90: Diet | I90: Bayreuth | J90: Samsun 3 | K90: Box Trailer | L90: 4 | M90: 45314 | O90: 1000453555 | P90: DHL TURKEY | Q90: CONFIRMED | R90: 9185339117 | S90: 45314 | V90: x | X90: Süden | Y90: Verladen | AA90: 45313 | AB90: 45314 | AC90: 0.32638889 | AD90: 0.39583333 | AE90: 0.41666667 | AF90: 0.51527778 | AN90: =IF(AC90="","Kein Eintrag",IF(AD90="","Kein Eintrag",AD90-AC90)) -> 0.069444444 | AO90: =IF(AF90="","Kein Eintrag",IF(AD90="","Kein Eintrag",AF90-AD90)) -> 0.11944444 | AP90: =IF(AF90="","Kein Eintrag",IF(AC90="","Kein Eintrag",AF90-AC90)) -> 0.18888889
A91: =IF(M91="","",WEEKNUM(M91,21)) -> 4 | B91: =IF(S91="","",WEEKNUM(S91,21)) -> 4 | D91: 4100038321 | E91: Magda | G91: 102 | H91: Diet | I91: Bayreuth | J91: Samsun 4 | K91: Box Trailer | L91: 4 | M91: 45314 | O91: 1000453556 | P91: GOPET | Q91: CONFIRMED | R91: 9184985641 | S91: 45314 | V91: x | X91: Süden | Y91: Verladen | AA91: 45313 | AB91: 45314 | AC91: 0.27083333 | AD91: 07>00 | AE91: 07>35 | AF91: 0.44097222 | AN91: =IF(AC91="","Kein Eintrag",IF(AD91="","Kein Eintrag",AD91-AC91)) -> #VALUE! | AO91: =IF(AF91="","Kein Eintrag",IF(AD91="","Kein Eintrag",AF91-AD91)) -> #VALUE! | AP91: =IF(AF91="","Kein Eintrag",IF(AC91="","Kein Eintrag",AF91-AC91)) -> 0.17013889
A92: =IF(M92="","",WEEKNUM(M92,21)) -> 4 | B92: =IF(S92="","",WEEKNUM(S92,21)) -> 4 | D92: 4702083695 | E92: muss LEAF abladen Inga | G92: 102 | H92: Diet | I92: Bayreuth | J92: Poznan 2 | K92: Box Trailer | L92: 4 | M92: 45314 | O92: 1000453621 | P92: EUROGATE | Q92: CONFIRMED | R92: 9185345106 | S92: 45314 | V92: x | X92: Süden | Y92: Verladen | AA92: 45313 | AB92: 45314 | AC92: 0.39583333 | AD92: 0.46875 | AE92: 0.48958333 | AF92: 0.50694444 | AN92: =IF(AC92="","Kein Eintrag",IF(AD92="","Kein Eintrag",AD92-AC92)) -> 0.072916667 | AO92: =IF(AF92="","Kein Eintrag",IF(AD92="","Kein Eintrag",AF92-AD92)) -> 0.038194444 | AP92: =IF(AF92="","Kein Eintrag",IF(AC92="","Kein Eintrag",AF92-AC92)) -> 0.11111111
A93: =IF(M93="","",WEEKNUM(M93,21)) -> 4 | B93: =IF(S93="","",WEEKNUM(S93,21)) -> 4 | D93: 4200215573 | E93: Inga - Incoterm FCA Bayreuth /docs geschickt/ docs ok | G93: 102 | H93: Diet | J93: Prilucky 2 | M93: 45314 | R93: 9185361864 | S93: 45314 | V93: x | X93: Süden | Y93: Verladen | AA93: 45313 | AB93: 45314 | AC93: 0.36111111 | AD93: 0.53472222 | AE93: 0.55555556 | AF93: 0.64027778 | AN93: =IF(AC93="","Kein Eintrag",IF(AD93="","Kein Eintrag",AD93-AC93)) -> 0.17361111 | AO93: =IF(AF93="","Kein Eintrag",IF(AD93="","Kein Eintrag",AF93-AD93)) -> 0.10555556 | AP93: =IF(AF93="","Kein Eintrag",IF(AC93="","Kein Eintrag",AF93-AC93)) -> 0.27916667
A94: =IF(M94="","",WEEKNUM(M94,21)) -> 4 | B94: =IF(S94="","",WEEKNUM(S94,21)) -> 4 | D94: 4200215574 | E94: Inga - Incoterm FCA Bayreuth /docs geschickt/ docs ok | G94: 102 | H94: Diet | J94: Prilucky 3 | M94: 45314 | R94: 9185365941 | S94: 45314 | V94: x | X94: süden | Y94: Verladen | AA94: 45313 | AB94: 45314 | AC94: 0.36111111 | AD94: 0.5625 | AE94: 0.58888889 | AF94: 0.71527778 | AN94: =IF(AC94="","Kein Eintrag",IF(AD94="","Kein Eintrag",AD94-AC94)) -> 0.20138889 | AO94: =IF(AF94="","Kein Eintrag",IF(AD94="","Kein Eintrag",AF94-AD94)) -> 0.15277778 | AP94: =IF(AF94="","Kein Eintrag",IF(AC94="","Kein Eintrag",AF94-AC94)) -> 0.35416667
A95: =IF(M95="","",WEEKNUM(M95,21)) -> 4 | B95: =IF(S95="","",WEEKNUM(S95,21)) -> 4 | D95: 4200215575 | E95: Inga - Incoterm FCA Bayreuth /docs geschickt/ docs ok | G95: 102 | H95: Diet | J95: Prilucky 4 | M95: 45314 | R95: 9185333577 | S95: 45314 | V95: x | X95: süden | Y95: Verladen | AA95: 45313 | AB95: 45314 | AC95: 0.36111111 | AD95: 0.71875 | AE95: 0.74305556 | AN95: =IF(AC95="","Kein Eintrag",IF(AD95="","Kein Eintrag",AD95-AC95)) -> 0.35763889 | AO95: =IF(AF95="","Kein Eintrag",IF(AD95="","Kein Eintrag",AF95-AD95)) -> Kein Eintrag | AP95: =IF(AF95="","Kein Eintrag",IF(AC95="","Kein Eintrag",AF95-AC95)) -> Kein Eintrag
A96: =IF(M96="","",WEEKNUM(M96,21)) -> 4 | B96: =IF(S96="","",WEEKNUM(S96,21)) -> 4 | D96: 4200211129 | E96: Inga / am 23.01. nicht gekommen Heike | G96: 102 | H96: Diet | I96: Bayreuth | J96: Vranje 1 | K96: Box Trailer | L96: 4 | M96: 45314 | O96: 1000453638 | P96: FERCAM | Q96: CONFIRMED | R96: 9185318840 | S96: 45315 | V96: x | X96: süden | Y96: Verladen | AA96: 45310 | AB96: 45315 | AC96: 0.4375 | AD96: 0.67013889 | AE96: 0.71527778 | AN96: =IF(AC96="","Kein Eintrag",IF(AD96="","Kein Eintrag",AD96-AC96)) -> 0.23263889 | AO96: =IF(AF96="","Kein Eintrag",IF(AD96="","Kein Eintrag",AF96-AD96)) -> Kein Eintrag | AP96: =IF(AF96="","Kein Eintrag",IF(AC96="","Kein Eintrag",AF96-AC96)) -> Kein Eintrag
A97: =IF(M97="","",WEEKNUM(M97,21)) -> 4 | B97: =IF(S97="","",WEEKNUM(S97,21)) -> 4 | D97: 4702081656 | E97: Ingaam 23.1. nicht gekommen | G97: 102 | H97: Diet | I97: Bayreuth | J97: Kanfanar 2 | K97: Box Trailer | L97: 4 | M97: 45314 | O97: 1000453586 | P97: TRANSEAST | Q97: CONFIRMED | R97: 9185310486 | S97: 45315 | V97: x | X97: süden | Y97: Verladen | AA97: 45313 | AB97: 45315 | AC97: 0.51736111 | AD97: 0.59722222 | AE97: 0.64583333 | AF97: 0.65972222 | AN97: =IF(AC97="","Kein Eintrag",IF(AD97="","Kein Eintrag",AD97-AC97)) -> 0.079861111 | AO97: =IF(AF97="","Kein Eintrag",IF(AD97="","Kein Eintrag",AF97-AD97)) -> 0.0625 | AP97: =IF(AF97="","Kein Eintrag",IF(AC97="","Kein Eintrag",AF97-AC97)) -> 0.14236111
A98: =IF(M98="","",WEEKNUM(M98,21)) -> 4 | B98: =IF(S98="","",WEEKNUM(S98,21)) -> 4 | D98: 4702081700 | E98: Inga konnte zeitl. nicht mehr verladen werden 17:10 Heike | G98: 102 | H98: Diet | I98: Bayreuth | J98: Pecs 2 | K98: Box Trailer | L98: 4 | M98: 45314 | O98: 1000453700 | P98: LOG-IN | Q98: CONFIRMED | R98: 9185334586 | S98: 45315 | V98: x | X98: Süden | Y98: Verladen | AA98: 45313 | AB98: 45315 | AC98: 0.30902778 | AD98: 0.42708333 | AE98: 0.49305556 | AG98: Kartonagen in der Schhleuße hängen geblieben! | AJ98: 45314 | AK98: 0.45486111 | AN98: =IF(AC98="","Kein Eintrag",IF(AD98="","Kein Eintrag",AD98-AC98)) -> 0.11805556 | AO98: =IF(AF98="","Kein Eintrag",IF(AD98="","Kein Eintrag",AF98-AD98)) -> Kein Eintrag | AP98: =IF(AF98="","Kein Eintrag",IF(AC98="","Kein Eintrag",AF98-AC98)) -> Kein Eintrag
A99: =IF(M99="","",WEEKNUM(M99,21)) -> 4 | B99: =IF(S99="","",WEEKNUM(S99,21)) -> 4 | D99: 4702108651 | E99: Inga konnte zeitl. nicht mehr verladen werden 17:10 Heike | G99: 102 | H99: Diet | I99: Bayreuth | J99: Poznan 3 | K99: Box Trailer | L99: 4 | M99: 45314 | O99: 1000453622 | P99: FT LOGISTICS | Q99: REQUESTED | R99: 9185318841 | S99: 45315 | V99: x | X99: Süden | Y99: Verladen | AA99: 45313 | AB99: 45315 | AC99: 0.28125 | AD99: 0.30555556 | AE99: 0.32638889 | AF99: 0.34375 | AJ99: 45314 | AK99: 0.46527778 | AN99: =IF(AC99="","Kein Eintrag",IF(AD99="","Kein Eintrag",AD99-AC99)) -> 0.024305556 | AO99: =IF(AF99="","Kein Eintrag",IF(AD99="","Kein Eintrag",AF99-AD99)) -> 0.038194444 | AP99: =IF(AF99="","Kein Eintrag",IF(AC99="","Kein Eintrag",AF99-AC99)) -> 0.0625
A100: =IF(M100="","",WEEKNUM(M100,21)) -> 4 | B100: =IF(S100="","",WEEKNUM(S100,21)) -> 4 | D100: 4200205346 | E100: Brauni /Contract erhalten/COO bitte in Farbe scannen! / Docs geschickt / Truck: Ws 0295 E/ws98742 / EU Exit point Pl301040 / Docs OK / am 23.1 nicht gekommen Heike/ docs okay | G100: 102 | H100: Diet | J100: Samarkand 2 | M100: 45314 | O100: Selbstabholer | R100: 9185348863 | S100: 45315 | V100: x | X100: süden | Y100: Verladen | AA100: 45314 | AB100: 45315 | AC100: 0.41319444 | AD100: 0.56944444 | AE100: 0.59722222 | AF100: 0.70486111 | AN100: =IF(AC100="","Kein Eintrag",IF(AD100="","Kein Eintrag",AD100-AC100)) -> 0.15625 | AO100: =IF(AF100="","Kein Eintrag",IF(AD100="","Kein Eintrag",AF100-AD100)) -> 0.13541667 | AP100: =IF(AF100="","Kein Eintrag",IF(AC100="","Kein Eintrag",AF100-AC100)) -> 0.29166667
...

Sheet Docs
A1: PO Number | B1: Datum | C1: Scan mit FI | D1: Scan per Mail | E1: Scan FI/COO/ATR | F1: Im Umschlag | G1: Verschickt mit Waybill No. | H1: Destination
A2: 4200203577 | B2: 45232 | H2: TR
A3: 4100038192 | B3: 45236 | H3: TR
A4: 4100038193 | B4: 45236 | H4: TR
A5: 4100038194 | B5: 45237 | H5: TR
A6: 4100038241 | B6: 45238 | H6: TR
A7: 4100038252 | B7: 45243 | H7: TR
A8: 4100038242 | B8: 45244 | H8: TR
A9: 4100038243 | B9: 45245 | H9: TR
A10: 4200208744 | B10: 45246 | H10: TR
A11: 4200210340 | B11: 45247 | H11: TR
A12: 4200210367 | B12: 45252 | H12: TR
A13: 4200210366 | B13: 45253 | H13: TR
... A15: 4100038599 | B15: 45257 | H15: TR
A16: 4100038291 | B16: 45278 | C16: x | D16: x | E16: x | F16: x | G16: 9768695930 | H16: TR
A17: 4100038290 | B17: 45278 | C17: x | D17: x | E17: x | F17: x | G17: 9768695930 | H17: TR
A18: 4100038299 | B18: 45278 | C18: x | D18: x | E18: x | F18: x | G18: 9768695930 | H18: TR
A19: 4100038298 | B19: 45280 | H19: TR
A20: 4100038292 | B20: 45281 | H20: TR
A21: 4200207906 | B21: 45232 | H21: TR
A22: 4200207917 | B22: 45233 | H22: TR
A23: 4200207908 | B23: 45236 | H23: TR
A24: 4200207910 | B24: 45237 | H24: TR
A25: 4200207918 | B25: 45237 | H25: TR
A26: 4200208358 | B26: 45238 | H26: TR
A27: 4200208359 | B27: 45238 | H27: TR
A28: 4200208360 | B28: 45239 | H28: TR
A29: 4200208361 | B29: 45240 | H29: TR
A30: 4200208362 | B30: 45240 | H30: TR
... A53: 4200208424 | B53: 45267 | H53: TR
A54: 4200208434 | B54: 45268 | C54: x | D54: x | E54: x | F54: x | G54: 9768695930 | H54: TR
A55: 4200208747 | B55: 45268 | H55: TR
A56: 4200208406 | B56: 45273 | C56: x | D56: x | E56: x | F56: x | G56: 9768695930 | H56: TR
A57: 4200208412 | B57: 45271 | C57: x | H57: TR
A58: 4200208414 | B58: 45272 | C58: x | D58: x | E58: x | F58: x | G58: 9768695930 | H58: TR
A59: 4200208415 | B59: 45272 | C59: x | D59: x | E59: x | F59: x | G59: 9768695930 | H59: TR
A60: 4200208416 | B60: 45273 | C60: x | D60: x | E60: x | F60: x | G60: 9768695930 | H60: TR
A61: 4200208417 | B61: 45273 | C61: x | D61: x | E61: x | F61: x | G61: 9768695930 | H61: TR
A62: 4200208418 | B62: 45275 | C62: x | D62: x | E62: x | F62: x | G62: 9768695930 | H62: TR
A63: 4200208419 | B63: 45274 | C63: x | D63: x | E63: x | F63: x | G63: 9768695930 | H63: TR
A64: 4200208425 | B64: 45279 | C64: x | D64: x | E64: x | F64: x | G64: 9768695930 | H64: TR
A65: 4200208426 | B65: 45279 | C65: x | D65: x | E65: x | F65: x | G65: 9768695930 | H65: TR
A66: 4200208427 | B66: 45279 | C66: x | D66: x | E66: x | F66: x | G66: 9768695930 | H66: TR
A67: 4200208429 | B67: 45279 | C67: x | D67: x | E67: x | F67: x | G67: 9768695930 | H67: TR
A68: 4200212534 | B68: 45280 | H68: TR
A69: 4200212536 | B69: 45280 | H69: TR
A70: 4200208748 | B70: 45281 | H70: TR
A71: 4200208363 | B71: 45313 | H71: TR
A72: 4200208386 | B72: 45315 | H72: TR
A73: 4200208370 | B73: 45322 | H73: TR
A74: 4200208381 | B74: 45329 | H74: TR
A75: 4200206530 | B75: 45279 | C75: x | D75: x | E75: x | F75: x | G75: 9768695930 | H75: TR
A76: 4200208945 | B76: 45280 | C76: x | D76: x | E76: x | F76: x | G76: 9768695930 | H76: TR
A77: 4200208082 | B77: 45279 | C77: x | D77: x | H77: Serbia
A78: 4200206710 | B78: 45274 | C78: x | D78: x | H78: Jordan
A79: 4200208948 | B79: 45275 | C79: x | D79: x | E79: x | F79: x | G79: 9768695930 | H79: TR
A80: 4200208947 | B80: 45274 | C80: x | D80: x | E80: x | F80: x | G80: 9768695930 | H80: TR
A81: 4200211998 | B81: 45274 | C81: x | D81: x | E81: x | F81: x | G81: 9768695930 | H81: TR
A82: 4200208946 | B82: 45274 | C82: x | D82: x | E82: x | F82: x | G82: 9768695930 | H82: TR
A83: 4200205341 | B83: 45273 | C83: x | D83: x | E83: x | F83: x | G83: 1562808623 | H83: UZ
A84: 4200205343 | B84: 45273 | C84: x | D84: x | E84: x | F84: x | G84: 1562808623 | H84: UZ
A85: 4200205336 | B85: 45274 | C85: x | D85: x | E85: x | F85: x | G85: 1562808623 | H85: UZ
A86: 4200205344 | B86: 45275 | C86: x | D86: x | E86: x | F86: x | G86: 1562808623 | H86: UZ
A87: 4200205345 | B87: 45275 | C87: x | D87: x | E87: x | F87: x | G87: 1562808623 | H87: UZ
A88: 4200205340 | B88: 45279 | C88: x | D88: x | E88: x | F88: x | G88: 1562808623 | H88: UZ
A89: 4200207598 | B89: 45281 | C89: x | D89: x | E89: x | F89: Orig. dem fahrer übergeben | H89: UZ

Sheet SFG_DDS
A1: DDS SFG Performance Tracker | G1: KW01 | M1: KW02 | T1: KW03 | AA1: KW04 | AH1: KW05 | AO1: KW06 | AV1: KW07 | BC1: KW08 | BJ1: KW09 | BQ1: KW10 | BX1: KW11 | CE1: KW12 | CL1: KW13 | CS1: KW14 | CZ1: KW15 | DG1: KW16 | DN1: KW17 | DU1: KW18 | EB1: KW19 | EI1: KW20 | EP1: KW21 | EW1: KW22 | FD1: KW23 | FK1: KW24 | FR1: KW25 | FY1: KW26 | GF1: KW27 | GM1: KW28 | GT1: KW29 | HA1: KW30 | HH1: KW31 | HO1: KW32 | HV1: KW33 | IC1: KW34 | IJ1: KW35 | IQ1: KW36 | IX1: KW37 | JE1: KW38 | JL1: KW39 | JS1: KW40 | JZ1: KW41 | KG1: KW42 | KN1: KW43 | KU1: KW44 | LB1: KW45 | LI1: KW46 | LP1: KW47 | LW1: KW48 | MD1: KW49 | MK1: KW50 | MR1: KW51 | MY1: KW52
C2: Limit/Target | D2: UoM | E2: Max. | F2: 44928 | G2: 44929 | H2: 44930 | I2: 44931 | J2: 44932 | K2: 44933 | L2: 44934 | M2: 44935 | N2: 44936 | O2: 44937 | P2: 44938 | Q2: 44939 | R2: 44940 | S2: 44941 | T2: 44942 | U2: 44943 | V2: 44944 | W2: 44945 | X2: 44946 | Y2: 44947 | Z2: 44948 | AA2: 44949 | AB2: 44950 | AC2: 44951 | AD2: 44952 | AE2: 44953 | AF2: 44954 | AG2: 44955 | AH2: 44956 | AI2: 44957 | AJ2: 44958 | AK2: 44959 | AL2: 44960 | AM2: 44961 | AN2: 44962 | AO2: 44963 | AP2: 44964 | AQ2: 44965 | AR2: 44966 | AS2: 44967 | AT2: 44968 | AU2: 44969 | AV2: 44970 | AW2: 44971 | AX2: 44972 | AY2: 44973 | AZ2: 44974 | BA2: 44975 | BB2: 44976 | BC2: 44977 | BD2: 44978 | BE2: 44979 | BF2: 44980 | BG2: 44981 | BH2: 44982 | BI2: 44983 | BJ2: 44984 | BK2: 44985 | BL2: 44986 | BM2: 44987 | BN2: 44988 | BO2: 44989 | BP2: 44990 | BQ2: 44991 | BR2: 44992 | BS2: 44993 | BT2: 44994 | BU2: 44995 | BV2: 44996 | BW2: 44997 | BX2: 44998 | BY2: 44999 | BZ2: 45000 | CA2: 45001 | CB2: 45002 | CC2: 45003 | CD2: 45004 | CE2: 45005 | CF2: 45006 | CG2: 45007 | CH2: 45008 | CI2: 45009 | CJ2: 45010 | CK2: 45011 | CL2: 45012 | CM2: 45013 | CN2: 45014 | CO2: 45015 | CP2: 45016 | CQ2: 45017 | CR2: 45018 | CS2: 45019 | CT2: 45020 | CU2: 45021 | CV2: 45022 | CW2: 45023 | CX2: 45024 | CY2: 45025 | CZ2: 45026 | DA2: 45027 | DB2: 45028 | DC2: 45029 | DD2: 45030 | DE2: 45031 | DF2: 45032 | DG2: 45033 | DH2: 45034 | DI2: 45035 | DJ2: 45036 | DK2: 45037 | DL2: 45038 | DM2: 45039 | DN2: 45040 | DO2: 45041 | DP2: 45042 | DQ2: 45043 | DR2: 45044 | DS2: 45045 | DT2: 45046 | DU2: 45047 | DV2: 45048 | DW2: 45049 | DX2: 45050 | DY2: 45051 | DZ2: 45052 | EA2: 45053 | EB2: 45054 | EC2: 45055 | ED2: 45056 | EE2: 45057 | EF2: 45058 | EG2: 45059 | EH2: 45060 | EI2: 45061 | EJ2: 45062 | EK2: 45063 | EL2: 45064 | EM2: 45065 | EN2: 45066 | EO2: 45067 | EP2: 45068 | EQ2: 45069 | ER2: 45070 | ES2: 45071 | ET2: 45072 | EU2: 45073 | EV2: 45074 | EW2: 45075 | EX2: 45076 | EY2: 45077 | EZ2: 45078 | FA2: 45079 | FB2: 45080 | FC2: 45081 | FD2: 45082 | FE2: 45083 | FF2: 45084 | FG2: 45085 | FH2: 45086 | FI2: 45087 | FJ2: 45088 | FK2: 45089 | FL2: 45090 | FM2: 45091 | FN2: 45092 | FO2: 45093 | FP2: 45094 | FQ2: 45095 | FR2: 45096 | FS2: 45097 | FT2: 45098 | FU2: 45099 | FV2: 45100 | FW2: 45101 | FX2: 45102 | FY2: 45103 | FZ2: 45104 | GA2: 45105 | GB2: 45106 | GC2: 45107 | GD2: 45108 | GE2: 45109 | GF2: 45110 | GG2: 45111 | GH2: 45112 | GI2: 45113 | GJ2: 45114 | GK2: 45115 | GL2: 45116 | GM2: 45117 | GN2: 45118 | GO2: 45119 | GP2: 45120 | GQ2: 45121 | GR2: 45122 | GS2: 45123 | GT2: 45124 | GU2: 45125 | GV2: 45126 | GW2: 45127 | GX2: 45128 | GY2: 45129 | GZ2: 45130 | HA2: 45131 | HB2: 45132 | HC2: 45133 | HD2: 45134 | HE2: 45135 | HF2: 45136 | HG2: 45137 | HH2: 45138 | HI2: 45139 | HJ2: 45140 | HK2: 45141 | HL2: 45142 | HM2: 45143 | HN2: 45144 | HO2: 45145 | HP2: 45146 | HQ2: 45147 | HR2: 45148 | HS2: 45149 | HT2: 45150 | HU2: 45151 | HV2: 45152 | HW2: 45153 | HX2: 45154 | HY2: 45155 | HZ2: 45156 | IA2: 45157 | IB2: 45158 | IC2: 45159 | ID2: 45160 | IE2: 45161 | IF2: 45162 | IG2: 45163 | IH2: 45164 | II2: 45165 | IJ2: 45166 | IK2: 45167 | IL2: 45168 | IM2: 45169 | IN2: 45170 | IO2: 45171 | IP2: 45172 | IQ2: 45173 | IR2: 45174 | IS2: 45175 | IT2: 45176 | IU2: 45177 | IV2: 45178 | IW2: 45179 | IX2: 45180 | IY2: 45181 | IZ2: 45182 | JA2: 45183 | JB2: 45184 | JC2: 45185 | JD2: 45186 | JE2: 45187 | JF2: 45188 | JG2: 45189 | JH2: 45190 | JI2: 45191 | JJ2: 45192 | JK2: 45193 | JL2: 45194 | JM2: 45195 | JN2: 45196 | JO2: 45197 | JP2: 45198 | JQ2: 45199 | JR2: 45200 | JS2: 45201 | JT2: 45202 | JU2: 45203 | JV2: 45204 | JW2: 45205 | JX2: 45206 | JY2: 45207 | JZ2: 45208 | KA2: 45209 | KB2: 45210 | KC2: 45211 | KD2: 45212 | KE2: 45213 | KF2: 45214 | KG2: 45215 | KH2: 45216 | KI2: 45217 | KJ2: 45218 | KK2: 45219 | KL2: 45220 | KM2: 45221 | KN2: 45222 | KO2: 45223 | KP2: 45224 | KQ2: 45225 | KR2: 45226 | KS2: 45227 | KT2: 45228 | KU2: 45229 | KV2: 45230 | KW2: 45231 | KX2: 45232 | KY2: 45233 | KZ2: 45234 | LA2: 45235 | LB2: 45236 | LC2: 45237 | LD2: 45238 | LE2: 45239 | LF2: 45240 | LG2: 45241 | LH2: 45242 | LI2: 45243 | LJ2: 45244 | LK2: 45245 | LL2: 45246 | LM2: 45247 | LN2: 45248 | LO2: 45249 | LP2: 45250 | LQ2: 45251 | LR2: 45252 | LS2: 45253 | LT2: 45254 | LU2: 45255 | LV2: 45256 | LW2: 45257 | LX2: 45258 | LY2: 45259 | LZ2: 45260 | MA2: 45261 | MB2: 45262 | MC2: 45263 | MD2: 45264 | ME2: 45265 | MF2: 45266 | MG2: 45267 | MH2: 45268 | MI2: 45269 | MJ2: 45270 | MK2: 45271 | ML2: 45272 | MM2: 45273 | MN2: 45274 | MO2: 45275 | MP2: 45276 | MQ2: 45277 | MR2: 45278 | MS2: 45279 | MT2: 45280 | MU2: 45281 | MV2: 45282 | MW2: 45283 | MX2: 45284 | MY2: 45285 | MZ2: 45286 | NA2: 45287 | NB2: 45288 | NC2: 45289 | ND2: 45290 | NE2: 45291
F3: Montag | G3: Dienstag | H3: Mittwoch | I3: Donnerstag | J3: Freitag | K3: Samstag | L3: Sonntag | M3: Montag | N3: Dienstag | O3: Mittwoch | P3: Donnerstag | Q3: Freitag | R3: Samstag | S3: Sonntag | T3: Montag | U3: Dienstag | V3: Mittwoch | W3: Donnerstag | X3: Freitag | Y3: Samstag | Z3: Sonntag | AA3: Montag | AB3: Dienstag | AC3: Mittwoch | AD3: Donnerstag | AE3: Freitag | AF3: Samstag | AG3: Sonntag | AH3: Montag | AI3: Dienstag | AJ3: Mittwoch | AK3: Donnerstag | AL3: Freitag | AM3: Samstag | AN3: Sonntag | AO3: Montag | AP3: Dienstag | AQ3: Mittwoch | AR3: Donnerstag | AS3: Freitag | AT3: Samstag | AU3: Sonntag | AV3: Montag | AW3: Dienstag | AX3: Mittwoch | AY3: Donnerstag | AZ3: Freitag | BA3: Samstag | BB3: Sonntag | BC3: Montag | BD3: Dienstag | BE3: Mittwoch | BF3: Donnerstag | BG3: Freitag | BH3: Samstag | BI3: Sonntag | BJ3: Montag | BK3: Dienstag | BL3: Mittwoch | BM3: Donnerstag | BN3: Freitag | BO3: Samstag | BP3: Sonntag | BQ3: Montag | BR3: Dienstag | BS3: Mittwoch | BT3: Donnerstag | BU3: Freitag | BV3: Samstag | BW3: Sonntag | BX3: Montag | BY3: Dienstag | BZ3: Mittwoch | CA3: Donnerstag | CB3: Freitag | CC3: Samstag | CD3: Sonntag | CE3: Montag | CF3: Dienstag | CG3: Mittwoch | CH3: Donnerstag | CI3: Freitag | CJ3: Samstag | CK3: Sonntag | CL3: Montag | CM3: Dienstag | CN3: Mittwoch | CO3: Donnerstag | CP3: Freitag | CQ3: Samstag | CR3: Sonntag | CS3: Montag | CT3: Dienstag | CU3: Mittwoch | CV3: Donnerstag | CW3: Freitag | CX3: Samstag | CY3: Sonntag | CZ3: Montag | DA3: Dienstag | DB3: Mittwoch | DC3: Donnerstag | DD3: Freitag | DE3: Samstag | DF3: Sonntag | DG3: Montag | DH3: Dienstag | DI3: Mittwoch | DJ3: Donnerstag | DK3: Freitag | DL3: Samstag | DM3: Sonntag | DN3: Montag | DO3: Dienstag | DP3: Mittwoch | DQ3: Donnerstag | DR3: Freitag | DS3: Samstag | DT3: Sonntag | DU3: Montag | DV3: Dienstag | DW3: Mittwoch | DX3: Donnerstag | DY3: Freitag | DZ3: Samstag | EA3: Sonntag | EB3: Montag | EC3: Dienstag | ED3: Mittwoch | EE3: Donnerstag | EF3: Freitag | EG3: Samstag | EH3: Sonntag | EI3: Montag | EJ3: Dienstag | EK3: Mittwoch | EL3: Donnerstag | EM3: Freitag | EN3: Samstag | EO3: Sonntag | EP3: Montag | EQ3: Dienstag | ER3: Mittwoch | ES3: Donnerstag | ET3: Freitag | EU3: Samstag | EV3: Sonntag | EW3: Montag | EX3: Dienstag | EY3: Mittwoch | EZ3: Donnerstag | FA3: Freitag | FB3: Samstag | FC3: Sonntag | FD3: Montag | FE3: Dienstag | FF3: Mittwoch | FG3: Donnerstag | FH3: Freitag | FI3: Samstag | FJ3: Sonntag | FK3: Montag | FL3: Dienstag | FM3: Mittwoch | FN3: Donnerstag | FO3: Freitag | FP3: Samstag | FQ3: Sonntag | FR3: Montag | FS3: Dienstag | FT3: Mittwoch | FU3: Donnerstag | FV3: Freitag | FW3: Samstag | FX3: Sonntag | FY3: Montag | FZ3: Dienstag | GA3: Mittwoch | GB3: Donnerstag | GC3: Freitag | GD3: Samstag | GE3: Sonntag | GF3: Montag | GG3: Dienstag | GH3: Mittwoch | GI3: Donnerstag | GJ3: Freitag | GK3: Samstag | GL3: Sonntag | GM3: Montag | GN3: Dienstag | GO3: Mittwoch | GP3: Donnerstag | GQ3: Freitag | GR3: Samstag | GS3: Sonntag | GT3: Montag | GU3: Dienstag | GV3: Mittwoch | GW3: Donnerstag | GX3: Freitag | GY3: Samstag | GZ3: Sonntag | HA3: Montag | HB3: Dienstag | HC3: Mittwoch | HD3: Donnerstag | HE3: Freitag | HF3: Samstag | HG3: Sonntag | HH3: Montag | HI3: Dienstag | HJ3: Mittwoch | HK3: Donnerstag | HL3: Freitag | HM3: Samstag | HN3: Sonntag | HO3: Montag | HP3: Dienstag | HQ3: Mittwoch | HR3: Donnerstag | HS3: Freitag | HT3: Samstag | HU3: Sonntag | HV3: Montag | HW3: Dienstag | HX3: Mittwoch | HY3: Donnerstag | HZ3: Freitag | IA3: Samstag | IB3: Sonntag | IC3: Montag | ID3: Dienstag | IE3: Mittwoch | IF3: Donnerstag | IG3: Freitag | IH3: Samstag | II3: Sonntag | IJ3: Montag | IK3: Dienstag | IL3: Mittwoch | IM3: Donnerstag | IN3: Freitag | IO3: Samstag | IP3: Sonntag | IQ3: Montag | IR3: Dienstag | IS3: Mittwoch | IT3: Donnerstag | IU3: Freitag | IV3: Samstag | IW3: Sonntag | IX3: Montag | IY3: Dienstag | IZ3: Mittwoch | JA3: Donnerstag | JB3: Freitag | JC3: Samstag | JD3: Sonntag | JE3: Montag | JF3: Dienstag | JG3: Mittwoch | JH3: Donnerstag | JI3: Freitag | JJ3: Samstag | JK3: Sonntag | JL3: Montag | JM3: Dienstag | JN3: Mittwoch | JO3: Donnerstag | JP3: Freitag | JQ3: Samstag | JR3: Sonntag | JS3: Montag | JT3: Dienstag | JU3: Mittwoch | JV3: Donnerstag | JW3: Freitag | JX3: Samstag | JY3: Sonntag | JZ3: Montag | KA3: Dienstag | KB3: Mittwoch | KC3: Donnerstag | KD3: Freitag | KE3: Samstag | KF3: Sonntag | KG3: Montag | KH3: Dienstag | KI3: Mittwoch | KJ3: Donnerstag | KK3: Freitag | KL3: Samstag | KM3: Sonntag | KN3: Montag | KO3: Dienstag | KP3: Mittwoch | KQ3: Donnerstag | KR3: Freitag | KS3: Samstag | KT3: Sonntag | KU3: Montag | KV3: Dienstag | KW3: Mittwoch | KX3: Donnerstag | KY3: Freitag | KZ3: Samstag | LA3: Sonntag | LB3: Montag | LC3: Dienstag | LD3: Mittwoch | LE3: Donnerstag | LF3: Freitag | LG3: Samstag | LH3: Sonntag | LI3: Montag | LJ3: Dienstag | LK3: Mittwoch | LL3: Donnerstag | LM3: Freitag | LN3: Samstag | LO3: Sonntag | LP3: Montag | LQ3: Dienstag | LR3: Mittwoch | LS3: Donnerstag | LT3: Freitag | LU3: Samstag | LV3: Sonntag | LW3: Montag | LX3: Dienstag | LY3: Mittwoch | LZ3: Donnerstag | MA3: Freitag | MB3: Samstag | MC3: Sonntag | MD3: Montag | ME3: Dienstag | MF3: Mittwoch | MG3: Donnerstag | MH3: Freitag | MI3: Samstag | MJ3: Sonntag | MK3: Montag | ML3: Dienstag | MM3: Mittwoch | MN3: Donnerstag | MO3: Freitag | MP3: Samstag | MQ3: Sonntag | MR3: Montag | MS3: Dienstag | MT3: Mittwoch | MU3: Donnerstag | MV3: Freitag | MW3: Samstag | MX3: Sonntag | MY3: Montag | MZ3: Dienstag | NA3: Mittwoch | NB3: Donnerstag | NC3: Freitag | ND3: Samstag | NE3: Sonntag
A4: EH&S | NF4: ENDE
A5: Ehem. Kommilager | NF5: ENDE
A6: 5S Gemba Walk / SoS Gang | B6: Min. 1 pro Monat pro Bereich LOG-IN & BAT | C6: 1 | D6: N/A | NF6: ENDE
A7: Accident / LTR | B7: Anzahl schwerer Verletzungen | C7: 0 | D7: EA | NF7: ENDE
A8: Incident / Near Misses | B8: Anzahl Verletzungen | C8: 0 | D8: EA | NF8: ENDE
A9: Safety trigger | B9: Safety Trigger Rohstofflager | C9: 5 | D9: N/A | F9: 0 | G9: 0 | H9: 0 | I9: 0 | J9: 0 | K9: 0 | L9: 0 | M9: 0 | N9: 0 | O9: 0 | P9: 0 | Q9: 0 | R9: 0 | S9: 0 | T9: 0 | U9: 0 | V9: 0 | W9: 0 | X9: 0 | Y9: 0 | Z9: 0 | AA9: 0 | AB9: 0 | AC9: 0 | AD9: 0 | AE9: 0 | AF9: 0 | AG9: 0 | AH9: 0 | AI9: 0 | AJ9: 0 | AK9: 0 | AL9: 0 | AM9: 0 | AN9: 0 | AO9: 0 | AP9: 0 | AQ9: 0 | AR9: 0 | AS9: 0 | AT9: 0 | AU9: 0 | AV9: 0 | AW9: 0 | AX9: 0 | AY9: 0 | AZ9: 0 | BA9: 0 | BB9: 0 | BC9: 0 | BD9: 0 | BE9: 0 | BF9: 0 | BG9: 0 | BH9: 0 | BI9: 0 | BJ9: 0 | BK9: 0 | BL9: 0 | BM9: 0 | BN9: 0 | BO9: 0 | BP9: 0 | BQ9: 0 | BR9: 0 | BS9: 0 | BT9: 0 | BU9: 0 | BV9: 0 | BW9: 0 | BX9: 0 | BY9: 0 | BZ9: 0 | CA9: 0 | CB9: 0 | CC9: 0 | CD9: 0 | CE9: 0 | CF9: 0 | CG9: 0 | CH9: 0 | CI9: 0 | CJ9: 0 | CK9: 0 | CL9: 0 | CM9: 0 | CN9: 0 | CO9: 0 | CP9: 0 | CQ9: 0 | CR9: 0 | CS9: 0 | CT9: 0 | CU9: 0 | CV9: 0 | CW9: 0 | CX9: 0 | CY9: 0 | CZ9: 0 | DA9: 0 | DB9: 0 | DC9: 0 | DD9: 0 | DE9: 0 | DF9: 0 | DG9: 0 | DH9: 0 | DI9: 0 | DJ9: 0 | DK9: 0 | DL9: 0 | DM9: 0 | DN9: 0 | DO9: 0 | DP9: 0 | DQ9: 0 | DR9: 0 | DS9: 0 | DT9: 0 | DU9: 0 | DV9: 0 | DW9: 0 | DX9: 0 | DY9: 0 | DZ9: 0 | EA9: 0 | EB9: 0 | EC9: 0 | ED9: 0 | EE9: 0 | EF9: 0 | EG9: 0 | EH9: 0 | EI9: 0 | EJ9: 0 | EK9: 0 | EL9: 0 | EM9: 0 | EN9: 0 | EO9: 0 | EP9: 0 | EQ9: 0 | ER9: 0 | ES9: 0 | ET9: 0 | EU9: 0 | EV9: 0 | EW9: 0 | EX9: 0 | EY9: 0 | EZ9: 0 | FA9: 0 | FB9: 0 | FC9: 0 | FD9: 0 | FE9: 0 | FF9: 0 | FG9: 0 | FH9: 0 | FI9: 0 | FJ9: 0 | FK9: 0 | FL9: 0 | FM9: 0 | FN9: 0 | FO9: 0 | FP9: 0 | FQ9: 0 | FR9: 0 | FS9: 0 | FT9: 0 | FU9: 0 | FV9: 0 | FW9: 0 | FX9: 0 | FY9: 0 | FZ9: 0 | GA9: 0 | GB9: 0 | GC9: 0 | GD9: 0 | GE9: 0 | GF9: 0 | GG9: 0 | GH9: 0 | GI9: 0 | GJ9: 0 | GK9: 0 | GL9: 0 | GM9: 0 | GN9: 0 | GO9: 0 | GP9: 0 | GQ9: 0 | GR9: 0 | GS9: 0 | GT9: 0 | GU9: 0 | GV9: 0 | GW9: 0 | GX9: 0 | GY9: 0 | GZ9: 0 | HA9: 0 | HB9: 0 | HC9: 0 | HD9: 0 | HE9: 0 | HF9: 0 | HG9: 0 | HH9: 0 | HI9: 0 | HJ9: 0 | HK9: 0 | HL9: 0 | HM9: 0 | HN9: 0 | HO9: 0 | HP9: 0 | HQ9: 0 | HR9: 0 | HS9: 0 | HT9: 0 | HU9: 0 | HV9: 0 | HW9: 0 | HX9: 0 | HY9: 0 | HZ9: 0 | IA9: 0 | IB9: 0 | IC9: 0 | ID9: 0 | IE9: 0 | IF9: 0 | IG9: 0 | IH9: 0 | II9: 0 | IJ9: 0 | IK9: 0 | IL9: 0 | IM9: 0 | IN9: 0 | IO9: 0 | IP9: 0 | IQ9: 0 | IR9: 0 | IS9: 0 | IT9: 0 | IU9: 0 | IV9: 0 | IW9: 0 | IX9: 0 | IY9: 0 | IZ9: 0 | JA9: 0 | JB9: 0 | JC9: 0 | JD9: 0 | JE9: 0 | JF9: 0 | JG9: 0 | JH9: 0 | JI9: 0 | JJ9: 0 | JK9: 0 | JL9: 0 | JM9: 0 | JN9: 0 | JO9: 0 | JP9: 0 | JQ9: 0 | JR9: 0 | JS9: 0 | JT9: 0 | JU9: 0 | JV9: 0 | JW9: 0 | JX9: 0 | JY9: 0 | JZ9: 0 | KA9: 0 | KB9: 0 | KC9: 0 | KD9: 0 | KE9: 0 | KF9: 0 | KG9: 0 | KH9: 0 | KI9: 0 | KJ9: 0 | KK9: 0 | KL9: 0 | KM9: 0 | KN9: 0 | KO9: 0 | KP9: 0 | KQ9: 0 | KR9: 0 | KS9: 0 | KT9: 0 | KU9: 0 | KV9: 0 | KW9: 0 | KX9: 0 | KY9: 0 | KZ9: 0 | LA9: 0 | LB9: 0 | LC9: 0 | LD9: 0 | LE9: 0 | LF9: 0 | LG9: 0 | LH9: 0 | LI9: 0 | LJ9: 0 | LK9: 0 | LL9: 0 | LM9: 0 | LN9: 0 | LO9: 0 | LP9: 0 | LQ9: 0 | LR9: 0 | LS9: 0 | LT9: 0 | LU9: 0 | LV9: 0 | LW9: 0 | LX9: 0 | LY9: 0 | LZ9: 0 | MA9: 0 | MB9: 0 | MC9: 0 | MD9: 0 | ME9: 0 | MF9: 0 | MG9: 0 | MH9: 0 | MI9: 0 | MJ9: 0 | MK9: 0 | ML9: 0 | MM9: 0 | MN9: 0 | MO9: 0 | MP9: 0 | MQ9: 0 | MR9: 0 | MS9: 0 | MT9: 0 | MU9: 0 | MV9: 0 | MW9: 0 | MX9: 0 | MY9: 0 | MZ9: 0 | NA9: 0 | NB9: 0 | NC9: 0 | ND9: 0 | NE9: 0 | NF9: ENDE
A10: DIET Lager | NF10: ENDE
A11: 5S Gemba Walk | B11: Min. 1 pro Monat pro Bereich LOG-IN & BAT | C11: 1 | D11: N/A | NF11: ENDE
A12: Accident / LTR | B12: Anzahl schwerer Verletzungen | C12: 0 | D12: EA | NF12: ENDE
A13: Incident / Near Misses | B13: Anzahl Verletzungen | C13: 0 | D13: EA | NF13: ENDE
A14: Safety trigger | B14: Safety Trigger DIET | C14: 5 | D14: N/A | F14: 0 | G14: 0 | H14: 0 | I14: 0 | J14: 0 | K14: 0 | L14: 0 | M14: 0 | N14: 0 | O14: 0 | P14: 0 | Q14: 0 | R14: 0 | S14: 0 | T14: 0 | U14: 0 | V14: 0 | W14: 0 | X14: 0 | Y14: 0 | Z14: 0 | AA14: 0 | AB14: 0 | AC14: 0 | AD14: 0 | AE14: 0 | AF14: 0 | AG14: 0 | AH14: 0 | AI14: 0 | AJ14: 0 | AK14: 0 | AL14: 0 | AM14: 0 | AN14: 0 | AO14: 0 | AP14: 0 | AQ14: 0 | AR14: 0 | AS14: 0 | AT14: 0 | AU14: 0 | AV14: 0 | AW14: 3 | AX14: 3 | AY14: 0 | AZ14: 0 | BA14: 0 | BB14: 0 | BC14: 0 | BD14: 0 | BE14: 0 | BF14: 0 | BG14: 0 | BH14: 0 | BI14: 0 | BJ14: 0 | BK14: 0 | BL14: 0 | BM14: 0 | BN14: 0 | BO14: 0 | BP14: 0 | BQ14: 0 | BR14: 0 | BS14: 0 | BT14: 0 | BU14: 0 | BV14: 0 | BW14: 0 | BX14: 0 | BY14: 0 | BZ14: 0 | CA14: 0 | CB14: 0 | CC14: 0 | CD14: 0 | CE14: 0 | CF14: 0 | CG14: 0 | CH14: 0 | CI14: 0 | CJ14: 0 | CK14: 0 | CL14: 0 | CM14: 0 | CN14: 0 | CO14: 0 | CP14: 0 | CQ14: 0 | CR14: 0 | CS14: 0 | CT14: 0 | CU14: 0 | CV14: 0 | CW14: 0 | CX14: 0 | CY14: 0 | CZ14: 0 | DA14: 0 | DB14: 0 | DC14: 0 | DD14: 0 | DE14: 0 | DF14: 0 | DG14: 0 | DH14: 0 | DI14: 0 | DJ14: 0 | DK14: 0 | DL14: 0 | DM14: 0 | DN14: 0 | DO14: 0 | DP14: 0 | DQ14: 0 | DR14: 0 | DS14: 0 | DT14: 0 | DU14: 0 | DV14: 0 | DW14: 0 | DX14: 0 | DY14: 0 | DZ14: 0 | EA14: 0 | EB14: 0 | EC14: 0 | ED14: 0 | EE14: 0 | EF14: 0 | EG14: 0 | EH14: 0 | EI14: 0 | EJ14: 0 | EK14: 0 | EL14: 0 | EM14: 0 | EN14: 0 | EO14: 0 | EP14: 0 | EQ14: 0 | ER14: 0 | ES14: 0 | ET14: 0 | EU14: 0 | EV14: 0 | EW14: 0 | EX14: 0 | EY14: 0 | EZ14: 0 | FA14: 0 | FB14: 0 | FC14: 0 | FD14: 0 | FE14: 0 | FF14: 0 | FG14: 0 | FH14: 0 | FI14: 0 | FJ14: 0 | FK14: 0 | FL14: 0 | FM14: 0 | FN14: 0 | FO14: 0 | FP14: 0 | FQ14: 0 | FR14: 0 | FS14: 0 | FT14: 0 | FU14: 0 | FV14: 0 | FW14: 0 | FX14: 0 | FY14: 0 | FZ14: 0 | GA14: 0 | GB14: 0 | GC14: 0 | GD14: 0 | GE14: 0 | GF14: 0 | GG14: 0 | GH14: 0 | GI14: 0 | GJ14: 0 | GK14: 0 | GL14: 0 | GM14: 0 | GN14: 0 | GO14: 0 | GP14: 0 | GQ14: 0 | GR14: 0 | GS14: 0 | GT14: 0 | GU14: 0 | GV14: 0 | GW14: 0 | GX14: 0 | GY14: 0 | GZ14: 0 | HA14: 0 | HB14: 0 | HC14: 0 | HD14: 0 | HE14: 0 | HF14: 0 | HG14: 0 | HH14: 0 | HI14: 0 | HJ14: 0 | HK14: 0 | HL14: 0 | HM14: 0 | HN14: 0 | HO14: 0 | HP14: 0 | HQ14: 0 | HR14: 0 | HS14: 0 | HT14: 0 | HU14: 0 | HV14: 0 | HW14: 0 | HX14: 0 | HY14: 0 | HZ14: 0 | IA14: 0 | IB14: 0 | IC14: 0 | ID14: 0 | IE14: 0 | IF14: 0 | IG14: 0 | IH14: 0 | II14: 0 | IJ14: 0 | IK14: 0 | IL14: 0 | IM14: 0 | IN14: 0 | IO14: 0 | IP14: 0 | IQ14: 0 | IR14: 0 | IS14: 0 | IT14: 0 | IU14: 0 | IV14: 0 | IW14: 0 | IX14: 0 | IY14: 0 | IZ14: 0 | JA14: 0 | JB14: 0 | JC14: 0 | JD14: 0 | JE14: 0 | JF14: 0 | JG14: 0 | JH14: 0 | JI14: 0 | JJ14: 0 | JK14: 0 | JL14: 0 | JM14: 0 | JN14: 0 | JO14: 0 | JP14: 0 | JQ14: 0 | JR14: 0 | JS14: 0 | JT14: 0 | JU14: 0 | JV14: 0 | JW14: 0 | JX14: 0 | JY14: 0 | JZ14: 0 | KA14: 0 | KB14: 0 | KC14: 0 | KD14: 0 | KE14: 0 | KF14: 0 | KG14: 0 | KH14: 0 | KI14: 0 | KJ14: 0 | KK14: 0 | KL14: 0 | KM14: 0 | KN14: 0 | KO14: 0 | KP14: 0 | KQ14: 0 | KR14: 0 | KS14: 0 | KT14: 0 | KU14: 0 | KV14: 0 | KW14: 0 | KX14: 0 | KY14: 0 | KZ14: 0 | LA14: 0 | LB14: 0 | LC14: 0 | LD14: 0 | LE14: 0 | LF14: 0 | LG14: 0 | LH14: 0 | LI14: 0 | LJ14: 0 | LK14: 0 | LL14: 0 | LM14: 0 | LN14: 0 | LO14: 0 | LP14: 0 | LQ14: 0 | LR14: 0 | LS14: 0 | LT14: 0 | LU14: 0 | LV14: 0 | LW14: 0 | LX14: 0 | LY14: 0 | LZ14: 0 | MA14: 0 | MB14: 0 | MC14: 0 | MD14: 0 | ME14: 0 | MF14: 0 | MG14: 0 | MH14: 0 | MI14: 0 | MJ14: 0 | MK14: 0 | ML14: 0 | MM14: 0 | MN14: 0 | MO14: 0 | MP14: 0 | MQ14: 0 | MR14: 0 | MS14: 0 | MT14: 0 | MU14: 0 | MV14: 0 | MW14: 0 | MX14: 0 | MY14: 0 | MZ14: 0 | NA14: 0 | NB14: 0 | NC14: 0 | ND14: 0 | NE14: 0 | NF14: ENDE
A15: C&F Lager | NF15: ENDE
A16: 5S Gemba Walk | B16: Min. 1 pro Monat pro Bereich LOG-IN & BAT | C16: 1 | D16: N/A | NF16: ENDE
A17: Accident / LTR | B17: Anzahl schwerer Verletzungen | C17: 0 | D17: EA | NF17: ENDE
A18: Incident / Near Misses | B18: Anzahl Verletzungen | C18: 0 | D18: EA | NF18: ENDE
A19: Safety trigger | B19: Safety Trigger DIET | C19: 5 | D19: N/A | F19: 0 | G19: 0 | H19: 0 | I19: 0 | J19: 0 | K19: 0 | L19: 0 | M19: 0 | N19: 0 | O19: 0 | P19: 0 | Q19: 0 | R19: 0 | S19: 0 | T19: 0 | U19: 0 | V19: 0 | W19: 0 | X19: 0 | Y19: 0 | Z19: 0 | AA19: 0 | AB19: 0 | AC19: 0 | AD19: 0 | AE19: 0 | AF19: 0 | AG19: 0 | AH19: 0 | AI19: 0 | AJ19: 0 | AK19: 0 | AL19: 3 | AM19: 3 | AN19: 0 | AO19: 0 | AP19: 0 | AQ19: 0 | AR19: 0 | AS19: 0 | AT19: 0 | AU19: 0 | AV19: 0 | AW19: 0 | AX19: 0 | AY19: 0 | AZ19: 0 | BA19: 0 | BB19: 0 | BC19: 0 | BD19: 0 | BE19: 0 | BF19: 0 | BG19: 0 | BH19: 0 | BI19: 0 | BJ19: 0 | BK19: 0 | BL19: 0 | BM19: 0 | BN19: 0 | BO19: 0 | BP19: 0 | BQ19: 0 | BR19: 0 | BS19: 0 | BT19: 0 | BU19: 0 | BV19: 0 | BW19: 0 | BX19: 0 | BY19: 0 | BZ19: 0 | CA19: 0 | CB19: 0 | CC19: 0 | CD19: 0 | CE19: 0 | CF19: 0 | CG19: 0 | CH19: 0 | CI19: 0 | CJ19: 0 | CK19: 0 | CL19: 0 | CM19: 0 | CN19: 0 | CO19: 0 | CP19: 0 | CQ19: 0 | CR19: 0 | CS19: 0 | CT19: 0 | CU19: 0 | CV19: 0 | CW19: 0 | CX19: 0 | CY19: 0 | CZ19: 0 | DA19: 0 | DB19: 0 | DC19: 0 | DD19: 0 | DE19: 0 | DF19: 0 | DG19: 0 | DH19: 0 | DI19: 0 | DJ19: 0 | DK19: 0 | DL19: 0 | DM19: 0 | DN19: 0 | DO19: 0 | DP19: 0 | DQ19: 0 | DR19: 0 | DS19: 0 | DT19: 0 | DU19: 0 | DV19: 0 | DW19: 0 | DX19: 0 | DY19: 0 | DZ19: 0 | EA19: 0 | EB19: 0 | EC19: 0 | ED19: 0 | EE19: 0 | EF19: 0 | EG19: 0 | EH19: 0 | EI19: 0 | EJ19: 0 | EK19: 0 | EL19: 0 | EM19: 0 | EN19: 0 | EO19: 0 | EP19: 0 | EQ19: 0 | ER19: 0 | ES19: 0 | ET19: 0 | EU19: 0 | EV19: 0 | EW19: 0 | EX19: 0 | EY19: 0 | EZ19: 0 | FA19: 0 | FB19: 0 | FC19: 0 | FD19: 0 | FE19: 0 | FF19: 0 | FG19: 0 | FH19: 0 | FI19: 0 | FJ19: 0 | FK19: 0 | FL19: 0 | FM19: 0 | FN19: 0 | FO19: 0 | FP19: 0 | FQ19: 0 | FR19: 0 | FS19: 0 | FT19: 0 | FU19: 0 | FV19: 0 | FW19: 0 | FX19: 0 | FY19: 0 | FZ19: 0 | GA19: 0 | GB19: 0 | GC19: 0 | GD19: 0 | GE19: 0 | GF19: 0 | GG19: 0 | GH19: 0 | GI19: 0 | GJ19: 0 | GK19: 0 | GL19: 0 | GM19: 0 | GN19: 0 | GO19: 0 | GP19: 0 | GQ19: 0 | GR19: 0 | GS19: 0 | GT19: 0 | GU19: 0 | GV19: 0 | GW19: 0 | GX19: 0 | GY19: 0 | GZ19: 0 | HA19: 0 | HB19: 0 | HC19: 0 | HD19: 0 | HE19: 0 | HF19: 0 | HG19: 0 | HH19: 0 | HI19: 0 | HJ19: 0 | HK19: 0 | HL19: 0 | HM19: 0 | HN19: 0 | HO19: 0 | HP19: 0 | HQ19: 0 | HR19: 0 | HS19: 0 | HT19: 0 | HU19: 0 | HV19: 0 | HW19: 0 | HX19: 0 | HY19: 0 | HZ19: 0 | IA19: 0 | IB19: 0 | IC19: 0 | ID19: 0 | IE19: 0 | IF19: 0 | IG19: 0 | IH19: 0 | II19: 0 | IJ19: 0 | IK19: 0 | IL19: 0 | IM19: 0 | IN19: 0 | IO19: 0 | IP19: 0 | IQ19: 0 | IR19: 0 | IS19: 0 | IT19: 0 | IU19: 0 | IV19: 0 | IW19: 0 | IX19: 0 | IY19: 0 | IZ19: 0 | JA19: 0 | JB19: 0 | JC19: 0 | JD19: 0 | JE19: 0 | JF19: 0 | JG19: 0 | JH19: 0 | JI19: 0 | JJ19: 0 | JK19: 0 | JL19: 0 | JM19: 0 | JN19: 0 | JO19: 0 | JP19: 0 | JQ19: 0 | JR19: 0 | JS19: 0 | JT19: 0 | JU19: 0 | JV19: 0 | JW19: 0 | JX19: 0 | JY19: 0 | JZ19: 0 | KA19: 0 | KB19: 0 | KC19: 0 | KD19: 0 | KE19: 0 | KF19: 0 | KG19: 0 | KH19: 0 | KI19: 0 | KJ19: 0 | KK19: 0 | KL19: 0 | KM19: 0 | KN19: 0 | KO19: 0 | KP19: 0 | KQ19: 0 | KR19: 0 | KS19: 0 | KT19: 0 | KU19: 0 | KV19: 0 | KW19: 0 | KX19: 0 | KY19: 0 | KZ19: 0 | LA19: 0 | LB19: 0 | LC19: 0 | LD19: 0 | LE19: 0 | LF19: 0 | LG19: 0 | LH19: 0 | LI19: 0 | LJ19: 0 | LK19: 0 | LL19: 0 | LM19: 0 | LN19: 0 | LO19: 0 | LP19: 0 | LQ19: 0 | LR19: 0 | LS19: 0 | LT19: 0 | LU19: 0 | LV19: 0 | LW19: 0 | LX19: 0 | LY19: 0 | LZ19: 0 | MA19: 0 | MB19: 0 | MC19: 0 | MD19: 0 | ME19: 0 | MF19: 0 | MG19: 0 | MH19: 0 | MI19: 0 | MJ19: 0 | MK19: 0 | ML19: 0 | MM19: 0 | MN19: 0 | MO19: 0 | MP19: 0 | MQ19: 0 | MR19: 0 | MS19: 0 | MT19: 0 | MU19: 0 | MV19: 0 | MW19: 0 | MX19: 0 | MY19: 0 | MZ19: 0 | NA19: 0 | NB19: 0 | NC19: 0 | ND19: 0 | NE19: 0 | NF19: ENDE
A20: Leaf Lager | NF20: ENDE
A21: 5S Gemba Walk | B21: Min. 1 pro Monat pro Bereich LOG-IN & BAT | C21: 1 | D21: N/A | NF21: ENDE
A22: Accident / LTR | B22: Anzahl schwerer Verletzungen | C22: 0 | D22: EA | NF22: ENDE
A23: Incident / Near Misses | B23: Anzahl Verletzungen | C23: 0 | D23: EA | NF23: ENDE
A24: Safety trigger | B24: Safety Trigger Leaf | C24: 5 | D24: N/A | F24: 0 | G24: 0 | H24: 0 | I24: 0 | J24: 0 | K24: 0 | L24: 0 | M24: 0 | N24: 0 | O24: 0 | P24: 0 | Q24: 0 | R24: 0 | S24: 0 | T24: 0 | U24: 0 | V24: 0 | W24: 0 | X24: 0 | Y24: 0 | Z24: 0 | AA24: 0 | AB24: 0 | AC24: 0 | AD24: 0 | AE24: 0 | AF24: 0 | AG24: 0 | AH24: 0 | AI24: 0 | AJ24: 0 | AK24: 0 | AL24: 0 | AM24: 0 | AN24: 0 | AO24: 0 | AP24: 0 | AQ24: 0 | AR24: 0 | AS24: 0 | AT24: 0 | AU24: 0 | AV24: 0 | AW24: 0 | AX24: 0 | AY24: 0 | AZ24: 0 | BA24: 0 | BB24: 0 | BC24: 0 | BD24: 0 | BE24: 0 | BF24: 0 | BG24: 0 | BH24: 0 | BI24: 0 | BJ24: 0 | BK24: 0 | BL24: 0 | BM24: 0 | BN24: 0 | BO24: 0 | BP24: 0 | BQ24: 0 | BR24: 0 | BS24: 0 | BT24: 0 | BU24: 0 | BV24: 0 | BW24: 0 | BX24: 0 | BY24: 0 | BZ24: 0 | CA24: 0 | CB24: 0 | CC24: 0 | CD24: 0 | CE24: 0 | CF24: 0 | CG24: 0 | CH24: 0 | CI24: 0 | CJ24: 0 | CK24: 0 | CL24: 0 | CM24: 0 | CN24: 0 | CO24: 0 | CP24: 0 | CQ24: 0 | CR24: 0 | CS24: 0 | CT24: 0 | CU24: 0 | CV24: 0 | CW24: 0 | CX24: 0 | CY24: 0 | CZ24: 0 | DA24: 0 | DB24: 0 | DC24: 0 | DD24: 0 | DE24: 0 | DF24: 0 | DG24: 0 | DH24: 0 | DI24: 0 | DJ24: 0 | DK24: 0 | DL24: 0 | DM24: 0 | DN24: 0 | DO24: 0 | DP24: 0 | DQ24: 0 | DR24: 0 | DS24: 0 | DT24: 0 | DU24: 0 | DV24: 0 | DW24: 0 | DX24: 0 | DY24: 0 | DZ24: 0 | EA24: 0 | EB24: 0 | EC24: 0 | ED24: 0 | EE24: 0 | EF24: 0 | EG24: 0 | EH24: 0 | EI24: 0 | EJ24: 0 | EK24: 0 | EL24: 0 | EM24: 0 | EN24: 0 | EO24: 0 | EP24: 0 | EQ24: 0 | ER24: 0 | ES24: 0 | ET24: 0 | EU24: 0 | EV24: 0 | EW24: 0 | EX24: 0 | EY24: 0 | EZ24: 0 | FA24: 0 | FB24: 0 | FC24: 0 | FD24: 0 | FE24: 0 | FF24: 0 | FG24: 0 | FH24: 0 | FI24: 0 | FJ24: 0 | FK24: 0 | FL24: 0 | FM24: 0 | FN24: 0 | FO24: 0 | FP24: 0 | FQ24: 0 | FR24: 0 | FS24: 0 | FT24: 0 | FU24: 0 | FV24: 0 | FW24: 0 | FX24: 0 | FY24: 0 | FZ24: 0 | GA24: 0 | GB24: 0 | GC24: 0 | GD24: 0 | GE24: 0 | GF24: 0 | GG24: 0 | GH24: 0 | GI24: 0 | GJ24: 0 | GK24: 0 | GL24: 0 | GM24: 0 | GN24: 0 | GO24: 0 | GP24: 0 | GQ24: 0 | GR24: 0 | GS24: 0 | GT24: 0 | GU24: 0 | GV24: 0 | GW24: 0 | GX24: 0 | GY24: 0 | GZ24: 0 | HA24: 0 | HB24: 0 | HC24: 0 | HD24: 0 | HE24: 0 | HF24: 0 | HG24: 0 | HH24: 0 | HI24: 0 | HJ24: 0 | HK24: 0 | HL24: 0 | HM24: 0 | HN24: 0 | HO24: 0 | HP24: 0 | HQ24: 0 | HR24: 0 | HS24: 0 | HT24: 0 | HU24: 0 | HV24: 0 | HW24: 0 | HX24: 0 | HY24: 0 | HZ24: 0 | IA24: 0 | IB24: 0 | IC24: 0 | ID24: 0 | IE24: 0 | IF24: 0 | IG24: 0 | IH24: 0 | II24: 0 | IJ24: 0 | IK24: 0 | IL24: 0 | IM24: 0 | IN24: 0 | IO24: 0 | IP24: 0 | IQ24: 0 | IR24: 0 | IS24: 0 | IT24: 0 | IU24: 0 | IV24: 0 | IW24: 0 | IX24: 0 | IY24: 0 | IZ24: 0 | JA24: 0 | JB24: 0 | JC24: 0 | JD24: 0 | JE24: 0 | JF24: 0 | JG24: 0 | JH24: 0 | JI24: 0 | JJ24: 0 | JK24: 0 | JL24: 0 | JM24: 0 | JN24: 0 | JO24: 0 | JP24: 0 | JQ24: 0 | JR24: 0 | JS24: 0 | JT24: 0 | JU24: 0 | JV24: 0 | JW24: 0 | JX24: 0 | JY24: 0 | JZ24: 0 | KA24: 0 | KB24: 0 | KC24: 0 | KD24: 0 | KE24: 0 | KF24: 0 | KG24: 0 | KH24: 0 | KI24: 0 | KJ24: 0 | KK24: 0 | KL24: 0 | KM24: 0 | KN24: 0 | KO24: 0 | KP24: 0 | KQ24: 0 | KR24: 0 | KS24: 0 | KT24: 0 | KU24: 0 | KV24: 0 | KW24: 0 | KX24: 0 | KY24: 0 | KZ24: 0 | LA24: 0 | LB24: 0 | LC24: 0 | LD24: 0 | LE24: 0 | LF24: 0 | LG24: 0 | LH24: 0 | LI24: 0 | LJ24: 0 | LK24: 0 | LL24: 0 | LM24: 0 | LN24: 0 | LO24: 0 | LP24: 0 | LQ24: 0 | LR24: 0 | LS24: 0 | LT24: 0 | LU24: 0 | LV24: 0 | LW24: 0 | LX24: 0 | LY24: 0 | LZ24: 0 | MA24: 0 | MB24: 0 | MC24: 0 | MD24: 0 | ME24: 0 | MF24: 0 | MG24: 0 | MH24: 0 | MI24: 0 | MJ24: 0 | MK24: 0 | ML24: 0 | MM24: 0 | MN24: 0 | MO24: 0 | MP24: 0 | MQ24: 0 | MR24: 0 | MS24: 0 | MT24: 0 | MU24: 0 | MV24: 0 | MW24: 0 | MX24: 0 | MY24: 0 | MZ24: 0 | NA24: 0 | NB24: 0 | NC24: 0 | ND24: 0 | NE24: 0 | NF24: ENDE
A25: Crewing | NF25: ENDE
A26: Versandhalle FS | B26: Anzahl Mitarbeiter im Bereich | C26: 2 | D26: EA | F26: 2 | G26: 2 | H26: 2 | I26: 2 | M26: 2 | N26: 2 | O26: 2 | P26: 1 | Q26: 1 | T26: 2 | U26: 2 | V26: 2 | W26: 2 | X26: 2 | AA26: 2 | AB26: 2 | AC26: 2 | AD26: 2 | AE26: 2 | AH26: 2 | AI26: 2 | AJ26: 2 | AK26: 2 | AL26: 2 | AO26: 2 | AP26: 2 | AQ26: 1 | AR26: 1 | AS26: 1 | AV26: 1 | AW26: 1 | AX26: 1 | AY26: 1 | AZ26: 1 | BC26: 2 | BD26: 2 | BE26: 2 | BF26: 2 | BG26: 2 | BJ26: 2 | BK26: 2 | BL26: 2 | BM26: 2 | BN26: 2 | BQ26: 2 | BR26: 2 | BS26: 2 | BT26: 2 | BU26: 2 | BX26: 2 | BY26: 2 | BZ26: 2 | CA26: 2 | CB26: 2 | CE26: 2 | CF26: 2 | CG26: 1 | CH26: 1 | CI26: 1 | CL26: 2 | CM26: 2 | CN26: 2 | CO26: 2 | CP26: 2 | CS26: 2 | CT26: 2 | CU26: 2 | CV26: 2 | CW26: 2 | CZ26: 1 | DA26: 1 | DB26: 1 | DC26: 1 | DD26: 1 | DG26: 2 | DH26: 2 | DI26: 2 | DJ26: 2 | DK26: 2 | DN26: 2 | DO26: 2 | DP26: 2 | DQ26: 2 | DR26: 2 | DU26: 2 | DV26: 2 | DW26: 2 | DX26: 2 | DY26: 2 | EB26: 1 | EC26: 1 | ED26: 1 | EE26: 1 | EF26: 1 | EI26: 2 | EJ26: 2 | EK26: 2 | EL26: 0 | EM26: 2 | EP26: 2 | EQ26: 2 | ER26: 2 | ES26: 2 | ET26: 2 | EW26: 0 | EX26: 2 | EY26: 2 | EZ26: 2 | FA26: 2 | FD26: 0 | FE26: 0 | FF26: 0 | FG26: 0 | FH26: 0 | FK26: 2 | FL26: 2 | FM26: 2 | FN26: 2 | FO26: 2 | FR26: 2 | FS26: 2 | FT26: 2 | FU26: 2 | FV26: 2 | FY26: 2 | FZ26: 2 | GA26: 2 | GB26: 2 | GC26: 2 | GF26: 2 | GG26: 2 | GH26: 2 | GI26: 2 | GJ26: 2 | GM26: 2 | GN26: 2 | GO26: 2 | GP26: 2 | GQ26: 2 | GT26: 2 | GU26: 2 | GV26: 2 | GW26: 2 | GX26: 2 | HA26: 2 | HB26: 2 | HC26: 2 | HD26: 2 | HE26: 2 | HH26: 2 | HI26: 2 | HJ26: 2 | HK26: 2 | HL26: 2 | HO26: 2 | HP26: 2 | HQ26: 2 | HR26: 2 | HS26: 2 | HV26: 0 | HW26: 0 | HX26: 0 | HY26: 0 | HZ26: 0 | IC26: 2 | ID26: 2 | IE26: 2 | IF26: 2 | IG26: 2 | IJ26: 2 | IK26: 2 | IL26: 2 | IM26: 1 | IN26: 0 | IQ26: 2 | IR26: 2 | IS26: 2 | IT26: 2 | IU26: 2 | IX26: 2 | IY26: 1 | IZ26: 1 | JA26: 1 | JB26: 1 | JE26: 2 | JF26: 2 | JG26: 2 | JH26: 2 | JI26: 2 | JL26: 2 | JM26: 2 | JN26: 2 | JO26: 2 | JP26: 2 | JS26: 2 | JT26: 0 | JU26: 2 | JV26: 2 | JW26: 2 | JZ26: 1 | KA26: 2 | KB26: 2 | KC26: 2 | KD26: 2 | KG26: 1 | KH26: 1 | KI26: 1 | KJ26: 1 | KK26: 1 | KN26: 1 | KO26: 1 | KP26: 1 | KQ26: 1 | KR26: 1 | KU26: 2 | KV26: 2 | KW26: 2 | KX26: 2 | KY26: 2 | LB26: 2 | LC26: 2 | LD26: 2 | LE26: 2 | LF26: 2 | LI26: 2 | LJ26: 2 | LK26: 2 | LL26: 2 | LM26: 2 | LP26: 2 | LQ26: 2 | LR26: 2 | LS26: 2 | LT26: 2 | LW26: 2 | LX26: 1 | LY26: 1 | LZ26: 1 | MA26: 1 | MD26: 1 | ME26: 2 | MF26: 2 | MG26: 2 | MH26: 2 | MK26: 2 | ML26: 2 | MM26: 2 | MN26: 2 | MO26: 1 | MR26: 1 | MS26: 1 | MT26: 1 | MU26: 1 | MV26: 1 | NF26: ENDE
A27: Versandhalle ZW | B27: Anzahl Mitarbeiter im Bereich | C27: 1 | D27: EA | F27: 0 | G27: 0 | H27: 0 | I27: 0 | M27: 0 | N27: 0 | O27: 0 | P27: 0 | Q27: 0 | T27: 0 | U27: 0 | V27: 0 | W27: 0 | X27: 0 | AA27: 0 | AB27: 0 | AC27: 0 | AD27: 0 | AE27: 0 | AH27: 0 | AI27: 0 | AJ27: 0 | AK27: 0 | AL27: 0 | AO27: 0 | AP27: 0 | AQ27: 1 | AR27: 1 | AS27: 1 | AV27: 1 | AW27: 1 | AX27: 1 | AY27: 1 | AZ27: 1 | BC27: 0 | BD27: 0 | BE27: 0 | BF27: 0 | BG27: 0 | BJ27: 0 | BK27: 0 | BL27: 0 | BM27: 0 | BN27: 0 | BQ27: 0 | BR27: 0 | BS27: 0 | BT27: 0 | BU27: 0 | BX27: 0 | BY27: 0 | BZ27: 0 | CA27: 0 | CB27: 0 | CE27: 0 | CF27: 0 | CG27: 1 | CH27: 1 | CI27: 1 | CL27: 0 | CM27: 0 | CN27: 0 | CO27: 0 | CP27: 0 | CS27: 0 | CT27: 0 | CU27: 0 | CV27: 0 | CW27: 0 | CZ27: 1 | DA27: 1 | DB27: 1 | DC27: 1 | DD27: 1 | DG27: 0 | DH27: 0 | DI27: 0 | DJ27: 0 | DK27: 0 | DN27: 0 | DO27: 0 | DP27: 0 | DQ27: 0 | DR27: 0 | DU27: 0 | DV27: 0 | DW27: 0 | DX27: 0 | DY27: 0 | EB27: 1 | EC27: 1 | ED27: 1 | EE27: 1 | EF27: 1 | EI27: 0 | EJ27: 0 | EK27: 0 | EL27: 0 | EM27: 0 | EP27: 0 | EQ27: 0 | ER27: 0 | ES27: 0 | ET27: 0 | EW27: 0 | EX27: 0 | EY27: 0 | EZ27: 0 | FA27: 0 | FD27: 0 | FE27: 0 | FF27: 0 | FG27: 0 | FH27: 0 | FK27: 0 | FL27: 0 | FM27: 0 | FN27: 0 | FO27: 0 | FR27: 0 | FS27: 0 | FT27: 0 | FU27: 0 | FV27: 0 | FY27: 0 | FZ27: 0 | GA27: 0 | GB27: 0 | GC27: 0 | GF27: 0 | GG27: 0 | GH27: 0 | GI27: 0 | GJ27: 0 | GM27: 0 | GN27: 0 | GO27: 0 | GP27: 0 | GQ27: 0 | GT27: 0 | GU27: 0 | GV27: 0 | GW27: 0 | GX27: 0 | HA27: 0 | HB27: 0 | HC27: 0 | HD27: 0 | HE27: 0 | HH27: 0 | HI27: 0 | HJ27: 0 | HK27: 0 | HL27: 0 | HO27: 0 | HP27: 0 | HQ27: 0 | HR27: 0 | HS27: 0 | HV27: 0 | HW27: 0 | HX27: 0 | HY27: 0 | HZ27: 0 | IC27: 0 | ID27: 0 | IE27: 0 | IF27: 0 | IG27: 0 | IJ27: 0 | IK27: 0 | IL27: 0 | IM27: 0 | IN27: 0 | IQ27: 0 | IR27: 0 | IS27: 0 | IT27: 0 | IU27: 0 | IX27: 0 | IY27: 0 | IZ27: 1 | JA27: 1 | JB27: 1 | JE27: 0 | JF27: 0 | JG27: 0 | JH27: 0 | JI27: 0 | JL27: 0 | JM27: 0 | JN27: 0 | JO27: 0 | JP27: 0 | JS27: 0 | JT27: 0 | JU27: 0 | JV27: 0 | JW27: 0 | JZ27: 1 | KA27: 0 | KB27: 0 | KC27: 0 | KD27: 0 | KG27: 1 | KH27: 1 | KI27: 1 | KJ27: 1 | KK27: 1 | KN27: 1 | KO27: 1 | KP27: 1 | KQ27: 1 | KR27: 1 | KU27: 0 | KV27: 0 | KW27: 0 | KX27: 0 | KY27: 0 | LB27: 0 | LC27: 0 | LD27: 0 | LE27: 0 | LF27: 0 | LI27: 0 | LJ27: 0 | LK27: 0 | LL27: 0 | LM27: 0 | LP27: 0 | LQ27: 0 | LR27: 0 | LS27: 0 | LT27: 0 | LW27: 0 | LX27: 1 | LY27: 1 | LZ27: 1 | MA27: 1 | MD27: 1 | ME27: 0 | MF27: 0 | MG27: 0 | MH27: 0 | MK27: 0 | ML27: 0 | MM27: 0 | MN27: 0 | MO27: 0 | MR27: 1 | MS27: 0 | MT27: 0 | MU27: 0 | MV27: 0 | NF27: ENDE
A28: Versandhalle SS | B28: Anzahl Mitarbeiter im Bereich | C28: 2 | D28: EA | F28: 2 | G28: 2 | H28: 2 | I28: 2 | M28: 2 | N28: 2 | O28: 2 | P28: 2 | Q28: 2 | T28: 2 | U28: 2 | V28: 2 | W28: 2 | X28: 2 | AA28: 2 | AB28: 2 | AC28: 2 | AD28: 2 | AE28: 2 | AH28: 2 | AI28: 2 | AJ28: 2 | AK28: 2 | AL28: 2 | AO28: 2 | AP28: 1 | AQ28: 1 | AR28: 1 | AS28: 1 | AV28: 1 | AW28: 1 | AX28: 1 | AY28: 1 | AZ28: 1 | BC28: 2 | BD28: 2 | BE28: 2 | BF28: 2 | BG28: 2 | BJ28: 2 | BK28: 2 | BL28: 2 | BM28: 2 | BN28: 2 | BQ28: 2 | BR28: 2 | BS28: 2 | BT28: 2 | BU28: 2 | BX28: 2 | BY28: 2 | BZ28: 2 | CA28: 2 | CB28: 2 | CE28: 2 | CF28: 2 | CG28: 1 | CH28: 1 | CI28: 1 | CL28: 2 | CM28: 2 | CN28: 2 | CO28: 2 | CP28: 2 | CS28: 2 | CT28: 2 | CU28: 2 | CV28: 2 | CW28: 2 | CZ28: 1 | DA28: 1 | DB28: 1 | DC28: 1 | DD28: 1 | DG28: 2 | DH28: 2 | DI28: 2 | DJ28: 2 | DK28: 2 | DN28: 2 | DO28: 2 | DP28: 2 | DQ28: 2 | DR28: 2 | DU28: 2 | DV28: 2 | DW28: 2 | DX28: 2 | DY28: 2 | EB28: 1 | EC28: 1 | ED28: 1 | EE28: 1 | EF28: 1 | EI28: 2 | EJ28: 2 | EK28: 2 | EL28: 0 | EM28: 2 | EP28: 2 | EQ28: 2 | ER28: 2 | ES28: 2 | ET28: 2 | EW28: 0 | EX28: 2 | EY28: 2 | EZ28: 2 | FA28: 2 | FD28: 0 | FE28: 0 | FF28: 0 | FG28: 0 | FH28: 0 | FK28: 2 | FL28: 2 | FM28: 2 | FN28: 2 | FO28: 2 | FR28: 2 | FS28: 2 | FT28: 1 | FU28: 1 | FV28: 2 | FY28: 2 | FZ28: 2 | GA28: 2 | GB28: 1 | GC28: 1 | GF28: 2 | GG28: 2 | GH28: 2 | GI28: 2 | GJ28: 2 | GM28: 1 | GN28: 1 | GO28: 1 | GP28: 2 | GQ28: 2 | GT28: 2 | GU28: 2 | GV28: 2 | GW28: 2 | GX28: 2 | HA28: 2 | HB28: 2 | HC28: 2 | HD28: 2 | HE28: 2 | HH28: 2 | HI28: 2 | HJ28: 2 | HK28: 2 | HL28: 2 | HO28: 2 | HP28: 2 | HQ28: 2 | HR28: 2 | HS28: 2 | HV28: 0 | HW28: 0 | HX28: 0 | HY28: 0 | HZ28: 0 | IC28: 2 | ID28: 2 | IE28: 2 | IF28: 2 | IG28: 1 | IJ28: 2 | IK28: 2 | IL28: 1 | IM28: 2 | IN28: 0 | IQ28: 2 | IR28: 2 | IS28: 2 | IT28: 2 | IU28: 2 | IX28: 2 | IY28: 2 | IZ28: 1 | JA28: 1 | JB28: 1 | JE28: 2 | JF28: 2 | JG28: 2 | JH28: 2 | JI28: 2 | JL28: 2 | JM28: 2 | JN28: 2 | JO28: 2 | JP28: 2 | JS28: 2 | JT28: 0 | JU28: 2 | JV28: 2 | JW28: 2 | JZ28: 1 | KA28: 2 | KB28: 2 | KC28: 2 | KD28: 2 | KG28: 1 | KH28: 1 | KI28: 1 | KJ28: 1 | KK28: 1 | KN28: 1 | KO28: 1 | KP28: 1 | KQ28: 1 | KR28: 1 | KU28: 2 | KV28: 2 | KW28: 2 | KX28: 2 | KY28: 2 | LB28: 2 | LC28: 2 | LD28: 2 | LE28: 2 | LF28: 2 | LI28: 2 | LJ28: 2 | LK28: 2 | LL28: 2 | LM28: 2 | LP28: 2 | LQ28: 2 | LR28: 2 | LS28: 2 | LT28: 2 | LW28: 2 | LX28: 1 | LY28: 1 | LZ28: 1 | MA28: 1 | MD28: 1 | ME28: 2 | MF28: 2 | MG28: 2 | MH28: 2 | MK28: 2 | ML28: 2 | MM28: 2 | MN28: 1 | MO28: 1 | MR28: 1 | MS28: 1 | MT28: 1 | MU28: 1 | MV28: 1 | NF28: ENDE
A29: Versandhalle NS | B29: Anzahl Mitarbeiter im Bereich | C29: 2 | D29: EA | F29: 2 | G29: 2 | H29: 2 | I29: 2 | M29: 2 | N29: 2 | O29: 2 | P29: 2 | Q29: 2 | T29: 2 | U29: 2 | V29: 2 | W29: 2 | X29: 2 | AA29: 2 | AB29: 2 | AC29: 2 | AD29: 2 | AE29: 2 | AH29: 2 | AI29: 2 | AJ29: 2 | AK29: 2 | AL29: 2 | AO29: 2 | AP29: 2 | AQ29: 2 | AR29: 2 | AS29: 2 | AV29: 2 | AW29: 2 | AX29: 2 | AY29: 2 | AZ29: 2 | BC29: 2 | BD29: 2 | BE29: 2 | BF29: 2 | BG29: 2 | BJ29: 2 | BK29: 2 | BL29: 2 | BM29: 2 | BN29: 2 | BQ29: 2 | BR29: 2 | BS29: 2 | BT29: 2 | BU29: 2 | BX29: 2 | BY29: 2 | BZ29: 2 | CA29: 2 | CB29: 2 | CE29: 1 | CF29: 1 | CG29: 1 | CH29: 1 | CI29: 1 | CL29: 1 | CM29: 1 | CN29: 0 | CO29: 0 | CP29: 0 | CS29: 2 | CT29: 2 | CU29: 2 | CV29: 2 | CW29: 2 | CZ29: 2 | DA29: 2 | DB29: 2 | DC29: 2 | DD29: 2 | DG29: 2 | DH29: 2 | DI29: 2 | DJ29: 2 | DK29: 2 | DN29: 1 | DO29: 1 | DP29: 1 | DQ29: 1 | DR29: 1 | DU29: 1 | DV29: 1 | DW29: 1 | DX29: 1 | DY29: 1 | EB29: 1 | EC29: 1 | ED29: 1 | EE29: 1 | EF29: 1 | EI29: 1 | EJ29: 1 | EK29: 1 | EL29: 0 | EM29: 1 | EP29: 1 | EQ29: 1 | ER29: 1 | ES29: 1 | ET29: 1 | EW29: 0 | EX29: 1 | EY29: 1 | EZ29: 1 | FA29: 1 | FD29: 0 | FE29: 0 | FF29: 0 | FG29: 0 | FH29: 0 | FK29: 1 | FL29: 1 | FM29: 1 | FN29: 1 | FO29: 1 | FR29: 1 | FS29: 1 | FT29: 1 | FU29: 1 | FV29: 1 | FY29: 1 | FZ29: 1 | GA29: 1 | GB29: 1 | GC29: 1 | GF29: 1 | GG29: 1 | GH29: 1 | GI29: 1 | GJ29: 1 | GM29: 1 | GN29: 1 | GO29: 1 | GP29: 1 | GQ29: 1 | GT29: 1 | GU29: 1 | GV29: 1 | GW29: 1 | GX29: 1 | HA29: 1 | HB29: 1 | HC29: 1 | HD29: 1 | HE29: 1 | HH29: 1 | HI29: 1 | HJ29: 1 | HK29: 1 | HL29: 1 | HO29: 1 | HP29: 1 | HQ29: 1 | HR29: 1 | HS29: 1 | HV29: 0 | HW29: 0 | HX29: 0 | HY29: 0 | HZ29: 0 | IC29: 1 | ID29: 1 | IE29: 1 | IF29: 1 | IG29: 1 | IJ29: 1 | IK29: 1 | IL29: 1 | IM29: 1 | IN29: 0 | IQ29: 1 | IR29: 1 | IS29: 1 | IT29: 1 | IU29: 1 | IX29: 1 | IY29: 1 | IZ29: 1 | JA29: 1 | JB29: 1 | JE29: 1 | JF29: 1 | JG29: 1 | JH29: 1 | JI29: 1 | JL29: 0 | JM29: 0 | JN29: 0 | JO29: 0 | JP29: 0 | JS29: 0 | JT29: 0 | JU29: 1 | JV29: 1 | JW29: 1 | JZ29: 1 | KA29: 1 | KB29: 1 | KC29: 1 | KD29: 1 | KG29: 1 | KH29: 1 | KI29: 1 | KJ29: 1 | KK29: 1 | KN29: 1 | KO29: 1 | KP29: 1 | KQ29: 1 | KR29: 1 | KU29: 1 | KV29: 1 | KW29: 1 | KX29: 1 | KY29: 1 | LB29: 1 | LC29: 1 | LD29: 1 | LE29: 1 | LF29: 1 | LI29: 1 | LJ29: 1 | LK29: 1 | LL29: 1 | LM29: 1 | LP29: 1 | LQ29: 1 | LR29: 0 | LS29: 0 | LT29: 0 | LW29: 0 | LX29: 0 | LY29: 0 | LZ29: 0 | MA29: 0 | MD29: 1 | ME29: 1 | MF29: 1 | MG29: 1 | MH29: 1 | MK29: 1 | ML29: 1 | MM29: 1 | MN29: 1 | MO29: 1 | MR29: 0 | MS29: 0 | MT29: 0 | MU29: 0 | MV29: 0 | NF29: ENDE
A30: Rampe 6 FS | B30: Anzahl Mitarbeiter im Bereich | C30: 1 | D30: EA | F30: 1 | G30: 1 | H30: 1 | I30: 1 | M30: 1 | N30: 1 | O30: 1 | P30: 1 | Q30: 1 | T30: 1 | U30: 1 | V30: 1 | W30: 1 | X30: 1 | AA30: 1 | AB30: 1 | AC30: 1 | AD30: 1 | AE30: 1 | AH30: 1 | AI30: 1 | AJ30: 1 | AK30: 1 | AL30: 1 | AO30: 1 | AP30: 1 | AQ30: 1 | AR30: 1 | AS30: 1 | AV30: 1 | AW30: 1 | AX30: 1 | AY30: 1 | AZ30: 1 | BC30: 1 | BD30: 1 | BE30: 1 | BF30: 1 | BG30: 1 | BJ30: 1 | BK30: 1 | BL30: 1 | BM30: 1 | BN30: 1 | BQ30: 1 | BR30: 1 | BS30: 1 | BT30: 1 | BU30: 1 | BX30: 1 | BY30: 1 | BZ30: 1 | CA30: 1 | CB30: 1 | CE30: 2 | CF30: 1 | CG30: 1 | CH30: 1 | CI30: 1 | CL30: 1 | CM30: 1 | CN30: 1 | CO30: 1 | CP30: 1 | CS30: 1 | CT30: 1 | CU30: 1 | CV30: 1 | CW30: 1 | CZ30: 1 | DA30: 1 | DB30: 1 | DC30: 1 | DD30: 1 | DG30: 1 | DH30: 1 | DI30: 1 | DJ30: 1 | DK30: 1 | DN30: 1 | DO30: 1 | DP30: 1 | DQ30: 1 | DR30: 1 | DU30: 1 | DV30: 1 | DW30: 1 | DX30: 1 | DY30: 1 | EB30: 1 | EC30: 1 | ED30: 1 | EE30: 1 | EF30: 1 | EI30: 1 | EJ30: 1 | EK30: 1 | EL30: 0 | EM30: 1 | EP30: 1 | EQ30: 1 | ER30: 1 | ES30: 1 | ET30: 1 | EW30: 0 | EX30: 1 | EY30: 1 | EZ30: 1 | FA30: 1 | FD30: 0 | FE30: 0 | FF30: 0 | FG30: 0 | FH30: 0 | FK30: 1 | FL30: 1 | FM30: 1 | FN30: 1 | FO30: 1 | FR30: 1 | FS30: 1 | FT30: 1 | FU30: 1 | FV30: 1 | FY30: 1 | FZ30: 1 | GA30: 1 | GB30: 1 | GC30: 1 | GF30: 1 | GG30: 1 | GH30: 1 | GI30: 1 | GJ30: 1 | GM30: 1 | GN30: 1 | GO30: 1 | GP30: 1 | GQ30: 1 | GT30: 1 | GU30: 1 | GV30: 1 | GW30: 1 | GX30: 1 | HA30: 1 | HB30: 1 | HC30: 1 | HD30: 1 | HE30: 1 | HH30: 1 | HI30: 1 | HJ30: 1 | HK30: 1 | HL30: 1 | HO30: 1 | HP30: 1 | HQ30: 1 | HR30: 1 | HS30: 1 | HV30: 0 | HW30: 0 | HX30: 0 | HY30: 0 | HZ30: 0 | IC30: 1 | ID30: 1 | IE30: 1 | IF30: 1 | IG30: 1 | IJ30: 0 | IK30: 1 | IL30: 1 | IM30: 1 | IN30: 0 | IQ30: 1 | IR30: 1 | IS30: 1 | IT30: 1 | IU30: 1 | IX30: 1 | IY30: 1 | IZ30: 1 | JA30: 1 | JB30: 1 | JE30: 1 | JF30: 1 | JG30: 1 | JH30: 1 | JI30: 1 | JL30: 1 | JM30: 1 | JN30: 1 | JO30: 1 | JP30: 1 | JS30: 1 | JT30: 0 | JU30: 1 | JV30: 1 | JW30: 1 | JZ30: 1 | KA30: 1 | KB30: 1 | KC30: 1 | KD30: 1 | KG30: 1 | KH30: 1 | KI30: 1 | KJ30: 1 | KK30: 1 | KN30: 1 | KO30: 1 | KP30: 1 | KQ30: 1 | KR30: 1 | KU30: 1 | KV30: 1 | KW30: 1 | KX30: 1 | KY30: 1 | LB30: 1 | LC30: 1 | LD30: 1 | LE30: 1 | LF30: 1 | LI30: 1 | LJ30: 1 | LK30: 1 | LL30: 1 | LM30: 1 | LP30: 1 | LQ30: 1 | LR30: 1 | LS30: 1 | LT30: 1 | LW30: 1 | LX30: 1 | LY30: 1 | LZ30: 1 | MA30: 1 | MD30: 1 | ME30: 1 | MF30: 1 | MG30: 1 | MH30: 1 | MK30: 1 | ML30: 1 | MM30: 1 | MN30: 1 | MO30: 1 | MR30: 1 | MS30: 1 | MT30: 1 | MU30: 1 | MV30: 1 | NF30: ENDE
A31: Rampe 6 ZW | B31: Anzahl Mitarbeiter im Bereich | C31: 1 | D31: EA | F31: 1 | G31: 1 | H31: 1 | I31: 1 | M31: 1 | N31: 1 | O31: 1 | P31: 1 | Q31: 1 | T31: 1 | U31: 1 | V31: 1 | W31: 1 | X31: 1 | AA31: 1 | AB31: 1 | AC31: 1 | AD31: 1 | AE31: 0 | AH31: 1 | AI31: 1 | AJ31: 1 | AK31: 1 | AL31: 1 | AO31: 1 | AP31: 1 | AQ31: 1 | AR31: 1 | AS31: 1 | AV31: 1 | AW31: 1 | AX31: 1 | AY31: 1 | AZ31: 1 | BC31: 1 | BD31: 1 | BE31: 1 | BF31: 1 | BG31: 1 | BJ31: 1 | BK31: 1 | BL31: 1 | BM31: 1 | BN31: 1 | BQ31: 1 | BR31: 1 | BS31: 1 | BT31: 1 | BU31: 1 | BX31: 1 | BY31: 1 | BZ31: 1 | CA31: 1 | CB31: 1 | CE31: 0 | CF31: 1 | CG31: 1 | CH31: 1 | CI31: 1 | CL31: 1 | CM31: 1 | CN31: 1 | CO31: 1 | CP31: 1 | CS31: 1 | CT31: 1 | CU31: 1 | CV31: 1 | CW31: 1 | CZ31: 0 | DA31: 0 | DB31: 0 | DC31: 0 | DD31: 0 | DG31: 1 | DH31: 1 | DI31: 1 | DJ31: 1 | DK31: 1 | DN31: 1 | DO31: 1 | DP31: 1 | DQ31: 1 | DR31: 1 | DU31: 1 | DV31: 1 | DW31: 1 | DX31: 1 | DY31: 1 | EB31: 1 | EC31: 1 | ED31: 1 | EE31: 1 | EF31: 1 | EI31: 1 | EJ31: 1 | EK31: 1 | EL31: 0 | EM31: 1 | EP31: 1 | EQ31: 1 | ER31: 1 | ES31: 1 | ET31: 1 | EW31: 0 | EX31: 1 | EY31: 1 | EZ31: 1 | FA31: 1 | FD31: 0 | FE31: 0 | FF31: 0 | FG31: 0 | FH31: 0 | FK31: 1 | FL31: 1 | FM31: 1 | FN31: 1 | FO31: 1 | FR31: 1 | FS31: 1 | FT31: 1 | FU31: 1 | FV31: 1 | FY31: 1 | FZ31: 1 | GA31: 1 | GB31: 1 | GC31: 1 | GF31: 1 | GG31: 1 | GH31: 1 | GI31: 1 | GJ31: 1 | GM31: 1 | GN31: 1 | GO31: 1 | GP31: 1 | GQ31: 1 | GT31: 1 | GU31: 1 | GV31: 1 | GW31: 1 | GX31: 1 | HA31: 1 | HB31: 1 | HC31: 1 | HD31: 1 | HE31: 1 | HH31: 1 | HI31: 1 | HJ31: 1 | HK31: 1 | HL31: 1 | HO31: 1 | HP31: 1 | HQ31: 1 | HR31: 1 | HS31: 1 | HV31: 0 | HW31: 0 | HX31: 0 | HY31: 0 | HZ31: 0 | IC31: 1 | ID31: 1 | IE31: 1 | IF31: 1 | IG31: 1 | IJ31: 1 | IK31: 1 | IL31: 1 | IM31: 1 | IN31: 0 | IQ31: 1 | IR31: 1 | IS31: 1 | IT31: 1 | IU31: 1 | IX31: 1 | IY31: 1 | IZ31: 1 | JA31: 1 | JB31: 1 | JE31: 1 | JF31: 1 | JG31: 1 | JH31: 1 | JI31: 1 | JL31: 1 | JM31: 1 | JN31: 1 | JO31: 1 | JP31: 1 | JS31: 1 | JT31: 0 | JU31: 1 | JV31: 1 | JW31: 1 | JZ31: 1 | KA31: 1 | KB31: 1 | KC31: 1 | KD31: 1 | KG31: 1 | KH31: 1 | KI31: 1 | KJ31: 1 | KK31: 1 | KN31: 1 | KO31: 1 | KP31: 1 | KQ31: 1 | KR31: 1 | KU31: 1 | KV31: 1 | KW31: 1 | KX31: 1 | KY31: 1 | LB31: 1 | LC31: 1 | LD31: 1 | LE31: 1 | LF31: 1 | LI31: 1 | LJ31: 1 | LK31: 1 | LL31: 1 | LM31: 1 | LP31: 1 | LQ31: 1 | LR31: 1 | LS31: 1 | LT31: 1 | LW31: 1 | LX31: 1 | LY31: 1 | LZ31: 1 | MA31: 1 | MD31: 1 | ME31: 1 | MF31: 1 | MG31: 1 | MH31: 1 | MK31: 1 | ML31: 1 | MM31: 1 | MN31: 1 | MO31: 1 | MR31: 1 | MS31: 1 | MT31: 1 | MU31: 1 | MV31: 1 | NF31: ENDE
A32: Rampe 6 SS | B32: Anzahl Mitarbeiter im Bereich | C32: 1 | D32: EA | F32: 0 | G32: 0 | H32: 0 | I32: 0 | M32: 0 | N32: 0 | O32: 0 | P32: 0 | Q32: 0 | T32: 0 | U32: 0 | V32: 0 | W32: 0 | X32: 0 | AA32: 0 | AB32: 0 | AC32: 0 | AD32: 0 | AE32: 0 | AH32: 0 | AI32: 0 | AJ32: 0 | AK32: 0 | AL32: 0 | AO32: 0 | AP32: 0 | AQ32: 0 | AR32: 0 | AS32: 0 | AV32: 0 | AW32: 0 | AX32: 0 | AY32: 0 | AZ32: 0 | BC32: 0 | BD32: 0 | BE32: 0 | BF32: 0 | BG32: 0 | BJ32: 0 | BK32: 0 | BL32: 0 | BM32: 0 | BN32: 0 | BQ32: 0 | BR32: 0 | BS32: 0 | BT32: 0 | BU32: 0 | BX32: 0 | BY32: 0 | BZ32: 0 | CA32: 0 | CB32: 0 | CE32: 2 | CF32: 1 | CG32: 1 | CH32: 1 | CI32: 1 | CL32: 1 | CM32: 1 | CN32: 1 | CO32: 1 | CP32: 1 | CS32: 1 | CT32: 1 | CU32: 1 | CV32: 1 | CW32: 1 | CZ32: 1 | DA32: 1 | DB32: 1 | DC32: 1 | DD32: 1 | DG32: 0 | DH32: 0 | DI32: 0 | DJ32: 0 | DK32: 0 | DN32: 0 | DO32: 0 | DP32: 0 | DQ32: 0 | DR32: 0 | DU32: 0 | DV32: 0 | DW32: 0 | DX32: 0 | DY32: 0 | EB32: 0 | EC32: 0 | ED32: 0 | EE32: 0 | EF32: 0 | EI32: 0 | EJ32: 0 | EK32: 0 | EL32: 0 | EM32: 0 | EP32: 0 | EQ32: 0 | ER32: 0 | ES32: 0 | ET32: 0 | EW32: 0 | EX32: 0 | EY32: 0 | EZ32: 0 | FA32: 0 | FD32: 0 | FE32: 0 | FF32: 0 | FG32: 0 | FH32: 0 | FK32: 0 | FL32: 0 | FM32: 0 | FN32: 0 | FO32: 0 | FR32: 0 | FS32: 0 | FT32: 0 | FU32: 0 | FV32: 0 | FY32: 0 | FZ32: 0 | GA32: 0 | GB32: 0 | GC32: 0 | GF32: 0 | GG32: 0 | GH32: 0 | GI32: 0 | GJ32: 0 | GM32: 0 | GN32: 0 | GO32: 0 | GP32: 0 | GQ32: 0 | GT32: 0 | GU32: 0 | GV32: 0 | GW32: 0 | GX32: 0 | HA32: 0 | HB32: 0 | HC32: 0 | HD32: 0 | HE32: 0 | HH32: 0 | HI32: 0 | HJ32: 0 | HK32: 0 | HL32: 0 | HO32: 0 | HP32: 0 | HQ32: 0 | HR32: 0 | HS32: 0 | HV32: 0 | HW32: 0 | HX32: 0 | HY32: 0 | HZ32: 0 | IC32: 0 | ID32: 0 | IE32: 0 | IF32: 0 | IG32: 0 | IJ32: 0 | IK32: 0 | IL32: 0 | IM32: 0 | IN32: 0 | IQ32: 0 | IR32: 0 | IS32: 0 | IT32: 0 | IU32: 0 | IX32: 0 | IY32: 0 | IZ32: 0 | JA32: 0 | JB32: 0 | JE32: 0 | JF32: 0 | JG32: 0 | JH32: 0 | JI32: 0 | JL32: 0 | JM32: 0 | JN32: 0 | JO32: 0 | JP32: 0 | JS32: 0 | JT32: 0 | JU32: 0 | JV32: 0 | JW32: 0 | JZ32: 0 | KA32: 0 | KB32: 0 | KC32: 0 | KD32: 0 | KG32: 0 | KH32: 0 | KI32: 0 | KJ32: 0 | KK32: 0 | KN32: 0 | KO32: 0 | KP32: 0 | KQ32: 0 | KR32: 0 | KU32: 1 | KV32: 1 | KW32: 1 | KX32: 1 | KY32: 1 | LB32: 1 | LC32: 1 | LD32: 1 | LE32: 1 | LF32: 1 | LI32: 1 | LJ32: 1 | LK32: 1 | LL32: 1 | LM32: 1 | LP32: 0 | LQ32: 0 | LR32: 0 | LS32: 0 | LT32: 0 | LW32: 0 | LX32: 0 | LY32: 0 | LZ32: 0 | MA32: 0 | MD32: 0 | ME32: 0 | MF32: 0 | MG32: 0 | MH32: 0 | MK32: 0 | ML32: 0 | MM32: 0 | MN32: 0 | MO32: 0 | MR32: 0 | MS32: 0 | MT32: 0 | MU32: 0 | MV32: 0 | NF32: ENDE
A33: I - Punkt II FS | B33: Anzahl Mitarbeiter im Bereich | C33: 1 | NF33: ENDE
A34: I - Punkt II SS | B34: Anzahl Mitarbeiter im Bereich | C34: 1 | NF34: ENDE
A35: I - Punkt II NS | B35: Anzahl Mitarbeiter im Bereich | C35: 0 | NF35: ENDE
A36: Versandhalle Arbeitszeit | B36: Soll Stunden Versandhalle (automatisch) | C36: =SUM(C26:C29)*8 -> 56 | D36: Hours | F36: =(F26+F27+F28+F29)*8 -> 48 | G36: =(G26+G27+G28+G29)*8 -> 48 | H36: =(H26+H27+H28+H29)*8 -> 48 | I36: =(I26+I27+I28+I29)*8 -> 48 | M36: =(M26+M27+M28+M29)*8 -> 48 | N36: =(N26+N27+N28+N29)*8 -> 48 | O36: =(O26+O27+O28+O29)*8 -> 48 | P36: =(P26+P27+P28+P29)*8 -> 40 | Q36: =(Q26+Q27+Q28+Q29)*8 -> 40 | T36: =(T26+T27+T28+T29)*8 -> 48 | U36: =(U26+U27+U28+U29)*8 -> 48 | V36: =(V26+V27+V28+V29)*8 -> 48 | W36: =(W26+W27+W28+W29)*8 -> 48 | X36: =(X26+X27+X28+X29)*8 -> 48 | AA36: =(AA26+AA27+AA28+AA29)*8 -> 48 | AB36: =(AB26+AB27+AB28+AB29)*8 -> 48 | AC36: =(AC26+AC27+AC28+AC29)*8 -> 48 | AD36: =(AD26+AD27+AD28+AD29)*8 -> 48 | AE36: =(AE26+AE27+AE28+AE29)*8 -> 48 | AH36: =(AH26+AH27+AH28+AH29)*8 -> 48 | AI36: =(AI26+AI27+AI28+AI29)*8 -> 48 | AJ36: =(AJ26+AJ27+AJ28+AJ29)*8 -> 48 | AK36: =(AK26+AK27+AK28+AK29)*8 -> 48 | AL36: =(AL26+AL27+AL28+AL29)*8 -> 48 | AO36: =(AO26+AO27+AO28+AO29)*8 -> 48 | AP36: =(AP26+AP27+AP28+AP29)*8 -> 40 | AQ36: =(AQ26+AQ27+AQ28+AQ29)*8 -> 40 | AR36: =(AR26+AR27+AR28+AR29)*8 -> 40 | AS36: =(AS26+AS27+AS28+AS29)*8 -> 40 | AV36: =(AV26+AV27+AV28+AV29)*8 -> 40 | AW36: =(AW26+AW27+AW28+AW29)*8 -> 40 | AX36: =(AX26+AX27+AX28+AX29)*8 -> 40 | AY36: =(AY26+AY27+AY28+AY29)*8 -> 40 | AZ36: =(AZ26+AZ27+AZ28+AZ29)*8 -> 40 | BC36: =(BC26+BC27+BC28+BC29)*8 -> 48 | BD36: =(BD26+BD27+BD28+BD29)*8 -> 48 | BE36: =(BE26+BE27+BE28+BE29)*8 -> 48 | BF36: =(BF26+BF27+BF28+BF29)*8 -> 48 | BG36: =(BG26+BG27+BG28+BG29)*8 -> 48 | BJ36: =(BJ26+BJ27+BJ28+BJ29)*8 -> 48 | BK36: =(BK26+BK27+BK28+BK29)*8 -> 48 | BL36: =(BL26+BL27+BL28+BL29)*8 -> 48 | BM36: =(BM26+BM27+BM28+BM29)*8 -> 48 | BN36: =(BN26+BN27+BN28+BN29)*8 -> 48 | BQ36: =(BQ26+BQ27+BQ28+BQ29)*8 -> 48 | BR36: =(BR26+BR27+BR28+BR29)*8 -> 48 | BS36: =(BS26+BS27+BS28+BS29)*8 -> 48 | BT36: =(BT26+BT27+BT28+BT29)*8 -> 48 | BU36: =(BU26+BU27+BU28+BU29)*8 -> 48 | BX36: =(BX26+BX27+BX28+BX29)*8 -> 48 | BY36: =(BY26+BY27+BY28+BY29)*8 -> 48 | BZ36: =(BZ26+BZ27+BZ28+BZ29)*8 -> 48 | CA36: =(CA26+CA27+CA28+CA29)*8 -> 48 | CB36: =(CB26+CB27+CB28+CB29)*8 -> 48 | CE36: =(CE26+CE27+CE28+CE29)*8 -> 40 | CF36: =(CF26+CF27+CF28+CF29)*8 -> 40 | CG36: =(CG26+CG27+CG28+CG29)*8 -> 32 | CH36: =(CH26+CH27+CH28+CH29)*8 -> 32 | CI36: =(CI26+CI27+CI28+CI29)*8 -> 32 | CL36: =(CL26+CL27+CL28+CL29)*8 -> 40 | CM36: =(CM26+CM27+CM28+CM29)*8 -> 40 | CN36: =(CN26+CN27+CN28+CN29)*8 -> 32 | CO36: =(CO26+CO27+CO28+CO29)*8 -> 32 | CP36: =(CP26+CP27+CP28+CP29)*8 -> 32 | CS36: =(CS26+CS27+CS28+CS29)*8 -> 48 | CT36: =(CT26+CT27+CT28+CT29)*8 -> 48 | CU36: =(CU26+CU27+CU28+CU29)*8 -> 48 | CV36: =(CV26+CV27+CV28+CV29)*8 -> 48 | CW36: =(CW26+CW27+CW28+CW29)*8 -> 48 | CZ36: =(CZ26+CZ27+CZ28+CZ29)*8 -> 40 | DA36: =(DA26+DA27+DA28+DA29)*8 -> 40 | DB36: =(DB26+DB27+DB28+DB29)*8 -> 40 | DC36: =(DC26+DC27+DC28+DC29)*8 -> 40 | DD36: =(DD26+DD27+DD28+DD29)*8 -> 40 | DG36: =(DG26+DG27+DG28+DG29)*8 -> 48 | DH36: =(DH26+DH27+DH28+DH29)*8 -> 48 | DI36: =(DI26+DI27+DI28+DI29)*8 -> 48 | DJ36: =(DJ26+DJ27+DJ28+DJ29)*8 -> 48 | DK36: =(DK26+DK27+DK28+DK29)*8 -> 48 | DN36: =(DN26+DN27+DN28+DN29)*8 -> 40 | DO36: =(DO26+DO27+DO28+DO29)*8 -> 40 | DP36: =(DP26+DP27+DP28+DP29)*8 -> 40 | DQ36: =(DQ26+DQ27+DQ28+DQ29)*8 -> 40 | DR36: =(DR26+DR27+DR28+DR29)*8 -> 40 | DU36: =(DU26+DU27+DU28+DU29)*8 -> 40 | DV36: =(DV26+DV27+DV28+DV29)*8 -> 40 | DW36: =(DW26+DW27+DW28+DW29)*8 -> 40 | DX36: =(DX26+DX27+DX28+DX29)*8 -> 40 | DY36: =(DY26+DY27+DY28+DY29)*8 -> 40 | EB36: =(EB26+EB27+EB28+EB29)*8 -> 32 | EC36: =(EC26+EC27+EC28+EC29)*8 -> 32 | ED36: =(ED26+ED27+ED28+ED29)*8 -> 32 | EE36: =(EE26+EE27+EE28+EE29)*8 -> 32 | EF36: =(EF26+EF27+EF28+EF29)*8 -> 32 | EI36: =(EI26+EI27+EI28+EI29)*8 -> 40 | EJ36: =(EJ26+EJ27+EJ28+EJ29)*8 -> 40 | EK36: =(EK26+EK27+EK28+EK29)*8 -> 40 | EL36: =(EL26+EL27+EL28+EL29)*8 -> 0 | EM36: =(EM26+EM27+EM28+EM29)*8 -> 40 | EP36: 40 | EQ36: =(EQ26+EQ27+EQ28+EQ29)*8 -> 40 | ER36: =(ER26+ER27+ER28+ER29)*8 -> 40 | ES36: =(ES26+ES27+ES28+ES29)*8 -> 40 | ET36: =(ET26+ET27+ET28+ET29)*8 -> 40 | EW36: 0 | EX36: =(EX26+EX27+EX28+EX29)*8 -> 40 | EY36: =(EY26+EY27+EY28+EY29)*8 -> 40 | EZ36: =(EZ26+EZ27+EZ28+EZ29)*8 -> 40 | FA36: =(FA26+FA27+FA28+FA29)*8 -> 40 | FD36: =(FD26+FD27+FD28+FD29)*8 -> 0 | FE36: 0 | FF36: 0 | FG36: 0 | FH36: 0 | FK36: =(FK26+FK27+FK28+FK29)*8 -> 40 | FL36: =(FL26+FL27+FL28+FL29)*8 -> 40 | FM36: =(FM26+FM27+FM28+FM29)*8 -> 40 | FN36: =(FN26+FN27+FN28+FN29)*8 -> 40 | FO36: =(FO26+FO27+FO28+FO29)*8 -> 40 | FR36: =(FR26+FR27+FR28+FR29)*8 -> 40 | FS36: =(FS26+FS27+FS28+FS29)*8 -> 40 | FT36: =(FT26+FT27+FT28+FT29)*8 -> 32 | FU36: =(FU26+FU27+FU28+FU29)*8 -> 32 | FV36: =(FV26+FV27+FV28+FV29)*8 -> 40 | FY36: =(FY26+FY27+FY28+FY29)*8 -> 40 | FZ36: =(FZ26+FZ27+FZ28+FZ29)*8 -> 40 | GA36: =(GA26+GA27+GA28+GA29)*8 -> 40 | GB36: =(GB26+GB27+GB28+GB29)*8 -> 32 | GC36: =(GC26+GC27+GC28+GC29)*8 -> 32 | GF36: =(GF26+GF27+GF28+GF29)*8 -> 40 | GG36: =(GG26+GG27+GG28+GG29)*8 -> 40 | GH36: =(GH26+GH27+GH28+GH29)*8 -> 40 | GI36: =(GI26+GI27+GI28+GI29)*8 -> 40 | GJ36: =(GJ26+GJ27+GJ28+GJ29)*8 -> 40 | GM36: =(GM26+GM27+GM28+GM29)*8 -> 32 | GN36: =(GN26+GN27+GN28+GN29)*8 -> 32 | GO36: =(GO26+GO27+GO28+GO29)*8 -> 32 | GP36: =(GP26+GP27+GP28+GP29)*8 -> 40 | GQ36: =(GQ26+GQ27+GQ28+GQ29)*8 -> 40 | GT36: =(GT26+GT27+GT28+GT29)*8 -> 40 | GU36: =(GU26+GU27+GU28+GU29)*8 -> 40 | GV36: =(GV26+GV27+GV28+GV29)*8 -> 40 | GW36: =(GW26+GW27+GW28+GW29)*8 -> 40 | GX36: =(GX26+GX27+GX28+GX29)*8 -> 40 | HA36: =(HA26+HA27+HA28+HA29)*8 -> 40 | HB36: =(HB26+HB27+HB28+HB29)*8 -> 40 | HC36: =(HC26+HC27+HC28+HC29)*8 -> 40 | HD36: =(HD26+HD27+HD28+HD29)*8 -> 40 | HE36: =(HE26+HE27+HE28+HE29)*8 -> 40 | HH36: =(HH26+HH27+HH28+HH29)*8 -> 40 | HI36: =(HI26+HI27+HI28+HI29)*8 -> 40 | HJ36: =(HJ26+HJ27+HJ28+HJ29)*8 -> 40 | HK36: =(HK26+HK27+HK28+HK29)*8 -> 40 | HL36: =(HL26+HL27+HL28+HL29)*8 -> 40 | HO36: =(HO26+HO27+HO28+HO29)*8 -> 40 | HP36: =(HP26+HP27+HP28+HP29)*8 -> 40 | HQ36: =(HQ26+HQ27+HQ28+HQ29)*8 -> 40 | HR36: =(HR26+HR27+HR28+HR29)*8 -> 40 | HS36: =(HS26+HS27+HS28+HS29)*8 -> 40 | HV36: =(HV26+HV27+HV28+HV29)*8 -> 0 | HW36: =(HW26+HW27+HW28+HW29)*8 -> 0 | HX36: =(HX26+HX27+HX28+HX29)*8 -> 0 | HY36: =(HY26+HY27+HY28+HY29)*8 -> 0 | HZ36: =(HZ26+HZ27+HZ28+HZ29)*8 -> 0 | IC36: =(IC26+IC27+IC28+IC29)*8 -> 40 | ID36: =(ID26+ID27+ID28+ID29)*8 -> 40 | IE36: =(IE26+IE27+IE28+IE29)*8 -> 40 | IF36: =(IF26+IF27+IF28+IF29)*8 -> 40 | IG36: =(IG26+IG27+IG28+IG29)*8 -> 32 | IJ36: =(IJ26+IJ27+IJ28+IJ29)*8 -> 40 | IK36: =(IK26+IK27+IK28+IK29)*8 -> 40 | IL36: =(IL26+IL27+IL28+IL29)*8 -> 32 | IM36: =(IM26+IM27+IM28+IM29)*8 -> 32 | IN36: =(IN26+IN27+IN28+IN29)*8 -> 0 | IQ36: =(IQ26+IQ27+IQ28+IQ29)*8 -> 40 | IR36: =(IR26+IR27+IR28+IR29)*8 -> 40 | IS36: =(IS26+IS27+IS28+IS29)*8 -> 40 | IT36: =(IT26+IT27+IT28+IT29)*8 -> 40 | IU36: =(IU26+IU27+IU28+IU29)*8 -> 40 | IX36: =(IX26+IX27+IX28+IX29)*8 -> 40 | IY36: =(IY26+IY27+IY28+IY29)*8 -> 32 | IZ36: =(IZ26+IZ27+IZ28+IZ29)*8 -> 32 | JA36: =(JA26+JA27+JA28+JA29)*8 -> 32 | JB36: =(JB26+JB27+JB28+JB29)*8 -> 32 | JE36: =(JE26+JE27+JE28+JE29)*8 -> 40 | JF36: =(JF26+JF27+JF28+JF29)*8 -> 40 | JG36: =(JG26+JG27+JG28+JG29)*8 -> 40 | JH36: =(JH26+JH27+JH28+JH29)*8 -> 40 | JI36: =(JI26+JI27+JI28+JI29)*8 -> 40 | JL36: =(JL26+JL27+JL28+JL29)*8 -> 32 | JM36: =(JM26+JM27+JM28+JM29)*8 -> 32 | JN36: =(JN26+JN27+JN28+JN29)*8 -> 32 | JO36: =(JO26+JO27+JO28+JO29)*8 -> 32 | JP36: =(JP26+JP27+JP28+JP29)*8 -> 32 | JS36: =(JS26+JS27+JS28+JS29)*8 -> 32 | JT36: =(JT26+JT27+JT28+JT29)*8 -> 0 | JU36: =(JU26+JU27+JU28+JU29)*8 -> 40 | JV36: =(JV26+JV27+JV28+JV29)*8 -> 40 | JW36: =(JW26+JW27+JW28+JW29)*8 -> 40 | JZ36: =(JZ26+JZ27+JZ28+JZ29)*8 -> 32 | KA36: =(KA26+KA27+KA28+KA29)*8 -> 40 | KB36: =(KB26+KB27+KB28+KB29)*8 -> 40 | KC36: =(KC26+KC27+KC28+KC29)*8 -> 40 | KD36: =(KD26+KD27+KD28+KD29)*8 -> 40 | KG36: =(KG26+KG27+KG28+KG29)*8 -> 32 | KH36: =(KH26+KH27+KH28+KH29)*8 -> 32 | KI36: =(KI26+KI27+KI28+KI29)*8 -> 32 | KJ36: =(KJ26+KJ27+KJ28+KJ29)*8 -> 32 | KK36: =(KK26+KK27+KK28+KK29)*8 -> 32 | KN36: =(KN26+KN27+KN28+KN29)*8 -> 32 | KO36: =(KO26+KO27+KO28+KO29)*8 -> 32 | KP36: =(KP26+KP27+KP28+KP29)*8 -> 32 | KQ36: =(KQ26+KQ27+KQ28+KQ29)*8 -> 32 | KR36: =(KR26+KR27+KR28+KR29)*8 -> 32 | KU36: =(KU26+KU27+KU28+KU29)*8 -> 40 | KV36: =(KV26+KV27+KV28+KV29)*8 -> 40 | KW36: =(KW26+KW27+KW28+KW29)*8 -> 40 | KX36: =(KX26+KX27+KX28+KX29)*8 -> 40 | KY36: =(KY26+KY27+KY28+KY29)*8 -> 40 | LB36: =(LB26+LB27+LB28+LB29)*8 -> 40 | LC36: =(LC26+LC27+LC28+LC29)*8 -> 40 | LD36: =(LD26+LD27+LD28+LD29)*8 -> 40 | LE36: =(LE26+LE27+LE28+LE29)*8 -> 40 | LF36: =(LF26+LF27+LF28+LF29)*8 -> 40 | LI36: =(LI26+LI27+LI28+LI29)*8 -> 40 | LJ36: =(LJ26+LJ27+LJ28+LJ29)*8 -> 40 | LK36: =(LK26+LK27+LK28+LK29)*8 -> 40 | LL36: =(LL26+LL27+LL28+LL29)*8 -> 40 | LM36: =(LM26+LM27+LM28+LM29)*8 -> 40 | LP36: =(LP26+LP27+LP28+LP29)*8 -> 40 | LQ36: =(LQ26+LQ27+LQ28+LQ29)*8 -> 40 | LR36: =(LR26+LR27+LR28+LR29)*8 -> 32 | LS36: =(LS26+LS27+LS28+LS29)*8 -> 32 | LT36: =(LT26+LT27+LT28+LT29)*8 -> 32 | LW36: =(LW26+LW27+LW28+LW29)*8 -> 32 | LX36: =(LX26+LX27+LX28+LX29)*8 -> 24 | LY36: =(LY26+LY27+LY28+LY29)*8 -> 24 | LZ36: =(LZ26+LZ27+LZ28+LZ29)*8 -> 24 | MA36: =(MA26+MA27+MA28+MA29)*8 -> 24 | MD36: =(MD26+MD27+MD28+MD29)*8 -> 32 | ME36: =(ME26+ME27+ME28+ME29)*8 -> 40 | MF36: =(MF26+MF27+MF28+MF29)*8 -> 40 | MG36: =(MG26+MG27+MG28+MG29)*8 -> 40 | MH36: =(MH26+MH27+MH28+MH29)*8 -> 40 | MK36: =(MK26+MK27+MK28+MK29)*8 -> 40 | ML36: =(ML26+ML27+ML28+ML29)*8 -> 40 | MM36: =(MM26+MM27+MM28+MM29)*8 -> 40 | MN36: =(MN26+MN27+MN28+MN29)*8 -> 32 | MO36: =(MO26+MO27+MO28+MO29)*8 -> 24 | MR36: =(MR26+MR27+MR28+MR29)*8 -> 24 | MS36: =(MS26+MS27+MS28+MS29)*8 -> 16 | MT36: =(MT26+MT27+MT28+MT29)*8 -> 16 | MU36: =(MU26+MU27+MU28+MU29)*8 -> 16 | MV36: =(MV26+MV27+MV28+MV29)*8 -> 16 | MY36: =(MY26+MY27+MY28+MY29)*8 -> 0 | MZ36: =(MZ26+MZ27+MZ28+MZ29)*8 -> 0 | NA36: =(NA26+NA27+NA28+NA29)*8 -> 0 | NB36: =(NB26+NB27+NB28+NB29)*8 -> 0 | NC36: =(NC26+NC27+NC28+NC29)*8 -> 0 | NF36: ENDE
A37: Versandhalle Arbeitszeit | B37: Vorzeitiges Arbeitsende Versandhalle | D37: Hours | F37: 0 | G37: 0 | H37: 0 | I37: 0 | M37: 0 | N37: 0 | O37: 0 | P37: 0 | Q37: 0 | T37: 0 | U37: 0 | V37: 0 | W37: 0 | X37: 0 | AA37: 0 | AB37: 0 | AC37: 0 | AD37: 0 | AE37: 0 | AH37: 0 | AI37: 0 | AJ37: 0 | AK37: 0 | AL37: 0 | AO37: 2.5 | AP37: 0 | AQ37: 0 | AR37: 0 | AS37: 0 | AV37: 0 | AW37: 0 | AX37: 0 | AY37: 0 | AZ37: 0 | BC37: 0 | BD37: 0 | BE37: 0 | BF37: 0 | BG37: 0 | BJ37: 0 | BK37: 0 | BL37: 0 | BM37: 0 | BN37: 0 | BQ37: 0 | BR37: 0 | BS37: 0 | BT37: 0 | BU37: 0 | BX37: 0 | BY37: 0 | BZ37: 0 | CA37: 0 | CB37: 0 | CE37: 0 | CF37: 0 | CG37: 0 | CH37: 0 | CI37: 0 | CL37: 0 | CM37: 0 | CN37: 0 | CO37: 0 | CP37: 0 | CS37: 0 | CT37: 0 | CU37: 0 | CV37: 2 | CW37: 0 | CZ37: 0 | DA37: 0 | DB37: 0 | DC37: 0 | DD37: 0 | DG37: 0 | DH37: 0 | DI37: 0 | DJ37: 0 | DK37: 0 | DN37: 0 | DO37: 0 | DP37: 0 | DQ37: 0 | DR37: 0 | DU37: 0 | DV37: 0 | DW37: 0 | DX37: 0 | DY37: 0 | EB37: 0 | EC37: 0 | ED37: 0 | EE37: 0 | EF37: 1.5 | EI37: 0 | EJ37: 0 | EL37: 0 | EM37: 3 | EP37: 0 | EQ37: 0 | ER37: 0 | ES37: 0 | ET37: 0 | EW37: 0 | EX37: 0 | EY37: 0 | EZ37: 0 | FA37: 2.5 | FD37: 0 | FE37: 0 | FF37: 0 | FG37: 0 | FH37: 0 | FK37: 0 | FL37: 0 | FM37: 0 | FN37: 0 | FO37: 0.5 | FR37: 0 | FS37: 0 | FT37: 0 | FU37: 0 | FV37: 0 | FY37: 0 | FZ37: 0 | GA37: 3 | GB37: 0 | GC37: 2 | GF37: 0 | GG37: 0 | GH37: 0 | GI37: 0 | GJ37: 1.5 | GM37: 0 | GN37: 0 | GO37: 1 | GP37: 0 | GQ37: 4 | GT37: 0 | GU37: 0 | GV37: 0 | GW37: 0 | GX37: 0 | HA37: 0 | HB37: 0 | HC37: 0 | HD37: 0 | HE37: 0 | HH37: 0 | HI37: 0 | HJ37: 0 | HK37: 0 | HL37: 4 | HO37: 0 | HP37: 0 | HQ37: 0 | HR37: 0 | HS37: 3 | HV37: 0 | HW37: 0 | HX37: 0 | HY37: 0 | HZ37: 0 | IC37: 0 | ID37: 0 | IE37: 0 | IF37: 0 | IG37: 3 | IJ37: 2 | IK37: 0 | IL37: 0 | IM37: 0 | IN37: 0 | IQ37: 0 | IR37: 0 | IS37: 0 | IT37: 0 | IU37: 0 | IX37: 0 | IY37: 0 | IZ37: 0 | JA37: 0 | JB37: 0 | JE37: 0 | JF37: 0 | JG37: 0 | JH37: 0 | JI37: 0 | JL37: 0 | JM37: 0 | JN37: 0 | JO37: 0 | JP37: 0 | JS37: 0 | JT37: 0 | JU37: 0 | JV37: 0 | JW37: 0 | JZ37: 0 | KA37: 0 | KB37: 0 | KC37: 1 | KD37: 0 | KG37: 0 | KH37: 0 | KI37: 0 | KJ37: 0 | KK37: 0 | KN37: 0 | KO37: 0 | KP37: 0 | KQ37: 0 | KR37: 0 | KU37: 0 | KV37: 0 | KW37: 0 | KX37: 0 | KY37: 0 | LB37: 0 | LC37: 0 | LD37: 0 | LE37: 0 | LF37: 0 | LI37: 0 | LJ37: 0 | LK37: 0 | LL37: 0 | LM37: 0 | LP37: 0 | LQ37: 0 | LR37: 0 | LS37: 0 | LT37: 0 | LW37: 0 | LX37: 0 | LY37: 0 | LZ37: 0 | MA37: 2 | MD37: 0 | ME37: 0 | MF37: 0 | MG37: 0 | MH37: 0 | MK37: 0 | ML37: 0 | MM37: 7 | MN37: 0 | MO37: 16 | MR37: 0 | NF37: ENDE
